Workbook

Sheet taXel全体
A1: 全社PL | J1: =IFERROR(I5/E5,"-") -> 21.732568 | K1: =IF(K5>0,K5/J5,"-") -> - | L1: =IF(L5>0,L5/K5,"-") -> - | M1: =IF(M5>0,M5/L5,"-") -> - | N1: =IF(N5>0,N5/M5,"-") -> -
E2: Y1 | F2: Y2 | G2: Y3 | H2: Y4 | I2: Y5 | J2: 5カ年 | P2: 実績 | Q2: 実績 | R2: 実績 | S2: 実績 | T2: 実績 | U2: 実績 | V2: 実績 | W2: 実績 | X2: 実績 | Y2: 実績 | Z2: 実績 | AA2: 実績 | AB2: M1 | AC2: M2 | AD2: M3 | AE2: M4 | AF2: M5 | AG2: M6 | AH2: M7 | AI2: M8 | AJ2: M9 | AK2: M10 | AL2: M11 | AM2: M12 | AN2: M13 | AO2: M1４ | AP2: M15 | AQ2: M16 | AR2: M17 | AS2: M18 | AT2: M19 | AU2: M20 | AV2: M21 | AW2: M22 | AX2: M23 | AY2: M24 | AZ2: M25 | BA2: M26 | BB2: M27 | BC2: M28 | BD2: M29 | BE2: M30 | BF2: M31 | BG2: M32 | BH2: M33 | BI2: M34 | BJ2: M35 | BK2: M36 | BL2: M37 | BM2: M38 | BN2: M39 | BO2: M40 | BP2: M41 | BQ2: M42 | BR2: M43 | BS2: M44 | BT2: M45 | BU2: M46 | BV2: M47 | BW2: M48 | BX2: M49 | BY2: M50 | BZ2: M51 | CA2: M52 | CB2: M53 | CC2: M54 | CD2: M55 | CE2: M56 | CF2: M57 | CG2: M58 | CH2: M59 | CI2: M60
E3: 計画 | F3: 計画 | G3: 計画 | H3: 計画 | I3: 計画 | J3: 計画 | K3: 計画 | L3: 計画 | M3: 計画 | N3: 計画 | P3: 22年6月期 | Q3: 22年6月期 | R3: 22年6月期 | S3: 22年6月期 | T3: 22年6月期 | U3: 22年6月期 | V3: 22年6月期 | W3: 22年6月期 | X3: 22年6月期 | Y3: 22年6月期 | Z3: 22年6月期 | AA3: 22年6月期 | AB3: 23年6月期 | AC3: 23年6月期 | AD3: 23年6月期 | AE3: 23年6月期 | AF3: 23年6月期 | AG3: 23年6月期 | AH3: 23年6月期 | AI3: 23年6月期 | AJ3: 23年6月期 | AK3: 23年6月期 | AL3: 23年6月期 | AM3: 23年6月期 | AN3: 24年6月期 | AO3: 24年6月期 | AP3: 24年6月期 | AQ3: 24年6月期 | AR3: 24年6月期 | AS3: 24年6月期 | AT3: 24年6月期 | AU3: 24年6月期 | AV3: 24年6月期 | AW3: 24年6月期 | AX3: 24年6月期 | AY3: 24年6月期 | AZ3: 25年6月期 | BA3: 25年6月期 | BB3: 25年6月期 | BC3: 25年6月期 | BD3: 25年6月期 | BE3: 25年6月期 | BF3: 25年6月期 | BG3: 25年6月期 | BH3: 25年6月期 | BI3: 25年6月期 | BJ3: 25年6月期 | BK3: 25年6月期 | BL3: 26年6月期 | BM3: 26年6月期 | BN3: 26年6月期 | BO3: 26年6月期 | BP3: 26年6月期 | BQ3: 26年6月期 | BR3: 26年6月期 | BS3: 26年6月期 | BT3: 26年6月期 | BU3: 26年6月期 | BV3: 26年6月期 | BW3: 26年6月期 | BX3: 27年6月期 | BY3: 27年6月期 | BZ3: 27年6月期 | CA3: 27年6月期 | CB3: 27年6月期 | CC3: 27年6月期 | CD3: 27年6月期 | CE3: 27年6月期 | CF3: 27年6月期 | CG3: 27年6月期 | CH3: 27年6月期 | CI3: 27年6月期
C4: Ref. | E4: =AB3 -> 23年6月期 | F4: =AN3 -> 24年6月期 | G4: =AZ3 -> 25年6月期 | H4: =BL3 -> 26年6月期 | I4: =BX3 -> 27年6月期 | J4: 5カ年合計 | K4: 29年6月期 | L4: 30年6月期 | M4: 31年6月期 | N4: 32年6月期 | P4: 21年7月 | Q4: 21年8月 | R4: 21年9月 | S4: 21年10月 | T4: 21年11月 | U4: 21年12月 | V4: 22年1月 | W4: 22年2月 | X4: 22年3月 | Y4: 22年4月 | Z4: 22年5月 | AA4: 22年6月 | AB4: 22年7月 | AC4: 22年8月 | AD4: 22年9月 | AE4: 22年10月 | AF4: 22年11月 | AG4: 22年12月 | AH4: 23年1月 | AI4: 23年2月 | AJ4: 23年3月 | AK4: 23年4月 | AL4: 23年5月 | AM4: 23年6月 | AN4: 23年7月 | AO4: 23年8月 | AP4: 23年9月 | AQ4: 23年10月 | AR4: 23年11月 | AS4: 23年12月 | AT4: 24年1月 | AU4: 24年2月 | AV4: 24年3月 | AW4: 24年4月 | AX4: 24年5月 | AY4: 24年6月 | AZ4: 24年7月 | BA4: 24年8月 | BB4: 24年9月 | BC4: 24年10月 | BD4: 24年11月 | BE4: 24年12月 | BF4: 25年1月 | BG4: 25年2月 | BH4: 25年3月 | BI4: 25年4月 | BJ4: 25年5月 | BK4: 25年6月 | BL4: 25年7月 | BM4: 25年8月 | BN4: 25年9月 | BO4: 25年10月 | BP4: 25年11月 | BQ4: 25年12月 | BR4: 26年1月 | BS4: 26年2月 | BT4: 26年3月 | BU4: 26年4月 | BV4: 26年5月 | BW4: 26年6月 | BX4: 26年7月 | BY4: 26年8月 | BZ4: 26年9月 | CA4: 26年10月 | CB4: 26年11月 | CC4: 26年12月 | CD4: 27年1月 | CE4: 27年2月 | CF4: 27年3月 | CG4: 27年4月 | CH4: 27年5月 | CI4: 27年6月
A5: 売上高 | C5: TaXel 全体 | D5: 円 | E5: =SUM(E6:E12) -> 23100792 | F5: =SUM(F6:F12) -> 1.0759832e+08 | G5: =SUM(G6:G12) -> 2.17985e+08 | H5: =SUM(H6:H12) -> 3.470612e+08 | I5: =SUM(I6:I12) -> 5.0203953e+08 | J5: =SUM(E5:I5) -> 1.1977848e+09 | K5: =SUMIF($P$3:$CN$3,K$4,$P5:$CN5) -> 0 | L5: =SUMIF($P$3:$CN$3,L$4,$P5:$CN5) -> 0 | M5: =SUMIF($P$3:$CN$3,M$4,$P5:$CN5) -> 0 | N5: =SUMIF($P$3:$CN$3,N$4,$P5:$CN5) -> 0 | P5: =SUM(P6) -> 0 | Q5: =SUM(Q6) -> 0 | R5: =SUM(R6) -> 0 | S5: =SUM(S6) -> 0 | T5: =SUM(T6) -> 0 | U5: =SUM(U6) -> 0 | V5: =SUM(V6) -> 0 | W5: =SUM(W6) -> 0 | ... AA5: =SUM(AA6) -> 0 | AB5: =SUM(AB6:AB12) -> 0 | AC5: =SUM(AC6:AC12) -> 56598.421 | AD5: =SUM(AD6:AD12) -> 331721.39 | AE5: =SUM(AE6:AE12) -> 601899.77 | AF5: =SUM(AF6:AF12) -> 860371.3 | AG5: =SUM(AG6:AG12) -> 1170767.7 | AH5: =SUM(AH6:AH12) -> 1805576 | AI5: =SUM(AI6:AI12) -> 2434908 | ... CI5: =SUM(CI6:CI12) -> 48484711
B6: SaaS事業 | C6: SaaS | E6: =SUMIF($AB$3:$CI$3,E$4,$AB6:$CI6) -> 13155039 | F6: =SUMIF($AB$3:$CI$3,F$4,$AB6:$CI6) -> 54970475 | G6: =SUMIF($AB$3:$CI$3,G$4,$AB6:$CI6) -> 1.1300102e+08 | H6: =SUMIF($AB$3:$CI$3,H$4,$AB6:$CI6) -> 1.8562995e+08 | I6: =SUMIF($AB$3:$CI$3,I$4,$AB6:$CI6) -> 2.7676127e+08 | J6: =SUM(E6:I6) -> 6.4351776e+08 | K6: =SUMIF($P$3:$CN$3,K$4,$P6:$CN6) -> 0 | L6: =SUMIF($P$3:$CN$3,L$4,$P6:$CN6) -> 0 | M6: =SUMIF($P$3:$CN$3,M$4,$P6:$CN6) -> 0 | N6: =SUMIF($P$3:$CN$3,N$4,$P6:$CN6) -> 0 | AB6: =SaaS!F5 -> 0 | AC6: =SaaS!G5 -> 42876.146 | AD6: =SaaS!H5 -> 256399.35 | AE6: =SaaS!I5 -> 465652.1 | AF6: =SaaS!J5 -> 670719.79 | AG6: =SaaS!K5 -> 914562.27 | AH6: =SaaS!L5 -> 1153527.9 | AI6: =SaaS!M5 -> 1387714.2 | ... CI6: =SaaS!BM5 -> 27073469
B7: コンサルティング事業 | C7: 事業・組織再生コンサル | E7: =SUMIF($AB$3:$CI$3,E$4,$AB7:$CI7) -> 6270000 | F7: =SUMIF($AB$3:$CI$3,F$4,$AB7:$CI7) -> 37950000 | G7: =SUMIF($AB$3:$CI$3,G$4,$AB7:$CI7) -> 75900000 | H7: =SUMIF($AB$3:$CI$3,H$4,$AB7:$CI7) -> 115170000 | I7: =SUMIF($AB$3:$CI$3,I$4,$AB7:$CI7) -> 157740000 | J7: =SUM(E7:I7) -> 393030000 | K7: =SUMIF($P$3:$CN$3,K$4,$P7:$CN7) -> 0 | L7: =SUMIF($P$3:$CN$3,L$4,$P7:$CN7) -> 0 | M7: =SUMIF($P$3:$CN$3,M$4,$P7:$CN7) -> 0 | N7: =SUMIF($P$3:$CN$3,N$4,$P7:$CN7) -> 0 | AB7: ='事業・組織再生コンサル'!F4 -> 0 | AC7: ='事業・組織再生コンサル'!G4 -> 0 | AD7: ='事業・組織再生コンサル'!H4 -> 0 | AE7: ='事業・組織再生コンサル'!I4 -> 0 | AF7: ='事業・組織再生コンサル'!J4 -> 0 | AG7: ='事業・組織再生コンサル'!K4 -> 0 | AH7: ='事業・組織再生コンサル'!L4 -> 330000 | AI7: ='事業・組織再生コンサル'!M4 -> 660000 | ... CI7: ='事業・組織再生コンサル'!BM4 -> 14850000
B8: 紹介事業 | C8: ビジとり | E8: =SUMIF($AB$3:$CI$3,E$4,$AB8:$CI8) -> 503095.67 | F8: =SUMIF($AB$3:$CI$3,F$4,$AB8:$CI8) -> 1927248.6 | G8: =SUMIF($AB$3:$CI$3,G$4,$AB8:$CI8) -> 3683882 | H8: =SUMIF($AB$3:$CI$3,H$4,$AB8:$CI8) -> 5663952.8 | I8: =SUMIF($AB$3:$CI$3,I$4,$AB8:$CI8) -> 8073839.8 | J8: =SUM(E8:I8) -> 19852019 | K8: =SUMIF($P$3:$CN$3,K$4,$P8:$CN8) -> 0 | L8: =SUMIF($P$3:$CN$3,L$4,$P8:$CN8) -> 0 | M8: =SUMIF($P$3:$CN$3,M$4,$P8:$CN8) -> 0 | N8: =SUMIF($P$3:$CN$3,N$4,$P8:$CN8) -> 0 | AB8: =ビジとり!F5 -> 0 | AC8: =ビジとり!G5 -> 1929.375 | AD8: =ビジとり!H5 -> 10572.975 | AE8: =ビジとり!I5 -> 19043.703 | AF8: =ビジとり!J5 -> 26380.329 | AG8: =ビジとり!K5 -> 35499.597 | AH8: =ビジとり!L5 -> 44436.48 | AI8: =ビジとり!M5 -> 53194.626 | ... CI8: =ビジとり!BM5 -> 778105.88
B9: 紹介事業 | C9: 支払い.com | E9: =SUMIF($AB$3:$CI$3,E$4,$AB9:$CI9) -> 1036460.2 | F9: =SUMIF($AB$3:$CI$3,F$4,$AB9:$CI9) -> 4331391.8 | G9: =SUMIF($AB$3:$CI$3,G$4,$AB9:$CI9) -> 8900813.2 | H9: =SUMIF($AB$3:$CI$3,H$4,$AB9:$CI9) -> 14619150 | I9: =SUMIF($AB$3:$CI$3,I$4,$AB9:$CI9) -> 21803150 | J9: =SUM(E9:I9) -> 50690966 | K9: =SUMIF($P$3:$CN$3,K$4,$P9:$CN9) -> 0 | L9: =SUMIF($P$3:$CN$3,L$4,$P9:$CN9) -> 0 | M9: =SUMIF($P$3:$CN$3,M$4,$P9:$CN9) -> 0 | N9: =SUMIF($P$3:$CN$3,N$4,$P9:$CN9) -> 0 | AB9: ='支払い.com'!F5 -> 0 | AC9: ='支払い.com'!G5 -> 3748.5 | AD9: ='支払い.com'!H5 -> 20616.75 | AE9: ='支払い.com'!I5 -> 37485 | AF9: ='支払い.com'!J5 -> 52479 | AG9: ='支払い.com'!K5 -> 71221.5 | AH9: ='支払い.com'!L5 -> 89964 | AI9: ='支払い.com'!M5 -> 108706.5 | ... CI9: ='支払い.com'!BM5 -> 2132896.5
B10: 仲介事業 | C10: プライペートバンク仲介 | E10: =SUMIF($AB$3:$CI$3,E$4,$AB10:$CI10) -> 473115.28 | F10: =SUMIF($AB$3:$CI$3,F$4,$AB10:$CI10) -> 1812400.3 | G10: =SUMIF($AB$3:$CI$3,G$4,$AB10:$CI10) -> 3464352.7 | H10: =SUMIF($AB$3:$CI$3,H$4,$AB10:$CI10) -> 5326427.4 | I10: =SUMIF($AB$3:$CI$3,I$4,$AB10:$CI10) -> 7592704.8 | J10: =SUM(E10:I10) -> 18669001 | K10: =SUMIF($P$3:$CN$3,K$4,$P10:$CN10) -> 0 | L10: =SUMIF($P$3:$CN$3,L$4,$P10:$CN10) -> 0 | M10: =SUMIF($P$3:$CN$3,M$4,$P10:$CN10) -> 0 | N10: =SUMIF($P$3:$CN$3,N$4,$P10:$CN10) -> 0 | AB10: =PB!F5 -> 0 | AC10: =PB!G5 -> 1814.4 | AD10: =PB!H5 -> 9942.912 | AE10: =PB!I5 -> 17908.854 | AF10: =PB!J5 -> 24808.277 | AG10: =PB!K5 -> 33384.111 | AH10: =PB!L5 -> 41788.429 | AI10: =PB!M5 -> 50024.66 | ... CI10: =PB!BM5 -> 731737.12
B11: 紹介事業 | C11: 電力コスト削減 | E11: =SUMIF($AB$3:$CI$3,E$4,$AB11:$CI11) -> 677425 | F11: =SUMIF($AB$3:$CI$3,F$4,$AB11:$CI11) -> 2830975 | G11: =SUMIF($AB$3:$CI$3,G$4,$AB11:$CI11) -> 5817525 | H11: =SUMIF($AB$3:$CI$3,H$4,$AB11:$CI11) -> 9555000 | I11: =SUMIF($AB$3:$CI$3,I$4,$AB11:$CI11) -> 14250425 | J11: =SUM(E11:I11) -> 33131350 | K11: =SUMIF($P$3:$CN$3,K$4,$P11:$CN11) -> 0 | L11: =SUMIF($P$3:$CN$3,L$4,$P11:$CN11) -> 0 | M11: =SUMIF($P$3:$CN$3,M$4,$P11:$CN11) -> 0 | N11: =SUMIF($P$3:$CN$3,N$4,$P11:$CN11) -> 0 | AB11: =電力コスト削減!F5 -> 0 | AC11: =電力コスト削減!G5 -> 2450 | AD11: =電力コスト削減!H5 -> 13475 | AE11: =電力コスト削減!I5 -> 24500 | AF11: =電力コスト削減!J5 -> 34300 | AG11: =電力コスト削減!K5 -> 46550 | AH11: =電力コスト削減!L5 -> 58800 | AI11: =電力コスト削減!M5 -> 71050 | ... CI11: =電力コスト削減!BM5 -> 1394050
B12: 紹介事業 | C12: 売掛金 | E12: =SUMIF($AB$3:$CI$3,E$4,$AB12:$CI12) -> 985656.83 | F12: =SUMIF($AB$3:$CI$3,F$4,$AB12:$CI12) -> 3775834 | G12: =SUMIF($AB$3:$CI$3,G$4,$AB12:$CI12) -> 7217401.4 | H12: =SUMIF($AB$3:$CI$3,H$4,$AB12:$CI12) -> 11096724 | I12: =SUMIF($AB$3:$CI$3,I$4,$AB12:$CI12) -> 15818135 | J12: =SUM(E12:I12) -> 38893751 | K12: =SUMIF($P$3:$CN$3,K$4,$P12:$CN12) -> 0 | L12: =SUMIF($P$3:$CN$3,L$4,$P12:$CN12) -> 0 | M12: =SUMIF($P$3:$CN$3,M$4,$P12:$CN12) -> 0 | N12: =SUMIF($P$3:$CN$3,N$4,$P12:$CN12) -> 0 | AB12: =' 売掛保証（保証型ファクタリング'!F5 -> 0 | AC12: =' 売掛保証（保証型ファクタリング'!G5 -> 3780 | AD12: =' 売掛保証（保証型ファクタリング'!H5 -> 20714.4 | AE12: =' 売掛保証（保証型ファクタリング'!I5 -> 37310.112 | AF12: =' 売掛保証（保証型ファクタリング'!J5 -> 51683.91 | AG12: =' 売掛保証（保証型ファクタリング'!K5 -> 69550.232 | AH12: =' 売掛保証（保証型ファクタリング'!L5 -> 87059.227 | AI12: =' 売掛保証（保証型ファクタリング'!M5 -> 104218.04 | ... CI12: =' 売掛保証（保証型ファクタリング'!BM5 -> 1524452.3
C13: 前期比 | D13: ％ | F13: =IF(E5>0,(F5-E5)/E5,"-") -> 3.6577764 | G13: =IF(F5>0,(G5-F5)/F5,"-") -> 1.0259144 | H13: =IF(G5>0,(H5-G5)/G5,"-") -> 0.59213344 | I13: =IF(H5>0,(I5-H5)/H5,"-") -> 0.44654465 | J13: =IFERROR((I5/E5)^(1/4)-1,"-") -> 1.1591249 | K13: =IF(K5>0,(K5-J5)/J5,"-") -> - | L13: =IF(L5>0,(L5-K5)/K5,"-") -> - | M13: =IF(M5>0,(M5-L5)/L5,"-") -> - | N13: =IF(N5>0,(N5-M5)/M5,"-") -> -
A14: 売上原価 | C14: COGS合計 | D14: 円 | E14: =SUMIF($AB$3:$CI$3,E$4,$AB14:$CI14) -> 1950363.2 | F14: =SUMIF($AB$3:$CI$3,F$4,$AB14:$CI14) -> 8004320.5 | G14: =SUMIF($AB$3:$CI$3,G$4,$AB14:$CI14) -> 16231490 | H14: =SUMIF($AB$3:$CI$3,H$4,$AB14:$CI14) -> 26316703 | I14: =SUMIF($AB$3:$CI$3,I$4,$AB14:$CI14) -> 39109407 | J14: =SUM(E14:I14) -> 91612284 | K14: =SUMIF($P$3:$CN$3,K$4,$P14:$CN14) -> 0 | L14: =SUMIF($P$3:$CN$3,L$4,$P14:$CN14) -> 0 | M14: =SUMIF($P$3:$CN$3,M$4,$P14:$CN14) -> 0 | N14: =SUMIF($P$3:$CN$3,N$4,$P14:$CN14) -> 0 | AB14: =SUM(AB17:AB20) -> 50000 | AC14: =SUM(AC17:AC20) -> 53343.541 | AD14: =SUM(AD17:AD20) -> 69994.377 | AE14: =SUM(AE17:AE20) -> 86312.196 | AF14: =SUM(AF17:AF20) -> 104555.91 | AG14: =SUM(AG17:AG20) -> 134719.72 | AH14: =SUM(AH17:AH20) -> 163945.8 | AI14: =SUM(AI17:AI20) -> 192269.62 | ... CI14: =SUM(CI17:CI20) -> 3652753.3
C15: AIレポート原価（円/社・月） | E15: =SUMIF($AB$3:$CI$3,E$4,$AB15:$CI15)/12 -> 150 | F15: =SUMIF($AB$3:$CI$3,F$4,$AB15:$CI15)/12 -> 150 | G15: =SUMIF($AB$3:$CI$3,G$4,$AB15:$CI15)/12 -> 150 | H15: =SUMIF($AB$3:$CI$3,H$4,$AB15:$CI15)/12 -> 150 | I15: =SUMIF($AB$3:$CI$3,I$4,$AB15:$CI15)/12 -> 150 | J15: =AVERAGE(E15:I15) -> 150 | AB15: =費用予算!F25 -> 150 | AC15: =費用予算!G25 -> 150 | AD15: =費用予算!H25 -> 150 | AE15: =費用予算!I25 -> 150 | AF15: =費用予算!J25 -> 150 | AG15: =費用予算!K25 -> 150 | AH15: =費用予算!L25 -> 150 | AI15: =費用予算!M25 -> 150 | ... CI15: =費用予算!BM25 -> 150
C16: 稼働顧問先数 | E16: =SUMIF($AB$3:$CI$3,E$4,$AB16:$CI16)/12 -> 306.81487 | F16: =SUMIF($AB$3:$CI$3,F$4,$AB16:$CI16)/12 -> 1282.0759 | G16: =SUMIF($AB$3:$CI$3,G$4,$AB16:$CI16)/12 -> 2635.5219 | H16: =SUMIF($AB$3:$CI$3,H$4,$AB16:$CI16)/12 -> 4329.4458 | I16: =SUMIF($AB$3:$CI$3,I$4,$AB16:$CI16)/12 -> 6454.9009 | J16: =AVERAGE(E16:I16) -> 3001.7519 | AB16: =費用予算!F26 -> 0 | AC16: =費用予算!G26 -> 12 | AD16: =費用予算!H26 -> 71.76 | AE16: =費用予算!I26 -> 130.3248 | AF16: =費用予算!J26 -> 187.7183 | AG16: =費用予算!K26 -> 255.96394 | AH16: =費用予算!L26 -> 322.84466 | AI16: =費用予算!M26 -> 388.38777 | ... CI16: =費用予算!BM26 -> 7577.2114
C17: AI API費 | E17: =SUMIF($AB$3:$CI$3,E$4,$AB17:$CI17) -> 552266.76 | F17: =SUMIF($AB$3:$CI$3,F$4,$AB17:$CI17) -> 2307736.7 | G17: =SUMIF($AB$3:$CI$3,G$4,$AB17:$CI17) -> 4743939.4 | H17: =SUMIF($AB$3:$CI$3,H$4,$AB17:$CI17) -> 7793002.4 | I17: =SUMIF($AB$3:$CI$3,I$4,$AB17:$CI17) -> 11618822 | J17: =SUM(E17:I17) -> 27015767 | AB17: =費用予算!F27 -> 0 | AC17: =費用予算!G27 -> 1800 | AD17: =費用予算!H27 -> 10764 | AE17: =費用予算!I27 -> 19548.72 | AF17: =費用予算!J27 -> 28157.746 | AG17: =費用予算!K27 -> 38394.591 | AH17: =費用予算!L27 -> 48426.699 | AI17: =費用予算!M27 -> 58258.165 | ... CI17: =費用予算!BM27 -> 1136581.7
C18: サーバー・DB費 | E18: =SUMIF($AB$3:$CI$3,E$4,$AB18:$CI18) -> 600000 | F18: =SUMIF($AB$3:$CI$3,F$4,$AB18:$CI18) -> 1800000 | G18: =SUMIF($AB$3:$CI$3,G$4,$AB18:$CI18) -> 3600000 | H18: =SUMIF($AB$3:$CI$3,H$4,$AB18:$CI18) -> 6000000 | I18: =SUMIF($AB$3:$CI$3,I$4,$AB18:$CI18) -> 9600000 | J18: =SUM(E18:I18) -> 21600000 | K18: =SUMIF($P$3:$CN$3,K$4,$P18:$CN18) -> 0 | L18: =SUMIF($P$3:$CN$3,L$4,$P18:$CN18) -> 0 | M18: =SUMIF($P$3:$CN$3,M$4,$P18:$CN18) -> 0 | N18: =SUMIF($P$3:$CN$3,N$4,$P18:$CN18) -> 0 | AB18: =費用予算!F28 -> 50000 | AC18: =費用予算!G28 -> 50000 | AD18: =費用予算!H28 -> 50000 | AE18: =費用予算!I28 -> 50000 | AF18: =費用予算!J28 -> 50000 | AG18: =費用予算!K28 -> 50000 | AH18: =費用予算!L28 -> 50000 | AI18: =費用予算!M28 -> 50000 | ... CI18: =費用予算!BM28 -> 800000
C19: 決済手数料 | E19: =SUMIF($AB$3:$CI$3,E$4,$AB19:$CI19) -> 473581.4 | F19: =SUMIF($AB$3:$CI$3,F$4,$AB19:$CI19) -> 1978937.1 | G19: =SUMIF($AB$3:$CI$3,G$4,$AB19:$CI19) -> 4068036.8 | H19: =SUMIF($AB$3:$CI$3,H$4,$AB19:$CI19) -> 6682678.2 | I19: =SUMIF($AB$3:$CI$3,I$4,$AB19:$CI19) -> 9963405.8 | J19: =SUM(E19:I19) -> 23166639 | K19: =SUMIF($P$3:$CN$3,K$4,$P19:$CN19) -> 0 | L19: =SUMIF($P$3:$CN$3,L$4,$P19:$CN19) -> 0 | M19: =SUMIF($P$3:$CN$3,M$4,$P19:$CN19) -> 0 | N19: =SUMIF($P$3:$CN$3,N$4,$P19:$CN19) -> 0 | AB19: =費用予算!F29 -> 0 | AC19: =費用予算!G29 -> 1543.5413 | AD19: =費用予算!H29 -> 9230.3767 | AE19: =費用予算!I29 -> 16763.476 | AF19: =費用予算!J29 -> 24145.912 | AG19: =費用予算!K29 -> 32924.242 | AH19: =費用予算!L29 -> 41527.004 | AI19: =費用予算!M29 -> 49957.712 | ... CI19: =費用予算!BM29 -> 974644.87
C20: コンサル直接経費 | E20: =SUMIF($AB$3:$CI$3,E$4,$AB20:$CI20) -> 324515.06 | F20: =SUMIF($AB$3:$CI$3,F$4,$AB20:$CI20) -> 1917646.7 | G20: =SUMIF($AB$3:$CI$3,G$4,$AB20:$CI20) -> 3819514.2 | H20: =SUMIF($AB$3:$CI$3,H$4,$AB20:$CI20) -> 5841022.4 | I20: =SUMIF($AB$3:$CI$3,I$4,$AB20:$CI20) -> 7927179.9 | J20: =SUM(E20:I20) -> 19829878 | K20: =SUMIF($P$3:$CN$3,K$4,$P20:$CN20) -> 0 | L20: =SUMIF($P$3:$CN$3,L$4,$P20:$CN20) -> 0 | M20: =SUMIF($P$3:$CN$3,M$4,$P20:$CN20) -> 0 | N20: =SUMIF($P$3:$CN$3,N$4,$P20:$CN20) -> 0 | AB20: =費用予算!F30 -> 0 | AC20: =費用予算!G30 -> 0 | AD20: =費用予算!H30 -> 0 | AE20: =費用予算!I30 -> 0 | AF20: =費用予算!J30 -> 2252.25 | AG20: =費用予算!K30 -> 13400.888 | AH20: =費用予算!L30 -> 23992.093 | AI20: =費用予算!M30 -> 34053.738 | ... CI20: =費用予算!BM30 -> 741526.67
J21: =SUMIF($P$3:$CN$3,J$4,$P21:$CN21) -> 0 | K21: =SUMIF($P$3:$CN$3,K$4,$P21:$CN21) -> 0 | L21: =SUMIF($P$3:$CN$3,L$4,$P21:$CN21) -> 0 | M21: =SUMIF($P$3:$CN$3,M$4,$P21:$CN21) -> 0 | N21: =SUMIF($P$3:$CN$3,N$4,$P21:$CN21) -> 0
B22: KPI | C22: 原価率 | D22: % | E22: =E14/E5*100 -> 8.4428413 | F22: =F14/F5*100 -> 7.4390754 | G22: =G14/G5*100 -> 7.4461503 | H22: =H14/H5*100 -> 7.5827268 | I22: =I14/I5*100 -> 7.7901052 | J22: =IFERROR(J14/J5*100,"-") -> 7.6484758 | K22: =IFERROR(K14/K5,"-") -> - | L22: =IFERROR(L14/L5,"-") -> - | M22: =IFERROR(M14/M5,"-") -> - | N22: =IFERROR(N14/N5,"-") -> - | AB22: =IFERROR(AB14/AB5*100,"-") -> - | AC22: =AC14/AC5*100 -> 94.249168 | AD22: =AD14/AD5*100 -> 21.100351 | AE22: =AE14/AE5*100 -> 14.339962 | AF22: =AF14/AF5*100 -> 12.152417 | AG22: =AG14/AG5*100 -> 11.506956 | AH22: =AH14/AH5*100 -> 9.0799719 | AI22: =AI14/AI5*100 -> 7.896381 | AJ22: =AJ14/AJ5*100 -> 7.2323206 | ... CI22: =CI14/CI5*100 -> 7.533825
A23: 売上総利益 | D23: 円 | E23: =E5-E14 -> 21150429 | F23: =F5-F14 -> 99594004 | G23: =G5-G14 -> 2.0175351e+08 | H23: =H5-H14 -> 3.207445e+08 | I23: =I5-I14 -> 4.6293012e+08 | J23: =J5-J14 -> 1.1061726e+09 | K23: =K5-K14 -> 0 | L23: =L5-L14 -> 0 | ... N23: =N5-N14 -> 0 | AB23: =AB5-AB14 -> -50000 | AC23: =AC5-AC14 -> 3254.8799 | AD23: =AD5-AD14 -> 261727.01 | AE23: =AE5-AE14 -> 515587.57 | AF23: =AF5-AF14 -> 755815.39 | AG23: =AG5-AG14 -> 1036048 | AH23: =AH5-AH14 -> 1641630.2 | AI23: =AI5-AI14 -> 2242638.4 | ... CI23: =CI5-CI14 -> 44831957
C24: 前期比 | D24: ％ | F24: =IF(E23>0,(F23-E23)/E23,"-") -> 3.7088409 | G24: =IF(F23>0,(G23-F23)/F23,"-") -> 1.0257596 | H24: =IF(G23>0,(H23-G23)/G23,"-") -> 0.58978402 | I24: =IF(H23>0,(I23-H23)/H23,"-") -> 0.4432987 | J24: =IFERROR((I23/E23)^(1/4)-1,"-") -> 1.1629629 | K24: =IF(K23>0,(K23-J23)/J23,"-") -> - | L24: =IF(L23>0,(L23-K23)/K23,"-") -> - | M24: =IF(M23>0,(M23-L23)/L23,"-") -> - | N24: =IF(N23>0,(N23-M23)/M23,"-") -> -
A25: 販管費 | D25: 円 | E25: =SUMIF($AB$3:$CI$3,E$4,$AB25:$CI25) -> 54400000 | F25: =SUMIF($AB$3:$CI$3,F$4,$AB25:$CI25) -> 111500000 | G25: =SUMIF($AB$3:$CI$3,G$4,$AB25:$CI25) -> 205900000 | H25: =SUMIF($AB$3:$CI$3,H$4,$AB25:$CI25) -> 316400000 | I25: =SUMIF($AB$3:$CI$3,I$4,$AB25:$CI25) -> 522100000 | J25: =SUM(E25:I25) -> 1210300000 | K25: =SUMIF($P$3:$CN$3,K$4,$P25:$CN25) -> 0 | L25: =SUMIF($P$3:$CN$3,L$4,$P25:$CN25) -> 0 | M25: =SUMIF($P$3:$CN$3,M$4,$P25:$CN25) -> 0 | N25: =SUMIF($P$3:$CN$3,N$4,$P25:$CN25) -> 0 | AB25: =AB26+AB27+AB31+AB35+AB39+AB43+AB46+AB50+AB51+AB52+AB53+AB54+AB58+AB61+AB62+AB63+AB64+AB65+AB66+AB67+AB68+AB69+AB70+AB71+AB72+AB75+AB78+AB79 -> 4533335 | AC25: =AC26+AC27+AC31+AC35+AC39+AC43+AC46+AC50+AC51+AC52+AC53+AC54+AC58+AC61+AC62+AC63+AC64+AC65+AC66+AC67+AC68+AC69+AC70+AC71+AC72+AC75+AC78+AC79 -> 4533335 | AD25: =AD26+AD27+AD31+AD35+AD39+AD43+AD46+AD50+AD51+AD52+AD53+AD54+AD58+AD61+AD62+AD63+AD64+AD65+AD66+AD67+AD68+AD69+AD70+AD71+AD72+AD75+AD78+AD79 -> 4533335 | AE25: =AE26+AE27+AE31+AE35+AE39+AE43+AE46+AE50+AE51+AE52+AE53+AE54+AE58+AE61+AE62+AE63+AE64+AE65+AE66+AE67+AE68+AE69+AE70+AE71+AE72+AE75+AE78+AE79 -> 4533335 | AF25: =AF26+AF27+AF31+AF35+AF39+AF43+AF46+AF50+AF51+AF52+AF53+AF54+AF58+AF61+AF62+AF63+AF64+AF65+AF66+AF67+AF68+AF69+AF70+AF71+AF72+AF75+AF78+AF79 -> 4533335 | AG25: =AG26+AG27+AG31+AG35+AG39+AG43+AG46+AG50+AG51+AG52+AG53+AG54+AG58+AG61+AG62+AG63+AG64+AG65+AG66+AG67+AG68+AG69+AG70+AG71+AG72+AG75+AG78+AG79 -> 4533335 | AH25: =AH26+AH27+AH31+AH35+AH39+AH43+AH46+AH50+AH51+AH52+AH53+AH54+AH58+AH61+AH62+AH63+AH64+AH65+AH66+AH67+AH68+AH69+AH70+AH71+AH72+AH75+AH78+AH79 -> 4533335 | AI25: =AI26+AI27+AI31+AI35+AI39+AI43+AI46+AI50+AI51+AI52+AI53+AI54+AI58+AI61+AI62+AI63+AI64+AI65+AI66+AI67+AI68+AI69+AI70+AI71+AI72+AI75+AI78+AI79 -> 4533335 | ... CI25: =CI26+CI27+CI31+CI35+CI39+CI43+CI46+CI50+CI51+CI52+CI53+CI54+CI58+CI61+CI62+CI63+CI64+CI65+CI66+CI67+CI68+CI69+CI70+CI71+CI72+CI75+CI78+CI79 -> 43508326
B26: 役員報酬 | E26: =SUMIF($AB$3:$CI$3,E$4,$AB26:$CI26) -> 12000000 | F26: =SUMIF($AB$3:$CI$3,F$4,$AB26:$CI26) -> 15000000 | G26: =SUMIF($AB$3:$CI$3,G$4,$AB26:$CI26) -> 18000000 | H26: =SUMIF($AB$3:$CI$3,H$4,$AB26:$CI26) -> 24000000 | I26: =SUMIF($AB$3:$CI$3,I$4,$AB26:$CI26) -> 30000000 | J26: =SUM(E26:I26) -> 99000000 | K26: =SUMIF($Q$3:$CN$3,K$4,$Q26:$CN26) -> 0 | L26: =SUMIF($Q$3:$CN$3,L$4,$Q26:$CN26) -> 0 | M26: =SUMIF($Q$3:$CN$3,M$4,$Q26:$CN26) -> 0 | N26: =SUMIF($Q$3:$CN$3,N$4,$Q26:$CN26) -> 0 | AB26: =ROUND(INDEX(販管費予算!$E$5:$I$5,MATCH(AB$3,販管費予算!$E$4:$I$4,0))/12,0)+IF(COUNTIF($AB$3:AB$3,AB$3)=12,INDEX(販管費予算!$E$5:$I$5,MATCH(AB$3,販管費予算!$E$4:$I$4,0))-12*ROUND(INDEX(販管費予算!$E$5:$I$5,MATCH(AB$3,販管費予算!$E$4:$I$4,0))/12,0),0) -> 1000000 | AC26: =ROUND(INDEX(販管費予算!$E$5:$I$5,MATCH(AC$3,販管費予算!$E$4:$I$4,0))/12,0)+IF(COUNTIF($AB$3:AC$3,AC$3)=12,INDEX(販管費予算!$E$5:$I$5,MATCH(AC$3,販管費予算!$E$4:$I$4,0))-12*ROUND(INDEX(販管費予算!$E$5:$I$5,MATCH(AC$3,販管費予算!$E$4:$I$4,0))/12,0),0) -> 1000000 | AD26: =ROUND(INDEX(販管費予算!$E$5:$I$5,MATCH(AD$3,販管費予算!$E$4:$I$4,0))/12,0)+IF(COUNTIF($AB$3:AD$3,AD$3)=12,INDEX(販管費予算!$E$5:$I$5,MATCH(AD$3,販管費予算!$E$4:$I$4,0))-12*ROUND(INDEX(販管費予算!$E$5:$I$5,MATCH(AD$3,販管費予算!$E$4:$I$4,0))/12,0),0) -> 1000000 | AE26: =ROUND(INDEX(販管費予算!$E$5:$I$5,MATCH(AE$3,販管費予算!$E$4:$I$4,0))/12,0)+IF(COUNTIF($AB$3:AE$3,AE$3)=12,INDEX(販管費予算!$E$5:$I$5,MATCH(AE$3,販管費予算!$E$4:$I$4,0))-12*ROUND(INDEX(販管費予算!$E$5:$I$5,MATCH(AE$3,販管費予算!$E$4:$I$4,0))/12,0),0) -> 1000000 | AF26: =ROUND(INDEX(販管費予算!$E$5:$I$5,MATCH(AF$3,販管費予算!$E$4:$I$4,0))/12,0)+IF(COUNTIF($AB$3:AF$3,AF$3)=12,INDEX(販管費予算!$E$5:$I$5,MATCH(AF$3,販管費予算!$E$4:$I$4,0))-12*ROUND(INDEX(販管費予算!$E$5:$I$5,MATCH(AF$3,販管費予算!$E$4:$I$4,0))/12,0),0) -> 1000000 | AG26: =ROUND(INDEX(販管費予算!$E$5:$I$5,MATCH(AG$3,販管費予算!$E$4:$I$4,0))/12,0)+IF(COUNTIF($AB$3:AG$3,AG$3)=12,INDEX(販管費予算!$E$5:$I$5,MATCH(AG$3,販管費予算!$E$4:$I$4,0))-12*ROUND(INDEX(販管費予算!$E$5:$I$5,MATCH(AG$3,販管費予算!$E$4:$I$4,0))/12,0),0) -> 1000000 | AH26: =ROUND(INDEX(販管費予算!$E$5:$I$5,MATCH(AH$3,販管費予算!$E$4:$I$4,0))/12,0)+IF(COUNTIF($AB$3:AH$3,AH$3)=12,INDEX(販管費予算!$E$5:$I$5,MATCH(AH$3,販管費予算!$E$4:$I$4,0))-12*ROUND(INDEX(販管費予算!$E$5:$I$5,MATCH(AH$3,販管費予算!$E$4:$I$4,0))/12,0),0) -> 1000000 | AI26: =ROUND(INDEX(販管費予算!$E$5:$I$5,MATCH(AI$3,販管費予算!$E$4:$I$4,0))/12,0)+IF(COUNTIF($AB$3:AI$3,AI$3)=12,INDEX(販管費予算!$E$5:$I$5,MATCH(AI$3,販管費予算!$E$4:$I$4,0))-12*ROUND(INDEX(販管費予算!$E$5:$I$5,MATCH(AI$3,販管費予算!$E$4:$I$4,0))/12,0),0) -> 1000000 | ... CI26: =ROUND(INDEX(販管費予算!$E$5:$I$5,MATCH(CI$3,販管費予算!$E$4:$I$4,0))/12,0)+IF(COUNTIF($AB$3:CI$3,CI$3)=12,INDEX(販管費予算!$E$5:$I$5,MATCH(CI$3,販管費予算!$E$4:$I$4,0))-12*ROUND(INDEX(販管費予算!$E$5:$I$5,MATCH(CI$3,販管費予算!$E$4:$I$4,0))/12,0),0) -> 2500000
B27: 給与手当 | E27: =SUMIF($AB$3:$CI$3,E$4,$AB27:$CI27) -> 12000000 | F27: =SUMIF($AB$3:$CI$3,F$4,$AB27:$CI27) -> 30000000 | G27: =SUMIF($AB$3:$CI$3,G$4,$AB27:$CI27) -> 60000000 | H27: =SUMIF($AB$3:$CI$3,H$4,$AB27:$CI27) -> 90000000 | I27: =SUMIF($AB$3:$CI$3,I$4,$AB27:$CI27) -> 150000000 | J27: =SUM(E27:I27) -> 342000000 | K27: =SUMIF($Q$3:$CN$3,K$4,$Q27:$CN27) -> 0 | L27: =SUMIF($Q$3:$CN$3,L$4,$Q27:$CN27) -> 0 | M27: =SUMIF($Q$3:$CN$3,M$4,$Q27:$CN27) -> 0 | N27: =SUMIF($Q$3:$CN$3,N$4,$Q27:$CN27) -> 0 | AB27: =SUM(AB28:AB30) -> 1000000 | AC27: =SUM(AC28:AC30) -> 1000000 | AD27: =SUM(AD28:AD30) -> 1000000 | AE27: =SUM(AE28:AE30) -> 1000000 | AF27: =SUM(AF28:AF30) -> 1000000 | AG27: =SUM(AG28:AG30) -> 1000000 | AH27: =SUM(AH28:AH30) -> 1000000 | AI27: =SUM(AI28:AI30) -> 1000000 | ... CI27: =SUM(CI28:CI30) -> 12500000
C28: 全社 | E28: =SUMIF($AB$3:$CI$3,E$4,$AB28:$CI28) -> 12000000 | F28: =SUMIF($AB$3:$CI$3,F$4,$AB28:$CI28) -> 30000000 | G28: =SUMIF($AB$3:$CI$3,G$4,$AB28:$CI28) -> 60000000 | H28: =SUMIF($AB$3:$CI$3,H$4,$AB28:$CI28) -> 90000000 | I28: =SUMIF($AB$3:$CI$3,I$4,$AB28:$CI28) -> 150000000 | J28: =SUM(E28:I28) -> 342000000 | K28: =SUMIF($Q$3:$CN$3,K$4,$Q28:$CN28) -> 0 | L28: =SUMIF($Q$3:$CN$3,L$4,$Q28:$CN28) -> 0 | M28: =SUMIF($Q$3:$CN$3,M$4,$Q28:$CN28) -> 0 | N28: =SUMIF($Q$3:$CN$3,N$4,$Q28:$CN28) -> 0 | AB28: =ROUND(INDEX(販管費予算!$E$6:$I$6,MATCH(AB$3,販管費予算!$E$4:$I$4,0))/12,0)+IF(COUNTIF($AB$3:AB$3,AB$3)=12,INDEX(販管費予算!$E$6:$I$6,MATCH(AB$3,販管費予算!$E$4:$I$4,0))-12*ROUND(INDEX(販管費予算!$E$6:$I$6,MATCH(AB$3,販管費予算!$E$4:$I$4,0))/12,0),0) -> 1000000 | AC28: =ROUND(INDEX(販管費予算!$E$6:$I$6,MATCH(AC$3,販管費予算!$E$4:$I$4,0))/12,0)+IF(COUNTIF($AB$3:AC$3,AC$3)=12,INDEX(販管費予算!$E$6:$I$6,MATCH(AC$3,販管費予算!$E$4:$I$4,0))-12*ROUND(INDEX(販管費予算!$E$6:$I$6,MATCH(AC$3,販管費予算!$E$4:$I$4,0))/12,0),0) -> 1000000 | AD28: =ROUND(INDEX(販管費予算!$E$6:$I$6,MATCH(AD$3,販管費予算!$E$4:$I$4,0))/12,0)+IF(COUNTIF($AB$3:AD$3,AD$3)=12,INDEX(販管費予算!$E$6:$I$6,MATCH(AD$3,販管費予算!$E$4:$I$4,0))-12*ROUND(INDEX(販管費予算!$E$6:$I$6,MATCH(AD$3,販管費予算!$E$4:$I$4,0))/12,0),0) -> 1000000 | AE28: =ROUND(INDEX(販管費予算!$E$6:$I$6,MATCH(AE$3,販管費予算!$E$4:$I$4,0))/12,0)+IF(COUNTIF($AB$3:AE$3,AE$3)=12,INDEX(販管費予算!$E$6:$I$6,MATCH(AE$3,販管費予算!$E$4:$I$4,0))-12*ROUND(INDEX(販管費予算!$E$6:$I$6,MATCH(AE$3,販管費予算!$E$4:$I$4,0))/12,0),0) -> 1000000 | AF28: =ROUND(INDEX(販管費予算!$E$6:$I$6,MATCH(AF$3,販管費予算!$E$4:$I$4,0))/12,0)+IF(COUNTIF($AB$3:AF$3,AF$3)=12,INDEX(販管費予算!$E$6:$I$6,MATCH(AF$3,販管費予算!$E$4:$I$4,0))-12*ROUND(INDEX(販管費予算!$E$6:$I$6,MATCH(AF$3,販管費予算!$E$4:$I$4,0))/12,0),0) -> 1000000 | AG28: =ROUND(INDEX(販管費予算!$E$6:$I$6,MATCH(AG$3,販管費予算!$E$4:$I$4,0))/12,0)+IF(COUNTIF($AB$3:AG$3,AG$3)=12,INDEX(販管費予算!$E$6:$I$6,MATCH(AG$3,販管費予算!$E$4:$I$4,0))-12*ROUND(INDEX(販管費予算!$E$6:$I$6,MATCH(AG$3,販管費予算!$E$4:$I$4,0))/12,0),0) -> 1000000 | AH28: =ROUND(INDEX(販管費予算!$E$6:$I$6,MATCH(AH$3,販管費予算!$E$4:$I$4,0))/12,0)+IF(COUNTIF($AB$3:AH$3,AH$3)=12,INDEX(販管費予算!$E$6:$I$6,MATCH(AH$3,販管費予算!$E$4:$I$4,0))-12*ROUND(INDEX(販管費予算!$E$6:$I$6,MATCH(AH$3,販管費予算!$E$4:$I$4,0))/12,0),0) -> 1000000 | AI28: =ROUND(INDEX(販管費予算!$E$6:$I$6,MATCH(AI$3,販管費予算!$E$4:$I$4,0))/12,0)+IF(COUNTIF($AB$3:AI$3,AI$3)=12,INDEX(販管費予算!$E$6:$I$6,MATCH(AI$3,販管費予算!$E$4:$I$4,0))-12*ROUND(INDEX(販管費予算!$E$6:$I$6,MATCH(AI$3,販管費予算!$E$4:$I$4,0))/12,0),0) -> 1000000 | ... CI28: =ROUND(INDEX(販管費予算!$E$6:$I$6,MATCH(CI$3,販管費予算!$E$4:$I$4,0))/12,0)+IF(COUNTIF($AB$3:CI$3,CI$3)=12,INDEX(販管費予算!$E$6:$I$6,MATCH(CI$3,販管費予算!$E$4:$I$4,0))-12*ROUND(INDEX(販管費予算!$E$6:$I$6,MATCH(CI$3,販管費予算!$E$4:$I$4,0))/12,0),0) -> 12500000
C29: SaaS | E29: =SUMIF($AB$3:$CI$3,E$4,$AB29:$CI29) -> 0 | F29: =SUMIF($AB$3:$CI$3,F$4,$AB29:$CI29) -> 0 | G29: =SUMIF($AB$3:$CI$3,G$4,$AB29:$CI29) -> 0 | H29: =SUMIF($AB$3:$CI$3,H$4,$AB29:$CI29) -> 0 | I29: =SUMIF($AB$3:$CI$3,I$4,$AB29:$CI29) -> 0 | J29: =SUM(E29:I29) -> 0 | K29: =SUMIF($Q$3:$CN$3,K$4,$Q29:$CN29) -> 0 | L29: =SUMIF($Q$3:$CN$3,L$4,$Q29:$CN29) -> 0 | M29: =SUMIF($Q$3:$CN$3,M$4,$Q29:$CN29) -> 0 | N29: =SUMIF($Q$3:$CN$3,N$4,$Q29:$CN29) -> 0
C30: 事業・組織再生コンサル | E30: =SUMIF($AB$3:$CI$3,E$4,$AB30:$CI30) -> 0 | F30: =SUMIF($AB$3:$CI$3,F$4,$AB30:$CI30) -> 0 | G30: =SUMIF($AB$3:$CI$3,G$4,$AB30:$CI30) -> 0 | H30: =SUMIF($AB$3:$CI$3,H$4,$AB30:$CI30) -> 0 | I30: =SUMIF($AB$3:$CI$3,I$4,$AB30:$CI30) -> 0 | J30: =SUM(E30:I30) -> 0 | K30: =SUMIF($Q$3:$CN$3,K$4,$Q30:$CN30) -> 0 | L30: =SUMIF($Q$3:$CN$3,L$4,$Q30:$CN30) -> 0 | M30: =SUMIF($Q$3:$CN$3,M$4,$Q30:$CN30) -> 0 | N30: =SUMIF($Q$3:$CN$3,N$4,$Q30:$CN30) -> 0
B31: 賞与手当 | E31: =SUMIF($AB$3:$CI$3,E$4,$AB31:$CI31) -> 0 | F31: =SUMIF($AB$3:$CI$3,F$4,$AB31:$CI31) -> 3000000 | G31: =SUMIF($AB$3:$CI$3,G$4,$AB31:$CI31) -> 6000000 | H31: =SUMIF($AB$3:$CI$3,H$4,$AB31:$CI31) -> 9000000 | I31: =SUMIF($AB$3:$CI$3,I$4,$AB31:$CI31) -> 15000000 | J31: =SUM(E31:I31) -> 33000000 | K31: =SUMIF($Q$3:$CN$3,K$4,$Q31:$CN31) -> 0 | L31: =SUMIF($Q$3:$CN$3,L$4,$Q31:$CN31) -> 0 | M31: =SUMIF($Q$3:$CN$3,M$4,$Q31:$CN31) -> 0 | N31: =SUMIF($Q$3:$CN$3,N$4,$Q31:$CN31) -> 0 | AB31: =SUM(AB32:AB34) -> 0 | AC31: =SUM(AC32:AC34) -> 0 | AD31: =SUM(AD32:AD34) -> 0 | AE31: =SUM(AE32:AE34) -> 0 | AF31: =SUM(AF32:AF34) -> 0 | AG31: =SUM(AG32:AG34) -> 0 | AH31: =SUM(AH32:AH34) -> 0 | AI31: =SUM(AI32:AI34) -> 0 | ... CI31: =SUM(CI32:CI34) -> 1250000
C32: 全社 | E32: =SUMIF($AB$3:$CI$3,E$4,$AB32:$CI32) -> 0 | F32: =SUMIF($AB$3:$CI$3,F$4,$AB32:$CI32) -> 3000000 | G32: =SUMIF($AB$3:$CI$3,G$4,$AB32:$CI32) -> 6000000 | H32: =SUMIF($AB$3:$CI$3,H$4,$AB32:$CI32) -> 9000000 | I32: =SUMIF($AB$3:$CI$3,I$4,$AB32:$CI32) -> 15000000 | J32: =SUM(E32:I32) -> 33000000 | K32: =SUMIF($Q$3:$CN$3,K$4,$Q32:$CN32) -> 0 | L32: =SUMIF($Q$3:$CN$3,L$4,$Q32:$CN32) -> 0 | M32: =SUMIF($Q$3:$CN$3,M$4,$Q32:$CN32) -> 0 | N32: =SUMIF($Q$3:$CN$3,N$4,$Q32:$CN32) -> 0 | AB32: =ROUND(INDEX(販管費予算!$E$7:$I$7,MATCH(AB$3,販管費予算!$E$4:$I$4,0))/12,0)+IF(COUNTIF($AB$3:AB$3,AB$3)=12,INDEX(販管費予算!$E$7:$I$7,MATCH(AB$3,販管費予算!$E$4:$I$4,0))-12*ROUND(INDEX(販管費予算!$E$7:$I$7,MATCH(AB$3,販管費予算!$E$4:$I$4,0))/12,0),0) -> 0 | AC32: =ROUND(INDEX(販管費予算!$E$7:$I$7,MATCH(AC$3,販管費予算!$E$4:$I$4,0))/12,0)+IF(COUNTIF($AB$3:AC$3,AC$3)=12,INDEX(販管費予算!$E$7:$I$7,MATCH(AC$3,販管費予算!$E$4:$I$4,0))-12*ROUND(INDEX(販管費予算!$E$7:$I$7,MATCH(AC$3,販管費予算!$E$4:$I$4,0))/12,0),0) -> 0 | AD32: =ROUND(INDEX(販管費予算!$E$7:$I$7,MATCH(AD$3,販管費予算!$E$4:$I$4,0))/12,0)+IF(COUNTIF($AB$3:AD$3,AD$3)=12,INDEX(販管費予算!$E$7:$I$7,MATCH(AD$3,販管費予算!$E$4:$I$4,0))-12*ROUND(INDEX(販管費予算!$E$7:$I$7,MATCH(AD$3,販管費予算!$E$4:$I$4,0))/12,0),0) -> 0 | AE32: =ROUND(INDEX(販管費予算!$E$7:$I$7,MATCH(AE$3,販管費予算!$E$4:$I$4,0))/12,0)+IF(COUNTIF($AB$3:AE$3,AE$3)=12,INDEX(販管費予算!$E$7:$I$7,MATCH(AE$3,販管費予算!$E$4:$I$4,0))-12*ROUND(INDEX(販管費予算!$E$7:$I$7,MATCH(AE$3,販管費予算!$E$4:$I$4,0))/12,0),0) -> 0 | AF32: =ROUND(INDEX(販管費予算!$E$7:$I$7,MATCH(AF$3,販管費予算!$E$4:$I$4,0))/12,0)+IF(COUNTIF($AB$3:AF$3,AF$3)=12,INDEX(販管費予算!$E$7:$I$7,MATCH(AF$3,販管費予算!$E$4:$I$4,0))-12*ROUND(INDEX(販管費予算!$E$7:$I$7,MATCH(AF$3,販管費予算!$E$4:$I$4,0))/12,0),0) -> 0 | AG32: =ROUND(INDEX(販管費予算!$E$7:$I$7,MATCH(AG$3,販管費予算!$E$4:$I$4,0))/12,0)+IF(COUNTIF($AB$3:AG$3,AG$3)=12,INDEX(販管費予算!$E$7:$I$7,MATCH(AG$3,販管費予算!$E$4:$I$4,0))-12*ROUND(INDEX(販管費予算!$E$7:$I$7,MATCH(AG$3,販管費予算!$E$4:$I$4,0))/12,0),0) -> 0 | AH32: =ROUND(INDEX(販管費予算!$E$7:$I$7,MATCH(AH$3,販管費予算!$E$4:$I$4,0))/12,0)+IF(COUNTIF($AB$3:AH$3,AH$3)=12,INDEX(販管費予算!$E$7:$I$7,MATCH(AH$3,販管費予算!$E$4:$I$4,0))-12*ROUND(INDEX(販管費予算!$E$7:$I$7,MATCH(AH$3,販管費予算!$E$4:$I$4,0))/12,0),0) -> 0 | AI32: =ROUND(INDEX(販管費予算!$E$7:$I$7,MATCH(AI$3,販管費予算!$E$4:$I$4,0))/12,0)+IF(COUNTIF($AB$3:AI$3,AI$3)=12,INDEX(販管費予算!$E$7:$I$7,MATCH(AI$3,販管費予算!$E$4:$I$4,0))-12*ROUND(INDEX(販管費予算!$E$7:$I$7,MATCH(AI$3,販管費予算!$E$4:$I$4,0))/12,0),0) -> 0 | ... CI32: =ROUND(INDEX(販管費予算!$E$7:$I$7,MATCH(CI$3,販管費予算!$E$4:$I$4,0))/12,0)+IF(COUNTIF($AB$3:CI$3,CI$3)=12,INDEX(販管費予算!$E$7:$I$7,MATCH(CI$3,販管費予算!$E$4:$I$4,0))-12*ROUND(INDEX(販管費予算!$E$7:$I$7,MATCH(CI$3,販管費予算!$E$4:$I$4,0))/12,0),0) -> 1250000
C33: SaaS | E33: =SUMIF($AB$3:$CI$3,E$4,$AB33:$CI33) -> 0 | F33: =SUMIF($AB$3:$CI$3,F$4,$AB33:$CI33) -> 0 | G33: =SUMIF($AB$3:$CI$3,G$4,$AB33:$CI33) -> 0 | H33: =SUMIF($AB$3:$CI$3,H$4,$AB33:$CI33) -> 0 | I33: =SUMIF($AB$3:$CI$3,I$4,$AB33:$CI33) -> 0 | J33: =SUM(E33:I33) -> 0 | K33: =SUMIF($Q$3:$CN$3,K$4,$Q33:$CN33) -> 0 | L33: =SUMIF($Q$3:$CN$3,L$4,$Q33:$CN33) -> 0 | M33: =SUMIF($Q$3:$CN$3,M$4,$Q33:$CN33) -> 0 | N33: =SUMIF($Q$3:$CN$3,N$4,$Q33:$CN33) -> 0
C34: 事業・組織再生コンサル | E34: =SUMIF($AB$3:$CI$3,E$4,$AB34:$CI34) -> 0 | F34: =SUMIF($AB$3:$CI$3,F$4,$AB34:$CI34) -> 0 | G34: =SUMIF($AB$3:$CI$3,G$4,$AB34:$CI34) -> 0 | H34: =SUMIF($AB$3:$CI$3,H$4,$AB34:$CI34) -> 0 | I34: =SUMIF($AB$3:$CI$3,I$4,$AB34:$CI34) -> 0 | J34: =SUM(E34:I34) -> 0 | K34: =SUMIF($Q$3:$CN$3,K$4,$Q34:$CN34) -> 0 | L34: =SUMIF($Q$3:$CN$3,L$4,$Q34:$CN34) -> 0 | M34: =SUMIF($Q$3:$CN$3,M$4,$Q34:$CN34) -> 0 | N34: =SUMIF($Q$3:$CN$3,N$4,$Q34:$CN34) -> 0
B35: 法定福利費 | E35: =SUMIF($AB$3:$CI$3,E$4,$AB35:$CI35) -> 3600000 | F35: =SUMIF($AB$3:$CI$3,F$4,$AB35:$CI35) -> 7200000 | G35: =SUMIF($AB$3:$CI$3,G$4,$AB35:$CI35) -> 14400000 | H35: =SUMIF($AB$3:$CI$3,H$4,$AB35:$CI35) -> 22000000 | I35: =SUMIF($AB$3:$CI$3,I$4,$AB35:$CI35) -> 38000000 | J35: =SUM(E35:I35) -> 85200000 | K35: =SUMIF($Q$3:$CN$3,K$4,$Q35:$CN35) -> 0 | L35: =SUMIF($Q$3:$CN$3,L$4,$Q35:$CN35) -> 0 | M35: =SUMIF($Q$3:$CN$3,M$4,$Q35:$CN35) -> 0 | N35: =SUMIF($Q$3:$CN$3,N$4,$Q35:$CN35) -> 0 | AB35: =SUM(AB36:AB38) -> 300000 | AC35: =SUM(AC36:AC38) -> 300000 | AD35: =SUM(AD36:AD38) -> 300000 | AE35: =SUM(AE36:AE38) -> 300000 | AF35: =SUM(AF36:AF38) -> 300000 | AG35: =SUM(AG36:AG38) -> 300000 | AH35: =SUM(AH36:AH38) -> 300000 | AI35: =SUM(AI36:AI38) -> 300000 | ... CI35: =SUM(CI36:CI38) -> 3166663
C36: 全社 | E36: =SUMIF($AB$3:$CI$3,E$4,$AB36:$CI36) -> 3600000 | F36: =SUMIF($AB$3:$CI$3,F$4,$AB36:$CI36) -> 7200000 | G36: =SUMIF($AB$3:$CI$3,G$4,$AB36:$CI36) -> 14400000 | H36: =SUMIF($AB$3:$CI$3,H$4,$AB36:$CI36) -> 22000000 | I36: =SUMIF($AB$3:$CI$3,I$4,$AB36:$CI36) -> 38000000 | J36: =SUM(E36:I36) -> 85200000 | K36: =SUMIF($Q$3:$CN$3,K$4,$Q36:$CN36) -> 0 | L36: =SUMIF($Q$3:$CN$3,L$4,$Q36:$CN36) -> 0 | M36: =SUMIF($Q$3:$CN$3,M$4,$Q36:$CN36) -> 0 | N36: =SUMIF($Q$3:$CN$3,N$4,$Q36:$CN36) -> 0 | AB36: =ROUND(INDEX(販管費予算!$E$8:$I$8,MATCH(AB$3,販管費予算!$E$4:$I$4,0))/12,0)+IF(COUNTIF($AB$3:AB$3,AB$3)=12,INDEX(販管費予算!$E$8:$I$8,MATCH(AB$3,販管費予算!$E$4:$I$4,0))-12*ROUND(INDEX(販管費予算!$E$8:$I$8,MATCH(AB$3,販管費予算!$E$4:$I$4,0))/12,0),0) -> 300000 | AC36: =ROUND(INDEX(販管費予算!$E$8:$I$8,MATCH(AC$3,販管費予算!$E$4:$I$4,0))/12,0)+IF(COUNTIF($AB$3:AC$3,AC$3)=12,INDEX(販管費予算!$E$8:$I$8,MATCH(AC$3,販管費予算!$E$4:$I$4,0))-12*ROUND(INDEX(販管費予算!$E$8:$I$8,MATCH(AC$3,販管費予算!$E$4:$I$4,0))/12,0),0) -> 300000 | AD36: =ROUND(INDEX(販管費予算!$E$8:$I$8,MATCH(AD$3,販管費予算!$E$4:$I$4,0))/12,0)+IF(COUNTIF($AB$3:AD$3,AD$3)=12,INDEX(販管費予算!$E$8:$I$8,MATCH(AD$3,販管費予算!$E$4:$I$4,0))-12*ROUND(INDEX(販管費予算!$E$8:$I$8,MATCH(AD$3,販管費予算!$E$4:$I$4,0))/12,0),0) -> 300000 | AE36: =ROUND(INDEX(販管費予算!$E$8:$I$8,MATCH(AE$3,販管費予算!$E$4:$I$4,0))/12,0)+IF(COUNTIF($AB$3:AE$3,AE$3)=12,INDEX(販管費予算!$E$8:$I$8,MATCH(AE$3,販管費予算!$E$4:$I$4,0))-12*ROUND(INDEX(販管費予算!$E$8:$I$8,MATCH(AE$3,販管費予算!$E$4:$I$4,0))/12,0),0) -> 300000 | AF36: =ROUND(INDEX(販管費予算!$E$8:$I$8,MATCH(AF$3,販管費予算!$E$4:$I$4,0))/12,0)+IF(COUNTIF($AB$3:AF$3,AF$3)=12,INDEX(販管費予算!$E$8:$I$8,MATCH(AF$3,販管費予算!$E$4:$I$4,0))-12*ROUND(INDEX(販管費予算!$E$8:$I$8,MATCH(AF$3,販管費予算!$E$4:$I$4,0))/12,0),0) -> 300000 | AG36: =ROUND(INDEX(販管費予算!$E$8:$I$8,MATCH(AG$3,販管費予算!$E$4:$I$4,0))/12,0)+IF(COUNTIF($AB$3:AG$3,AG$3)=12,INDEX(販管費予算!$E$8:$I$8,MATCH(AG$3,販管費予算!$E$4:$I$4,0))-12*ROUND(INDEX(販管費予算!$E$8:$I$8,MATCH(AG$3,販管費予算!$E$4:$I$4,0))/12,0),0) -> 300000 | AH36: =ROUND(INDEX(販管費予算!$E$8:$I$8,MATCH(AH$3,販管費予算!$E$4:$I$4,0))/12,0)+IF(COUNTIF($AB$3:AH$3,AH$3)=12,INDEX(販管費予算!$E$8:$I$8,MATCH(AH$3,販管費予算!$E$4:$I$4,0))-12*ROUND(INDEX(販管費予算!$E$8:$I$8,MATCH(AH$3,販管費予算!$E$4:$I$4,0))/12,0),0) -> 300000 | AI36: =ROUND(INDEX(販管費予算!$E$8:$I$8,MATCH(AI$3,販管費予算!$E$4:$I$4,0))/12,0)+IF(COUNTIF($AB$3:AI$3,AI$3)=12,INDEX(販管費予算!$E$8:$I$8,MATCH(AI$3,販管費予算!$E$4:$I$4,0))-12*ROUND(INDEX(販管費予算!$E$8:$I$8,MATCH(AI$3,販管費予算!$E$4:$I$4,0))/12,0),0) -> 300000 | ... CI36: =ROUND(INDEX(販管費予算!$E$8:$I$8,MATCH(CI$3,販管費予算!$E$4:$I$4,0))/12,0)+IF(COUNTIF($AB$3:CI$3,CI$3)=12,INDEX(販管費予算!$E$8:$I$8,MATCH(CI$3,販管費予算!$E$4:$I$4,0))-12*ROUND(INDEX(販管費予算!$E$8:$I$8,MATCH(CI$3,販管費予算!$E$4:$I$4,0))/12,0),0) -> 3166663
C37: SaaS | E37: =SUMIF($AB$3:$CI$3,E$4,$AB37:$CI37) -> 0 | F37: =SUMIF($AB$3:$CI$3,F$4,$AB37:$CI37) -> 0 | G37: =SUMIF($AB$3:$CI$3,G$4,$AB37:$CI37) -> 0 | H37: =SUMIF($AB$3:$CI$3,H$4,$AB37:$CI37) -> 0 | I37: =SUMIF($AB$3:$CI$3,I$4,$AB37:$CI37) -> 0 | J37: =SUM(E37:I37) -> 0 | K37: =SUMIF($Q$3:$CN$3,K$4,$Q37:$CN37) -> 0 | L37: =SUMIF($Q$3:$CN$3,L$4,$Q37:$CN37) -> 0 | M37: =SUMIF($Q$3:$CN$3,M$4,$Q37:$CN37) -> 0 | N37: =SUMIF($Q$3:$CN$3,N$4,$Q37:$CN37) -> 0
C38: 事業・組織再生コンサル | E38: =SUMIF($AB$3:$CI$3,E$4,$AB38:$CI38) -> 0 | F38: =SUMIF($AB$3:$CI$3,F$4,$AB38:$CI38) -> 0 | G38: =SUMIF($AB$3:$CI$3,G$4,$AB38:$CI38) -> 0 | H38: =SUMIF($AB$3:$CI$3,H$4,$AB38:$CI38) -> 0 | I38: =SUMIF($AB$3:$CI$3,I$4,$AB38:$CI38) -> 0 | J38: =SUM(E38:I38) -> 0 | K38: =SUMIF($Q$3:$CN$3,K$4,$Q38:$CN38) -> 0 | L38: =SUMIF($Q$3:$CN$3,L$4,$Q38:$CN38) -> 0 | M38: =SUMIF($Q$3:$CN$3,M$4,$Q38:$CN38) -> 0 | N38: =SUMIF($Q$3:$CN$3,N$4,$Q38:$CN38) -> 0
B39: 福利厚生費 | E39: =SUMIF($AB$3:$CI$3,E$4,$AB39:$CI39) -> 300000 | F39: =SUMIF($AB$3:$CI$3,F$4,$AB39:$CI39) -> 600000 | G39: =SUMIF($AB$3:$CI$3,G$4,$AB39:$CI39) -> 1200000 | H39: =SUMIF($AB$3:$CI$3,H$4,$AB39:$CI39) -> 2000000 | I39: =SUMIF($AB$3:$CI$3,I$4,$AB39:$CI39) -> 3500000 | J39: =SUM(E39:I39) -> 7600000 | K39: =SUMIF($Q$3:$CN$3,K$4,$Q39:$CN39) -> 0 | L39: =SUMIF($Q$3:$CN$3,L$4,$Q39:$CN39) -> 0 | M39: =SUMIF($Q$3:$CN$3,M$4,$Q39:$CN39) -> 0 | N39: =SUMIF($Q$3:$CN$3,N$4,$Q39:$CN39) -> 0 | AB39: =SUM(AB40:AB42) -> 25000 | AC39: =SUM(AC40:AC42) -> 25000 | AD39: =SUM(AD40:AD42) -> 25000 | AE39: =SUM(AE40:AE42) -> 25000 | AF39: =SUM(AF40:AF42) -> 25000 | AG39: =SUM(AG40:AG42) -> 25000 | AH39: =SUM(AH40:AH42) -> 25000 | AI39: =SUM(AI40:AI42) -> 25000 | ... CI39: =SUM(CI40:CI42) -> 291663
C40: 全社 | E40: =SUMIF($AB$3:$CI$3,E$4,$AB40:$CI40) -> 300000 | F40: =SUMIF($AB$3:$CI$3,F$4,$AB40:$CI40) -> 600000 | G40: =SUMIF($AB$3:$CI$3,G$4,$AB40:$CI40) -> 1200000 | H40: =SUMIF($AB$3:$CI$3,H$4,$AB40:$CI40) -> 2000000 | I40: =SUMIF($AB$3:$CI$3,I$4,$AB40:$CI40) -> 3500000 | J40: =SUM(E40:I40) -> 7600000 | K40: =SUMIF($Q$3:$CN$3,K$4,$Q40:$CN40) -> 0 | L40: =SUMIF($Q$3:$CN$3,L$4,$Q40:$CN40) -> 0 | M40: =SUMIF($Q$3:$CN$3,M$4,$Q40:$CN40) -> 0 | N40: =SUMIF($Q$3:$CN$3,N$4,$Q40:$CN40) -> 0 | AB40: =ROUND(INDEX(販管費予算!$E$9:$I$9,MATCH(AB$3,販管費予算!$E$4:$I$4,0))/12,0)+IF(COUNTIF($AB$3:AB$3,AB$3)=12,INDEX(販管費予算!$E$9:$I$9,MATCH(AB$3,販管費予算!$E$4:$I$4,0))-12*ROUND(INDEX(販管費予算!$E$9:$I$9,MATCH(AB$3,販管費予算!$E$4:$I$4,0))/12,0),0) -> 25000 | AC40: =ROUND(INDEX(販管費予算!$E$9:$I$9,MATCH(AC$3,販管費予算!$E$4:$I$4,0))/12,0)+IF(COUNTIF($AB$3:AC$3,AC$3)=12,INDEX(販管費予算!$E$9:$I$9,MATCH(AC$3,販管費予算!$E$4:$I$4,0))-12*ROUND(INDEX(販管費予算!$E$9:$I$9,MATCH(AC$3,販管費予算!$E$4:$I$4,0))/12,0),0) -> 25000 | AD40: =ROUND(INDEX(販管費予算!$E$9:$I$9,MATCH(AD$3,販管費予算!$E$4:$I$4,0))/12,0)+IF(COUNTIF($AB$3:AD$3,AD$3)=12,INDEX(販管費予算!$E$9:$I$9,MATCH(AD$3,販管費予算!$E$4:$I$4,0))-12*ROUND(INDEX(販管費予算!$E$9:$I$9,MATCH(AD$3,販管費予算!$E$4:$I$4,0))/12,0),0) -> 25000 | AE40: =ROUND(INDEX(販管費予算!$E$9:$I$9,MATCH(AE$3,販管費予算!$E$4:$I$4,0))/12,0)+IF(COUNTIF($AB$3:AE$3,AE$3)=12,INDEX(販管費予算!$E$9:$I$9,MATCH(AE$3,販管費予算!$E$4:$I$4,0))-12*ROUND(INDEX(販管費予算!$E$9:$I$9,MATCH(AE$3,販管費予算!$E$4:$I$4,0))/12,0),0) -> 25000 | AF40: =ROUND(INDEX(販管費予算!$E$9:$I$9,MATCH(AF$3,販管費予算!$E$4:$I$4,0))/12,0)+IF(COUNTIF($AB$3:AF$3,AF$3)=12,INDEX(販管費予算!$E$9:$I$9,MATCH(AF$3,販管費予算!$E$4:$I$4,0))-12*ROUND(INDEX(販管費予算!$E$9:$I$9,MATCH(AF$3,販管費予算!$E$4:$I$4,0))/12,0),0) -> 25000 | AG40: =ROUND(INDEX(販管費予算!$E$9:$I$9,MATCH(AG$3,販管費予算!$E$4:$I$4,0))/12,0)+IF(COUNTIF($AB$3:AG$3,AG$3)=12,INDEX(販管費予算!$E$9:$I$9,MATCH(AG$3,販管費予算!$E$4:$I$4,0))-12*ROUND(INDEX(販管費予算!$E$9:$I$9,MATCH(AG$3,販管費予算!$E$4:$I$4,0))/12,0),0) -> 25000 | AH40: =ROUND(INDEX(販管費予算!$E$9:$I$9,MATCH(AH$3,販管費予算!$E$4:$I$4,0))/12,0)+IF(COUNTIF($AB$3:AH$3,AH$3)=12,INDEX(販管費予算!$E$9:$I$9,MATCH(AH$3,販管費予算!$E$4:$I$4,0))-12*ROUND(INDEX(販管費予算!$E$9:$I$9,MATCH(AH$3,販管費予算!$E$4:$I$4,0))/12,0),0) -> 25000 | AI40: =ROUND(INDEX(販管費予算!$E$9:$I$9,MATCH(AI$3,販管費予算!$E$4:$I$4,0))/12,0)+IF(COUNTIF($AB$3:AI$3,AI$3)=12,INDEX(販管費予算!$E$9:$I$9,MATCH(AI$3,販管費予算!$E$4:$I$4,0))-12*ROUND(INDEX(販管費予算!$E$9:$I$9,MATCH(AI$3,販管費予算!$E$4:$I$4,0))/12,0),0) -> 25000 | ... CI40: =ROUND(INDEX(販管費予算!$E$9:$I$9,MATCH(CI$3,販管費予算!$E$4:$I$4,0))/12,0)+IF(COUNTIF($AB$3:CI$3,CI$3)=12,INDEX(販管費予算!$E$9:$I$9,MATCH(CI$3,販管費予算!$E$4:$I$4,0))-12*ROUND(INDEX(販管費予算!$E$9:$I$9,MATCH(CI$3,販管費予算!$E$4:$I$4,0))/12,0),0) -> 291663
C41: SaaS | E41: =SUMIF($AB$3:$CI$3,E$4,$AB41:$CI41) -> 0 | F41: =SUMIF($AB$3:$CI$3,F$4,$AB41:$CI41) -> 0 | G41: =SUMIF($AB$3:$CI$3,G$4,$AB41:$CI41) -> 0 | H41: =SUMIF($AB$3:$CI$3,H$4,$AB41:$CI41) -> 0 | I41: =SUMIF($AB$3:$CI$3,I$4,$AB41:$CI41) -> 0 | J41: =SUM(E41:I41) -> 0 | K41: =SUMIF($Q$3:$CN$3,K$4,$Q41:$CN41) -> 0 | L41: =SUMIF($Q$3:$CN$3,L$4,$Q41:$CN41) -> 0 | M41: =SUMIF($Q$3:$CN$3,M$4,$Q41:$CN41) -> 0 | N41: =SUMIF($Q$3:$CN$3,N$4,$Q41:$CN41) -> 0
C42: 事業・組織再生コンサル | E42: =SUMIF($AB$3:$CI$3,E$4,$AB42:$CI42) -> 0 | F42: =SUMIF($AB$3:$CI$3,F$4,$AB42:$CI42) -> 0 | G42: =SUMIF($AB$3:$CI$3,G$4,$AB42:$CI42) -> 0 | H42: =SUMIF($AB$3:$CI$3,H$4,$AB42:$CI42) -> 0 | I42: =SUMIF($AB$3:$CI$3,I$4,$AB42:$CI42) -> 0 | J42: =SUM(E42:I42) -> 0 | K42: =SUMIF($Q$3:$CN$3,K$4,$Q42:$CN42) -> 0 | L42: =SUMIF($Q$3:$CN$3,L$4,$Q42:$CN42) -> 0 | M42: =SUMIF($Q$3:$CN$3,M$4,$Q42:$CN42) -> 0 | N42: =SUMIF($Q$3:$CN$3,N$4,$Q42:$CN42) -> 0
B43: 採用教育費 | E43: =SUMIF($AB$3:$CI$3,E$4,$AB43:$CI43) -> 2000000 | F43: =SUMIF($AB$3:$CI$3,F$4,$AB43:$CI43) -> 5000000 | G43: =SUMIF($AB$3:$CI$3,G$4,$AB43:$CI43) -> 10000000 | H43: =SUMIF($AB$3:$CI$3,H$4,$AB43:$CI43) -> 15000000 | I43: =SUMIF($AB$3:$CI$3,I$4,$AB43:$CI43) -> 25000000 | J43: =SUM(E43:I43) -> 57000000 | K43: =SUMIF($Q$3:$CN$3,K$4,$Q43:$CN43) -> 0 | L43: =SUMIF($Q$3:$CN$3,L$4,$Q43:$CN43) -> 0 | M43: =SUMIF($Q$3:$CN$3,M$4,$Q43:$CN43) -> 0 | N43: =SUMIF($Q$3:$CN$3,N$4,$Q43:$CN43) -> 0 | AB43: =SUM(AB44:AB45) -> 166667 | AC43: =SUM(AC44:AC45) -> 166667 | AD43: =SUM(AD44:AD45) -> 166667 | AE43: =SUM(AE44:AE45) -> 166667 | AF43: =SUM(AF44:AF45) -> 166667 | AG43: =SUM(AG44:AG45) -> 166667 | AH43: =SUM(AH44:AH45) -> 166667 | AI43: =SUM(AI44:AI45) -> 166667 | ... CI43: =SUM(CI44:CI45) -> 2083337
C44: 全社 | E44: =SUMIF($AB$3:$CI$3,E$4,$AB44:$CI44) -> 2000000 | F44: =SUMIF($AB$3:$CI$3,F$4,$AB44:$CI44) -> 5000000 | G44: =SUMIF($AB$3:$CI$3,G$4,$AB44:$CI44) -> 10000000 | H44: =SUMIF($AB$3:$CI$3,H$4,$AB44:$CI44) -> 15000000 | I44: =SUMIF($AB$3:$CI$3,I$4,$AB44:$CI44) -> 25000000 | J44: =SUM(E44:I44) -> 57000000 | K44: =SUMIF($Q$3:$CN$3,K$4,$Q44:$CN44) -> 0 | L44: =SUMIF($Q$3:$CN$3,L$4,$Q44:$CN44) -> 0 | M44: =SUMIF($Q$3:$CN$3,M$4,$Q44:$CN44) -> 0 | N44: =SUMIF($Q$3:$CN$3,N$4,$Q44:$CN44) -> 0 | AB44: =ROUND(INDEX(販管費予算!$E$10:$I$10,MATCH(AB$3,販管費予算!$E$4:$I$4,0))/12,0)+IF(COUNTIF($AB$3:AB$3,AB$3)=12,INDEX(販管費予算!$E$10:$I$10,MATCH(AB$3,販管費予算!$E$4:$I$4,0))-12*ROUND(INDEX(販管費予算!$E$10:$I$10,MATCH(AB$3,販管費予算!$E$4:$I$4,0))/12,0),0) -> 166667 | AC44: =ROUND(INDEX(販管費予算!$E$10:$I$10,MATCH(AC$3,販管費予算!$E$4:$I$4,0))/12,0)+IF(COUNTIF($AB$3:AC$3,AC$3)=12,INDEX(販管費予算!$E$10:$I$10,MATCH(AC$3,販管費予算!$E$4:$I$4,0))-12*ROUND(INDEX(販管費予算!$E$10:$I$10,MATCH(AC$3,販管費予算!$E$4:$I$4,0))/12,0),0) -> 166667 | AD44: =ROUND(INDEX(販管費予算!$E$10:$I$10,MATCH(AD$3,販管費予算!$E$4:$I$4,0))/12,0)+IF(COUNTIF($AB$3:AD$3,AD$3)=12,INDEX(販管費予算!$E$10:$I$10,MATCH(AD$3,販管費予算!$E$4:$I$4,0))-12*ROUND(INDEX(販管費予算!$E$10:$I$10,MATCH(AD$3,販管費予算!$E$4:$I$4,0))/12,0),0) -> 166667 | AE44: =ROUND(INDEX(販管費予算!$E$10:$I$10,MATCH(AE$3,販管費予算!$E$4:$I$4,0))/12,0)+IF(COUNTIF($AB$3:AE$3,AE$3)=12,INDEX(販管費予算!$E$10:$I$10,MATCH(AE$3,販管費予算!$E$4:$I$4,0))-12*ROUND(INDEX(販管費予算!$E$10:$I$10,MATCH(AE$3,販管費予算!$E$4:$I$4,0))/12,0),0) -> 166667 | AF44: =ROUND(INDEX(販管費予算!$E$10:$I$10,MATCH(AF$3,販管費予算!$E$4:$I$4,0))/12,0)+IF(COUNTIF($AB$3:AF$3,AF$3)=12,INDEX(販管費予算!$E$10:$I$10,MATCH(AF$3,販管費予算!$E$4:$I$4,0))-12*ROUND(INDEX(販管費予算!$E$10:$I$10,MATCH(AF$3,販管費予算!$E$4:$I$4,0))/12,0),0) -> 166667 | AG44: =ROUND(INDEX(販管費予算!$E$10:$I$10,MATCH(AG$3,販管費予算!$E$4:$I$4,0))/12,0)+IF(COUNTIF($AB$3:AG$3,AG$3)=12,INDEX(販管費予算!$E$10:$I$10,MATCH(AG$3,販管費予算!$E$4:$I$4,0))-12*ROUND(INDEX(販管費予算!$E$10:$I$10,MATCH(AG$3,販管費予算!$E$4:$I$4,0))/12,0),0) -> 166667 | AH44: =ROUND(INDEX(販管費予算!$E$10:$I$10,MATCH(AH$3,販管費予算!$E$4:$I$4,0))/12,0)+IF(COUNTIF($AB$3:AH$3,AH$3)=12,INDEX(販管費予算!$E$10:$I$10,MATCH(AH$3,販管費予算!$E$4:$I$4,0))-12*ROUND(INDEX(販管費予算!$E$10:$I$10,MATCH(AH$3,販管費予算!$E$4:$I$4,0))/12,0),0) -> 166667 | AI44: =ROUND(INDEX(販管費予算!$E$10:$I$10,MATCH(AI$3,販管費予算!$E$4:$I$4,0))/12,0)+IF(COUNTIF($AB$3:AI$3,AI$3)=12,INDEX(販管費予算!$E$10:$I$10,MATCH(AI$3,販管費予算!$E$4:$I$4,0))-12*ROUND(INDEX(販管費予算!$E$10:$I$10,MATCH(AI$3,販管費予算!$E$4:$I$4,0))/12,0),0) -> 166667 | ... CI44: =ROUND(INDEX(販管費予算!$E$10:$I$10,MATCH(CI$3,販管費予算!$E$4:$I$4,0))/12,0)+IF(COUNTIF($AB$3:CI$3,CI$3)=12,INDEX(販管費予算!$E$10:$I$10,MATCH(CI$3,販管費予算!$E$4:$I$4,0))-12*ROUND(INDEX(販管費予算!$E$10:$I$10,MATCH(CI$3,販管費予算!$E$4:$I$4,0))/12,0),0) -> 2083337
C45: SaaS | E45: =SUMIF($AB$3:$CI$3,E$4,$AB45:$CI45) -> 0 | F45: =SUMIF($AB$3:$CI$3,F$4,$AB45:$CI45) -> 0 | G45: =SUMIF($AB$3:$CI$3,G$4,$AB45:$CI45) -> 0 | H45: =SUMIF($AB$3:$CI$3,H$4,$AB45:$CI45) -> 0 | I45: =SUMIF($AB$3:$CI$3,I$4,$AB45:$CI45) -> 0 | J45: =SUM(E45:I45) -> 0 | K45: =SUMIF($Q$3:$CN$3,K$4,$Q45:$CN45) -> 0 | L45: =SUMIF($Q$3:$CN$3,L$4,$Q45:$CN45) -> 0 | M45: =SUMIF($Q$3:$CN$3,M$4,$Q45:$CN45) -> 0 | N45: =SUMIF($Q$3:$CN$3,N$4,$Q45:$CN45) -> 0
B46: 広告宣伝費 | E46: =SUMIF($AB$3:$CI$3,E$4,$AB46:$CI46) -> 3000000 | F46: =SUMIF($AB$3:$CI$3,F$4,$AB46:$CI46) -> 8000000 | G46: =SUMIF($AB$3:$CI$3,G$4,$AB46:$CI46) -> 20000000 | H46: =SUMIF($AB$3:$CI$3,H$4,$AB46:$CI46) -> 40000000 | I46: =SUMIF($AB$3:$CI$3,I$4,$AB46:$CI46) -> 80000000 | J46: =SUM(E46:I46) -> 151000000 | K46: =SUMIF($Q$3:$CN$3,K$4,$Q46:$CN46) -> 0 | L46: =SUMIF($Q$3:$CN$3,L$4,$Q46:$CN46) -> 0 | M46: =SUMIF($Q$3:$CN$3,M$4,$Q46:$CN46) -> 0 | N46: =SUMIF($Q$3:$CN$3,N$4,$Q46:$CN46) -> 0 | AB46: =SUM(AB47:AB49) -> 250000 | AC46: =SUM(AC47:AC49) -> 250000 | AD46: =SUM(AD47:AD49) -> 250000 | AE46: =SUM(AE47:AE49) -> 250000 | AF46: =SUM(AF47:AF49) -> 250000 | AG46: =SUM(AG47:AG49) -> 250000 | AH46: =SUM(AH47:AH49) -> 250000 | AI46: =SUM(AI47:AI49) -> 250000 | ... CI46: =SUM(CI47:CI49) -> 6666663
C47: 全社 | E47: =SUMIF($AB$3:$CI$3,E$4,$AB47:$CI47) -> 3000000 | F47: =SUMIF($AB$3:$CI$3,F$4,$AB47:$CI47) -> 8000000 | G47: =SUMIF($AB$3:$CI$3,G$4,$AB47:$CI47) -> 20000000 | H47: =SUMIF($AB$3:$CI$3,H$4,$AB47:$CI47) -> 40000000 | I47: =SUMIF($AB$3:$CI$3,I$4,$AB47:$CI47) -> 80000000 | J47: =SUM(E47:I47) -> 151000000 | K47: =SUMIF($Q$3:$CN$3,K$4,$Q47:$CN47) -> 0 | L47: =SUMIF($Q$3:$CN$3,L$4,$Q47:$CN47) -> 0 | M47: =SUMIF($Q$3:$CN$3,M$4,$Q47:$CN47) -> 0 | AB47: =ROUND(INDEX(販管費予算!$E$11:$I$11,MATCH(AB$3,販管費予算!$E$4:$I$4,0))/12,0)+IF(COUNTIF($AB$3:AB$3,AB$3)=12,INDEX(販管費予算!$E$11:$I$11,MATCH(AB$3,販管費予算!$E$4:$I$4,0))-12*ROUND(INDEX(販管費予算!$E$11:$I$11,MATCH(AB$3,販管費予算!$E$4:$I$4,0))/12,0),0) -> 250000 | AC47: =ROUND(INDEX(販管費予算!$E$11:$I$11,MATCH(AC$3,販管費予算!$E$4:$I$4,0))/12,0)+IF(COUNTIF($AB$3:AC$3,AC$3)=12,INDEX(販管費予算!$E$11:$I$11,MATCH(AC$3,販管費予算!$E$4:$I$4,0))-12*ROUND(INDEX(販管費予算!$E$11:$I$11,MATCH(AC$3,販管費予算!$E$4:$I$4,0))/12,0),0) -> 250000 | AD47: =ROUND(INDEX(販管費予算!$E$11:$I$11,MATCH(AD$3,販管費予算!$E$4:$I$4,0))/12,0)+IF(COUNTIF($AB$3:AD$3,AD$3)=12,INDEX(販管費予算!$E$11:$I$11,MATCH(AD$3,販管費予算!$E$4:$I$4,0))-12*ROUND(INDEX(販管費予算!$E$11:$I$11,MATCH(AD$3,販管費予算!$E$4:$I$4,0))/12,0),0) -> 250000 | AE47: =ROUND(INDEX(販管費予算!$E$11:$I$11,MATCH(AE$3,販管費予算!$E$4:$I$4,0))/12,0)+IF(COUNTIF($AB$3:AE$3,AE$3)=12,INDEX(販管費予算!$E$11:$I$11,MATCH(AE$3,販管費予算!$E$4:$I$4,0))-12*ROUND(INDEX(販管費予算!$E$11:$I$11,MATCH(AE$3,販管費予算!$E$4:$I$4,0))/12,0),0) -> 250000 | AF47: =ROUND(INDEX(販管費予算!$E$11:$I$11,MATCH(AF$3,販管費予算!$E$4:$I$4,0))/12,0)+IF(COUNTIF($AB$3:AF$3,AF$3)=12,INDEX(販管費予算!$E$11:$I$11,MATCH(AF$3,販管費予算!$E$4:$I$4,0))-12*ROUND(INDEX(販管費予算!$E$11:$I$11,MATCH(AF$3,販管費予算!$E$4:$I$4,0))/12,0),0) -> 250000 | AG47: =ROUND(INDEX(販管費予算!$E$11:$I$11,MATCH(AG$3,販管費予算!$E$4:$I$4,0))/12,0)+IF(COUNTIF($AB$3:AG$3,AG$3)=12,INDEX(販管費予算!$E$11:$I$11,MATCH(AG$3,販管費予算!$E$4:$I$4,0))-12*ROUND(INDEX(販管費予算!$E$11:$I$11,MATCH(AG$3,販管費予算!$E$4:$I$4,0))/12,0),0) -> 250000 | AH47: =ROUND(INDEX(販管費予算!$E$11:$I$11,MATCH(AH$3,販管費予算!$E$4:$I$4,0))/12,0)+IF(COUNTIF($AB$3:AH$3,AH$3)=12,INDEX(販管費予算!$E$11:$I$11,MATCH(AH$3,販管費予算!$E$4:$I$4,0))-12*ROUND(INDEX(販管費予算!$E$11:$I$11,MATCH(AH$3,販管費予算!$E$4:$I$4,0))/12,0),0) -> 250000 | AI47: =ROUND(INDEX(販管費予算!$E$11:$I$11,MATCH(AI$3,販管費予算!$E$4:$I$4,0))/12,0)+IF(COUNTIF($AB$3:AI$3,AI$3)=12,INDEX(販管費予算!$E$11:$I$11,MATCH(AI$3,販管費予算!$E$4:$I$4,0))-12*ROUND(INDEX(販管費予算!$E$11:$I$11,MATCH(AI$3,販管費予算!$E$4:$I$4,0))/12,0),0) -> 250000 | ... CI47: =ROUND(INDEX(販管費予算!$E$11:$I$11,MATCH(CI$3,販管費予算!$E$4:$I$4,0))/12,0)+IF(COUNTIF($AB$3:CI$3,CI$3)=12,INDEX(販管費予算!$E$11:$I$11,MATCH(CI$3,販管費予算!$E$4:$I$4,0))-12*ROUND(INDEX(販管費予算!$E$11:$I$11,MATCH(CI$3,販管費予算!$E$4:$I$4,0))/12,0),0) -> 6666663
C48: SaaS | E48: =SUMIF($AB$3:$CI$3,E$4,$AB48:$CI48) -> 0 | F48: =SUMIF($AB$3:$CI$3,F$4,$AB48:$CI48) -> 0 | G48: =SUMIF($AB$3:$CI$3,G$4,$AB48:$CI48) -> 0 | H48: =SUMIF($AB$3:$CI$3,H$4,$AB48:$CI48) -> 0 | I48: =SUMIF($AB$3:$CI$3,I$4,$AB48:$CI48) -> 0 | J48: =SUM(E48:I48) -> 0 | K48: =SUMIF($Q$3:$CN$3,K$4,$Q48:$CN48) -> 0 | L48: =SUMIF($Q$3:$CN$3,L$4,$Q48:$CN48) -> 0 | M48: =SUMIF($Q$3:$CN$3,M$4,$Q48:$CN48) -> 0
C49: 事業・組織再生コンサル | E49: =SUMIF($AB$3:$CI$3,E$4,$AB49:$CI49) -> 0 | F49: =SUMIF($AB$3:$CI$3,F$4,$AB49:$CI49) -> 0 | G49: =SUMIF($AB$3:$CI$3,G$4,$AB49:$CI49) -> 0 | H49: =SUMIF($AB$3:$CI$3,H$4,$AB49:$CI49) -> 0 | I49: =SUMIF($AB$3:$CI$3,I$4,$AB49:$CI49) -> 0 | J49: =SUM(E49:I49) -> 0 | K49: =SUMIF($Q$3:$CN$3,K$4,$Q49:$CN49) -> 0 | L49: =SUMIF($Q$3:$CN$3,L$4,$Q49:$CN49) -> 0 | M49: =SUMIF($Q$3:$CN$3,M$4,$Q49:$CN49) -> 0
B50: 荷造包装費 | C50: 全社 | E50: =SUMIF($AB$3:$CI$3,E$4,$AB50:$CI50) -> 0 | F50: =SUMIF($AB$3:$CI$3,F$4,$AB50:$CI50) -> 0 | G50: =SUMIF($AB$3:$CI$3,G$4,$AB50:$CI50) -> 100000 | H50: =SUMIF($AB$3:$CI$3,H$4,$AB50:$CI50) -> 100000 | I50: =SUMIF($AB$3:$CI$3,I$4,$AB50:$CI50) -> 100000 | J50: =SUM(E50:I50) -> 300000 | K50: =SUMIF($Q$3:$CN$3,K$4,$Q50:$CN50) -> 0 | L50: =SUMIF($Q$3:$CN$3,L$4,$Q50:$CN50) -> 0 | M50: =SUMIF($Q$3:$CN$3,M$4,$Q50:$CN50) -> 0 | N50: =SUMIF($Q$3:$CN$3,N$4,$Q50:$CN50) -> 0 | AB50: =ROUND(INDEX(販管費予算!$E$12:$I$12,MATCH(AB$3,販管費予算!$E$4:$I$4,0))/12,0)+IF(COUNTIF($AB$3:AB$3,AB$3)=12,INDEX(販管費予算!$E$12:$I$12,MATCH(AB$3,販管費予算!$E$4:$I$4,0))-12*ROUND(INDEX(販管費予算!$E$12:$I$12,MATCH(AB$3,販管費予算!$E$4:$I$4,0))/12,0),0) -> 0 | AC50: =ROUND(INDEX(販管費予算!$E$12:$I$12,MATCH(AC$3,販管費予算!$E$4:$I$4,0))/12,0)+IF(COUNTIF($AB$3:AC$3,AC$3)=12,INDEX(販管費予算!$E$12:$I$12,MATCH(AC$3,販管費予算!$E$4:$I$4,0))-12*ROUND(INDEX(販管費予算!$E$12:$I$12,MATCH(AC$3,販管費予算!$E$4:$I$4,0))/12,0),0) -> 0 | AD50: =ROUND(INDEX(販管費予算!$E$12:$I$12,MATCH(AD$3,販管費予算!$E$4:$I$4,0))/12,0)+IF(COUNTIF($AB$3:AD$3,AD$3)=12,INDEX(販管費予算!$E$12:$I$12,MATCH(AD$3,販管費予算!$E$4:$I$4,0))-12*ROUND(INDEX(販管費予算!$E$12:$I$12,MATCH(AD$3,販管費予算!$E$4:$I$4,0))/12,0),0) -> 0 | AE50: =ROUND(INDEX(販管費予算!$E$12:$I$12,MATCH(AE$3,販管費予算!$E$4:$I$4,0))/12,0)+IF(COUNTIF($AB$3:AE$3,AE$3)=12,INDEX(販管費予算!$E$12:$I$12,MATCH(AE$3,販管費予算!$E$4:$I$4,0))-12*ROUND(INDEX(販管費予算!$E$12:$I$12,MATCH(AE$3,販管費予算!$E$4:$I$4,0))/12,0),0) -> 0 | AF50: =ROUND(INDEX(販管費予算!$E$12:$I$12,MATCH(AF$3,販管費予算!$E$4:$I$4,0))/12,0)+IF(COUNTIF($AB$3:AF$3,AF$3)=12,INDEX(販管費予算!$E$12:$I$12,MATCH(AF$3,販管費予算!$E$4:$I$4,0))-12*ROUND(INDEX(販管費予算!$E$12:$I$12,MATCH(AF$3,販管費予算!$E$4:$I$4,0))/12,0),0) -> 0 | AG50: =ROUND(INDEX(販管費予算!$E$12:$I$12,MATCH(AG$3,販管費予算!$E$4:$I$4,0))/12,0)+IF(COUNTIF($AB$3:AG$3,AG$3)=12,INDEX(販管費予算!$E$12:$I$12,MATCH(AG$3,販管費予算!$E$4:$I$4,0))-12*ROUND(INDEX(販管費予算!$E$12:$I$12,MATCH(AG$3,販管費予算!$E$4:$I$4,0))/12,0),0) -> 0 | AH50: =ROUND(INDEX(販管費予算!$E$12:$I$12,MATCH(AH$3,販管費予算!$E$4:$I$4,0))/12,0)+IF(COUNTIF($AB$3:AH$3,AH$3)=12,INDEX(販管費予算!$E$12:$I$12,MATCH(AH$3,販管費予算!$E$4:$I$4,0))-12*ROUND(INDEX(販管費予算!$E$12:$I$12,MATCH(AH$3,販管費予算!$E$4:$I$4,0))/12,0),0) -> 0 | AI50: =ROUND(INDEX(販管費予算!$E$12:$I$12,MATCH(AI$3,販管費予算!$E$4:$I$4,0))/12,0)+IF(COUNTIF($AB$3:AI$3,AI$3)=12,INDEX(販管費予算!$E$12:$I$12,MATCH(AI$3,販管費予算!$E$4:$I$4,0))-12*ROUND(INDEX(販管費予算!$E$12:$I$12,MATCH(AI$3,販管費予算!$E$4:$I$4,0))/12,0),0) -> 0 | ... CI50: =ROUND(INDEX(販管費予算!$E$12:$I$12,MATCH(CI$3,販管費予算!$E$4:$I$4,0))/12,0)+IF(COUNTIF($AB$3:CI$3,CI$3)=12,INDEX(販管費予算!$E$12:$I$12,MATCH(CI$3,販管費予算!$E$4:$I$4,0))-12*ROUND(INDEX(販管費予算!$E$12:$I$12,MATCH(CI$3,販管費予算!$E$4:$I$4,0))/12,0),0) -> 8337
B51: 外注費 | C51: 全社 | E51: =SUMIF($AB$3:$CI$3,E$4,$AB51:$CI51) -> 6000000 | F51: =SUMIF($AB$3:$CI$3,F$4,$AB51:$CI51) -> 12000000 | G51: =SUMIF($AB$3:$CI$3,G$4,$AB51:$CI51) -> 18000000 | H51: =SUMIF($AB$3:$CI$3,H$4,$AB51:$CI51) -> 24000000 | I51: =SUMIF($AB$3:$CI$3,I$4,$AB51:$CI51) -> 30000000 | J51: =SUM(E51:I51) -> 90000000 | K51: =SUMIF($Q$3:$CN$3,K$4,$Q51:$CN51) -> 0 | L51: =SUMIF($Q$3:$CN$3,L$4,$Q51:$CN51) -> 0 | M51: =SUMIF($Q$3:$CN$3,M$4,$Q51:$CN51) -> 0 | N51: =SUMIF($Q$3:$CN$3,N$4,$Q51:$CN51) -> 0 | AB51: =ROUND(INDEX(販管費予算!$E$13:$I$13,MATCH(AB$3,販管費予算!$E$4:$I$4,0))/12,0)+IF(COUNTIF($AB$3:AB$3,AB$3)=12,INDEX(販管費予算!$E$13:$I$13,MATCH(AB$3,販管費予算!$E$4:$I$4,0))-12*ROUND(INDEX(販管費予算!$E$13:$I$13,MATCH(AB$3,販管費予算!$E$4:$I$4,0))/12,0),0) -> 500000 | AC51: =ROUND(INDEX(販管費予算!$E$13:$I$13,MATCH(AC$3,販管費予算!$E$4:$I$4,0))/12,0)+IF(COUNTIF($AB$3:AC$3,AC$3)=12,INDEX(販管費予算!$E$13:$I$13,MATCH(AC$3,販管費予算!$E$4:$I$4,0))-12*ROUND(INDEX(販管費予算!$E$13:$I$13,MATCH(AC$3,販管費予算!$E$4:$I$4,0))/12,0),0) -> 500000 | AD51: =ROUND(INDEX(販管費予算!$E$13:$I$13,MATCH(AD$3,販管費予算!$E$4:$I$4,0))/12,0)+IF(COUNTIF($AB$3:AD$3,AD$3)=12,INDEX(販管費予算!$E$13:$I$13,MATCH(AD$3,販管費予算!$E$4:$I$4,0))-12*ROUND(INDEX(販管費予算!$E$13:$I$13,MATCH(AD$3,販管費予算!$E$4:$I$4,0))/12,0),0) -> 500000 | AE51: =ROUND(INDEX(販管費予算!$E$13:$I$13,MATCH(AE$3,販管費予算!$E$4:$I$4,0))/12,0)+IF(COUNTIF($AB$3:AE$3,AE$3)=12,INDEX(販管費予算!$E$13:$I$13,MATCH(AE$3,販管費予算!$E$4:$I$4,0))-12*ROUND(INDEX(販管費予算!$E$13:$I$13,MATCH(AE$3,販管費予算!$E$4:$I$4,0))/12,0),0) -> 500000 | AF51: =ROUND(INDEX(販管費予算!$E$13:$I$13,MATCH(AF$3,販管費予算!$E$4:$I$4,0))/12,0)+IF(COUNTIF($AB$3:AF$3,AF$3)=12,INDEX(販管費予算!$E$13:$I$13,MATCH(AF$3,販管費予算!$E$4:$I$4,0))-12*ROUND(INDEX(販管費予算!$E$13:$I$13,MATCH(AF$3,販管費予算!$E$4:$I$4,0))/12,0),0) -> 500000 | AG51: =ROUND(INDEX(販管費予算!$E$13:$I$13,MATCH(AG$3,販管費予算!$E$4:$I$4,0))/12,0)+IF(COUNTIF($AB$3:AG$3,AG$3)=12,INDEX(販管費予算!$E$13:$I$13,MATCH(AG$3,販管費予算!$E$4:$I$4,0))-12*ROUND(INDEX(販管費予算!$E$13:$I$13,MATCH(AG$3,販管費予算!$E$4:$I$4,0))/12,0),0) -> 500000 | AH51: =ROUND(INDEX(販管費予算!$E$13:$I$13,MATCH(AH$3,販管費予算!$E$4:$I$4,0))/12,0)+IF(COUNTIF($AB$3:AH$3,AH$3)=12,INDEX(販管費予算!$E$13:$I$13,MATCH(AH$3,販管費予算!$E$4:$I$4,0))-12*ROUND(INDEX(販管費予算!$E$13:$I$13,MATCH(AH$3,販管費予算!$E$4:$I$4,0))/12,0),0) -> 500000 | AI51: =ROUND(INDEX(販管費予算!$E$13:$I$13,MATCH(AI$3,販管費予算!$E$4:$I$4,0))/12,0)+IF(COUNTIF($AB$3:AI$3,AI$3)=12,INDEX(販管費予算!$E$13:$I$13,MATCH(AI$3,販管費予算!$E$4:$I$4,0))-12*ROUND(INDEX(販管費予算!$E$13:$I$13,MATCH(AI$3,販管費予算!$E$4:$I$4,0))/12,0),0) -> 500000 | ... CI51: =ROUND(INDEX(販管費予算!$E$13:$I$13,MATCH(CI$3,販管費予算!$E$4:$I$4,0))/12,0)+IF(COUNTIF($AB$3:CI$3,CI$3)=12,INDEX(販管費予算!$E$13:$I$13,MATCH(CI$3,販管費予算!$E$4:$I$4,0))-12*ROUND(INDEX(販管費予算!$E$13:$I$13,MATCH(CI$3,販管費予算!$E$4:$I$4,0))/12,0),0) -> 2500000
B52: 交際費 | C52: 全社 | E52: =SUMIF($AB$3:$CI$3,E$4,$AB52:$CI52) -> 300000 | F52: =SUMIF($AB$3:$CI$3,F$4,$AB52:$CI52) -> 500000 | G52: =SUMIF($AB$3:$CI$3,G$4,$AB52:$CI52) -> 1000000 | H52: =SUMIF($AB$3:$CI$3,H$4,$AB52:$CI52) -> 1500000 | I52: =SUMIF($AB$3:$CI$3,I$4,$AB52:$CI52) -> 2500000 | J52: =SUM(E52:I52) -> 5800000 | K52: =SUMIF($Q$3:$CN$3,K$4,$Q52:$CN52) -> 0 | L52: =SUMIF($Q$3:$CN$3,L$4,$Q52:$CN52) -> 0 | M52: =SUMIF($Q$3:$CN$3,M$4,$Q52:$CN52) -> 0 | N52: =SUMIF($Q$3:$CN$3,N$4,$Q52:$CN52) -> 0 | AB52: =ROUND(INDEX(販管費予算!$E$14:$I$14,MATCH(AB$3,販管費予算!$E$4:$I$4,0))/12,0)+IF(COUNTIF($AB$3:AB$3,AB$3)=12,INDEX(販管費予算!$E$14:$I$14,MATCH(AB$3,販管費予算!$E$4:$I$4,0))-12*ROUND(INDEX(販管費予算!$E$14:$I$14,MATCH(AB$3,販管費予算!$E$4:$I$4,0))/12,0),0) -> 25000 | AC52: =ROUND(INDEX(販管費予算!$E$14:$I$14,MATCH(AC$3,販管費予算!$E$4:$I$4,0))/12,0)+IF(COUNTIF($AB$3:AC$3,AC$3)=12,INDEX(販管費予算!$E$14:$I$14,MATCH(AC$3,販管費予算!$E$4:$I$4,0))-12*ROUND(INDEX(販管費予算!$E$14:$I$14,MATCH(AC$3,販管費予算!$E$4:$I$4,0))/12,0),0) -> 25000 | AD52: =ROUND(INDEX(販管費予算!$E$14:$I$14,MATCH(AD$3,販管費予算!$E$4:$I$4,0))/12,0)+IF(COUNTIF($AB$3:AD$3,AD$3)=12,INDEX(販管費予算!$E$14:$I$14,MATCH(AD$3,販管費予算!$E$4:$I$4,0))-12*ROUND(INDEX(販管費予算!$E$14:$I$14,MATCH(AD$3,販管費予算!$E$4:$I$4,0))/12,0),0) -> 25000 | AE52: =ROUND(INDEX(販管費予算!$E$14:$I$14,MATCH(AE$3,販管費予算!$E$4:$I$4,0))/12,0)+IF(COUNTIF($AB$3:AE$3,AE$3)=12,INDEX(販管費予算!$E$14:$I$14,MATCH(AE$3,販管費予算!$E$4:$I$4,0))-12*ROUND(INDEX(販管費予算!$E$14:$I$14,MATCH(AE$3,販管費予算!$E$4:$I$4,0))/12,0),0) -> 25000 | AF52: =ROUND(INDEX(販管費予算!$E$14:$I$14,MATCH(AF$3,販管費予算!$E$4:$I$4,0))/12,0)+IF(COUNTIF($AB$3:AF$3,AF$3)=12,INDEX(販管費予算!$E$14:$I$14,MATCH(AF$3,販管費予算!$E$4:$I$4,0))-12*ROUND(INDEX(販管費予算!$E$14:$I$14,MATCH(AF$3,販管費予算!$E$4:$I$4,0))/12,0),0) -> 25000 | AG52: =ROUND(INDEX(販管費予算!$E$14:$I$14,MATCH(AG$3,販管費予算!$E$4:$I$4,0))/12,0)+IF(COUNTIF($AB$3:AG$3,AG$3)=12,INDEX(販管費予算!$E$14:$I$14,MATCH(AG$3,販管費予算!$E$4:$I$4,0))-12*ROUND(INDEX(販管費予算!$E$14:$I$14,MATCH(AG$3,販管費予算!$E$4:$I$4,0))/12,0),0) -> 25000 | AH52: =ROUND(INDEX(販管費予算!$E$14:$I$14,MATCH(AH$3,販管費予算!$E$4:$I$4,0))/12,0)+IF(COUNTIF($AB$3:AH$3,AH$3)=12,INDEX(販管費予算!$E$14:$I$14,MATCH(AH$3,販管費予算!$E$4:$I$4,0))-12*ROUND(INDEX(販管費予算!$E$14:$I$14,MATCH(AH$3,販管費予算!$E$4:$I$4,0))/12,0),0) -> 25000 | AI52: =ROUND(INDEX(販管費予算!$E$14:$I$14,MATCH(AI$3,販管費予算!$E$4:$I$4,0))/12,0)+IF(COUNTIF($AB$3:AI$3,AI$3)=12,INDEX(販管費予算!$E$14:$I$14,MATCH(AI$3,販管費予算!$E$4:$I$4,0))-12*ROUND(INDEX(販管費予算!$E$14:$I$14,MATCH(AI$3,販管費予算!$E$4:$I$4,0))/12,0),0) -> 25000 | ... CI52: =ROUND(INDEX(販管費予算!$E$14:$I$14,MATCH(CI$3,販管費予算!$E$4:$I$4,0))/12,0)+IF(COUNTIF($AB$3:CI$3,CI$3)=12,INDEX(販管費予算!$E$14:$I$14,MATCH(CI$3,販管費予算!$E$4:$I$4,0))-12*ROUND(INDEX(販管費予算!$E$14:$I$14,MATCH(CI$3,販管費予算!$E$4:$I$4,0))/12,0),0) -> 208337
B53: 会議費 | C53: 全社 | E53: =SUMIF($AB$3:$CI$3,E$4,$AB53:$CI53) -> 200000 | F53: =SUMIF($AB$3:$CI$3,F$4,$AB53:$CI53) -> 300000 | G53: =SUMIF($AB$3:$CI$3,G$4,$AB53:$CI53) -> 500000 | H53: =SUMIF($AB$3:$CI$3,H$4,$AB53:$CI53) -> 1000000 | I53: =SUMIF($AB$3:$CI$3,I$4,$AB53:$CI53) -> 2000000 | J53: =SUM(E53:I53) -> 4000000 | K53: =SUMIF($Q$3:$CN$3,K$4,$Q53:$CN53) -> 0 | L53: =SUMIF($Q$3:$CN$3,L$4,$Q53:$CN53) -> 0 | M53: =SUMIF($Q$3:$CN$3,M$4,$Q53:$CN53) -> 0 | N53: =SUMIF($Q$3:$CN$3,N$4,$Q53:$CN53) -> 0 | AB53: =ROUND(INDEX(販管費予算!$E$15:$I$15,MATCH(AB$3,販管費予算!$E$4:$I$4,0))/12,0)+IF(COUNTIF($AB$3:AB$3,AB$3)=12,INDEX(販管費予算!$E$15:$I$15,MATCH(AB$3,販管費予算!$E$4:$I$4,0))-12*ROUND(INDEX(販管費予算!$E$15:$I$15,MATCH(AB$3,販管費予算!$E$4:$I$4,0))/12,0),0) -> 16667 | AC53: =ROUND(INDEX(販管費予算!$E$15:$I$15,MATCH(AC$3,販管費予算!$E$4:$I$4,0))/12,0)+IF(COUNTIF($AB$3:AC$3,AC$3)=12,INDEX(販管費予算!$E$15:$I$15,MATCH(AC$3,販管費予算!$E$4:$I$4,0))-12*ROUND(INDEX(販管費予算!$E$15:$I$15,MATCH(AC$3,販管費予算!$E$4:$I$4,0))/12,0),0) -> 16667 | AD53: =ROUND(INDEX(販管費予算!$E$15:$I$15,MATCH(AD$3,販管費予算!$E$4:$I$4,0))/12,0)+IF(COUNTIF($AB$3:AD$3,AD$3)=12,INDEX(販管費予算!$E$15:$I$15,MATCH(AD$3,販管費予算!$E$4:$I$4,0))-12*ROUND(INDEX(販管費予算!$E$15:$I$15,MATCH(AD$3,販管費予算!$E$4:$I$4,0))/12,0),0) -> 16667 | AE53: =ROUND(INDEX(販管費予算!$E$15:$I$15,MATCH(AE$3,販管費予算!$E$4:$I$4,0))/12,0)+IF(COUNTIF($AB$3:AE$3,AE$3)=12,INDEX(販管費予算!$E$15:$I$15,MATCH(AE$3,販管費予算!$E$4:$I$4,0))-12*ROUND(INDEX(販管費予算!$E$15:$I$15,MATCH(AE$3,販管費予算!$E$4:$I$4,0))/12,0),0) -> 16667 | AF53: =ROUND(INDEX(販管費予算!$E$15:$I$15,MATCH(AF$3,販管費予算!$E$4:$I$4,0))/12,0)+IF(COUNTIF($AB$3:AF$3,AF$3)=12,INDEX(販管費予算!$E$15:$I$15,MATCH(AF$3,販管費予算!$E$4:$I$4,0))-12*ROUND(INDEX(販管費予算!$E$15:$I$15,MATCH(AF$3,販管費予算!$E$4:$I$4,0))/12,0),0) -> 16667 | AG53: =ROUND(INDEX(販管費予算!$E$15:$I$15,MATCH(AG$3,販管費予算!$E$4:$I$4,0))/12,0)+IF(COUNTIF($AB$3:AG$3,AG$3)=12,INDEX(販管費予算!$E$15:$I$15,MATCH(AG$3,販管費予算!$E$4:$I$4,0))-12*ROUND(INDEX(販管費予算!$E$15:$I$15,MATCH(AG$3,販管費予算!$E$4:$I$4,0))/12,0),0) -> 16667 | AH53: =ROUND(INDEX(販管費予算!$E$15:$I$15,MATCH(AH$3,販管費予算!$E$4:$I$4,0))/12,0)+IF(COUNTIF($AB$3:AH$3,AH$3)=12,INDEX(販管費予算!$E$15:$I$15,MATCH(AH$3,販管費予算!$E$4:$I$4,0))-12*ROUND(INDEX(販管費予算!$E$15:$I$15,MATCH(AH$3,販管費予算!$E$4:$I$4,0))/12,0),0) -> 16667 | AI53: =ROUND(INDEX(販管費予算!$E$15:$I$15,MATCH(AI$3,販管費予算!$E$4:$I$4,0))/12,0)+IF(COUNTIF($AB$3:AI$3,AI$3)=12,INDEX(販管費予算!$E$15:$I$15,MATCH(AI$3,販管費予算!$E$4:$I$4,0))-12*ROUND(INDEX(販管費予算!$E$15:$I$15,MATCH(AI$3,販管費予算!$E$4:$I$4,0))/12,0),0) -> 16667 | ... CI53: =ROUND(INDEX(販管費予算!$E$15:$I$15,MATCH(CI$3,販管費予算!$E$4:$I$4,0))/12,0)+IF(COUNTIF($AB$3:CI$3,CI$3)=12,INDEX(販管費予算!$E$15:$I$15,MATCH(CI$3,販管費予算!$E$4:$I$4,0))-12*ROUND(INDEX(販管費予算!$E$15:$I$15,MATCH(CI$3,販管費予算!$E$4:$I$4,0))/12,0),0) -> 166663
B54: 旅費交通費 | E54: =SUMIF($AB$3:$CI$3,E$4,$AB54:$CI54) -> 1000000 | F54: =SUMIF($AB$3:$CI$3,F$4,$AB54:$CI54) -> 2000000 | G54: =SUMIF($AB$3:$CI$3,G$4,$AB54:$CI54) -> 4000000 | H54: =SUMIF($AB$3:$CI$3,H$4,$AB54:$CI54) -> 6000000 | I54: =SUMIF($AB$3:$CI$3,I$4,$AB54:$CI54) -> 10000000 | J54: =SUM(E54:I54) -> 23000000 | K54: =SUMIF($Q$3:$CN$3,K$4,$Q54:$CN54) -> 0 | L54: =SUMIF($Q$3:$CN$3,L$4,$Q54:$CN54) -> 0 | M54: =SUMIF($Q$3:$CN$3,M$4,$Q54:$CN54) -> 0 | N54: =SUMIF($Q$3:$CN$3,N$4,$Q54:$CN54) -> 0 | AB54: =SUM(AB55:AB57) -> 83333 | AC54: =SUM(AC55:AC57) -> 83333 | AD54: =SUM(AD55:AD57) -> 83333 | AE54: =SUM(AE55:AE57) -> 83333 | AF54: =SUM(AF55:AF57) -> 83333 | AG54: =SUM(AG55:AG57) -> 83333 | AH54: =SUM(AH55:AH57) -> 83333 | AI54: =SUM(AI55:AI57) -> 83333 | ... CI54: =SUM(CI55:CI57) -> 833337
C55: 全社 | E55: =SUMIF($AB$3:$CI$3,E$4,$AB55:$CI55) -> 1000000 | F55: =SUMIF($AB$3:$CI$3,F$4,$AB55:$CI55) -> 2000000 | G55: =SUMIF($AB$3:$CI$3,G$4,$AB55:$CI55) -> 4000000 | H55: =SUMIF($AB$3:$CI$3,H$4,$AB55:$CI55) -> 6000000 | I55: =SUMIF($AB$3:$CI$3,I$4,$AB55:$CI55) -> 10000000 | J55: =SUM(E55:I55) -> 23000000 | K55: =SUMIF($Q$3:$CN$3,K$4,$Q55:$CN55) -> 0 | L55: =SUMIF($Q$3:$CN$3,L$4,$Q55:$CN55) -> 0 | M55: =SUMIF($Q$3:$CN$3,M$4,$Q55:$CN55) -> 0 | AB55: =ROUND(INDEX(販管費予算!$E$16:$I$16,MATCH(AB$3,販管費予算!$E$4:$I$4,0))/12,0)+IF(COUNTIF($AB$3:AB$3,AB$3)=12,INDEX(販管費予算!$E$16:$I$16,MATCH(AB$3,販管費予算!$E$4:$I$4,0))-12*ROUND(INDEX(販管費予算!$E$16:$I$16,MATCH(AB$3,販管費予算!$E$4:$I$4,0))/12,0),0) -> 83333 | AC55: =ROUND(INDEX(販管費予算!$E$16:$I$16,MATCH(AC$3,販管費予算!$E$4:$I$4,0))/12,0)+IF(COUNTIF($AB$3:AC$3,AC$3)=12,INDEX(販管費予算!$E$16:$I$16,MATCH(AC$3,販管費予算!$E$4:$I$4,0))-12*ROUND(INDEX(販管費予算!$E$16:$I$16,MATCH(AC$3,販管費予算!$E$4:$I$4,0))/12,0),0) -> 83333 | AD55: =ROUND(INDEX(販管費予算!$E$16:$I$16,MATCH(AD$3,販管費予算!$E$4:$I$4,0))/12,0)+IF(COUNTIF($AB$3:AD$3,AD$3)=12,INDEX(販管費予算!$E$16:$I$16,MATCH(AD$3,販管費予算!$E$4:$I$4,0))-12*ROUND(INDEX(販管費予算!$E$16:$I$16,MATCH(AD$3,販管費予算!$E$4:$I$4,0))/12,0),0) -> 83333 | AE55: =ROUND(INDEX(販管費予算!$E$16:$I$16,MATCH(AE$3,販管費予算!$E$4:$I$4,0))/12,0)+IF(COUNTIF($AB$3:AE$3,AE$3)=12,INDEX(販管費予算!$E$16:$I$16,MATCH(AE$3,販管費予算!$E$4:$I$4,0))-12*ROUND(INDEX(販管費予算!$E$16:$I$16,MATCH(AE$3,販管費予算!$E$4:$I$4,0))/12,0),0) -> 83333 | AF55: =ROUND(INDEX(販管費予算!$E$16:$I$16,MATCH(AF$3,販管費予算!$E$4:$I$4,0))/12,0)+IF(COUNTIF($AB$3:AF$3,AF$3)=12,INDEX(販管費予算!$E$16:$I$16,MATCH(AF$3,販管費予算!$E$4:$I$4,0))-12*ROUND(INDEX(販管費予算!$E$16:$I$16,MATCH(AF$3,販管費予算!$E$4:$I$4,0))/12,0),0) -> 83333 | AG55: =ROUND(INDEX(販管費予算!$E$16:$I$16,MATCH(AG$3,販管費予算!$E$4:$I$4,0))/12,0)+IF(COUNTIF($AB$3:AG$3,AG$3)=12,INDEX(販管費予算!$E$16:$I$16,MATCH(AG$3,販管費予算!$E$4:$I$4,0))-12*ROUND(INDEX(販管費予算!$E$16:$I$16,MATCH(AG$3,販管費予算!$E$4:$I$4,0))/12,0),0) -> 83333 | AH55: =ROUND(INDEX(販管費予算!$E$16:$I$16,MATCH(AH$3,販管費予算!$E$4:$I$4,0))/12,0)+IF(COUNTIF($AB$3:AH$3,AH$3)=12,INDEX(販管費予算!$E$16:$I$16,MATCH(AH$3,販管費予算!$E$4:$I$4,0))-12*ROUND(INDEX(販管費予算!$E$16:$I$16,MATCH(AH$3,販管費予算!$E$4:$I$4,0))/12,0),0) -> 83333 | AI55: =ROUND(INDEX(販管費予算!$E$16:$I$16,MATCH(AI$3,販管費予算!$E$4:$I$4,0))/12,0)+IF(COUNTIF($AB$3:AI$3,AI$3)=12,INDEX(販管費予算!$E$16:$I$16,MATCH(AI$3,販管費予算!$E$4:$I$4,0))-12*ROUND(INDEX(販管費予算!$E$16:$I$16,MATCH(AI$3,販管費予算!$E$4:$I$4,0))/12,0),0) -> 83333 | ... CI55: =ROUND(INDEX(販管費予算!$E$16:$I$16,MATCH(CI$3,販管費予算!$E$4:$I$4,0))/12,0)+IF(COUNTIF($AB$3:CI$3,CI$3)=12,INDEX(販管費予算!$E$16:$I$16,MATCH(CI$3,販管費予算!$E$4:$I$4,0))-12*ROUND(INDEX(販管費予算!$E$16:$I$16,MATCH(CI$3,販管費予算!$E$4:$I$4,0))/12,0),0) -> 833337
C56: SaaS | E56: =SUMIF($AB$3:$CI$3,E$4,$AB56:$CI56) -> 0 | F56: =SUMIF($AB$3:$CI$3,F$4,$AB56:$CI56) -> 0 | G56: =SUMIF($AB$3:$CI$3,G$4,$AB56:$CI56) -> 0 | H56: =SUMIF($AB$3:$CI$3,H$4,$AB56:$CI56) -> 0 | I56: =SUMIF($AB$3:$CI$3,I$4,$AB56:$CI56) -> 0 | J56: =SUM(E56:I56) -> 0
C57: 事業・組織再生コンサル | E57: =SUMIF($AB$3:$CI$3,E$4,$AB57:$CI57) -> 0 | F57: =SUMIF($AB$3:$CI$3,F$4,$AB57:$CI57) -> 0 | G57: =SUMIF($AB$3:$CI$3,G$4,$AB57:$CI57) -> 0 | H57: =SUMIF($AB$3:$CI$3,H$4,$AB57:$CI57) -> 0 | I57: =SUMIF($AB$3:$CI$3,I$4,$AB57:$CI57) -> 0 | J57: =SUM(E57:I57) -> 0 | K57: =SUMIF($Q$3:$CN$3,K$4,$Q57:$CN57) -> 0 | L57: =SUMIF($Q$3:$CN$3,L$4,$Q57:$CN57) -> 0 | M57: =SUMIF($Q$3:$CN$3,M$4,$Q57:$CN57) -> 0
B58: 通信費 | E58: =SUMIF($AB$3:$CI$3,E$4,$AB58:$CI58) -> 300000 | F58: =SUMIF($AB$3:$CI$3,F$4,$AB58:$CI58) -> 600000 | G58: =SUMIF($AB$3:$CI$3,G$4,$AB58:$CI58) -> 900000 | H58: =SUMIF($AB$3:$CI$3,H$4,$AB58:$CI58) -> 1500000 | I58: =SUMIF($AB$3:$CI$3,I$4,$AB58:$CI58) -> 2500000 | J58: =SUM(E58:I58) -> 5800000 | AB58: =SUM(AB59:AB60) -> 25000 | AC58: =SUM(AC59:AC60) -> 25000 | AD58: =SUM(AD59:AD60) -> 25000 | AE58: =SUM(AE59:AE60) -> 25000 | AF58: =SUM(AF59:AF60) -> 25000 | AG58: =SUM(AG59:AG60) -> 25000 | AH58: =SUM(AH59:AH60) -> 25000 | AI58: =SUM(AI59:AI60) -> 25000 | ... CI58: =SUM(CI59:CI60) -> 208337
C59: 全社 | E59: =SUMIF($AB$3:$CI$3,E$4,$AB59:$CI59) -> 300000 | F59: =SUMIF($AB$3:$CI$3,F$4,$AB59:$CI59) -> 600000 | G59: =SUMIF($AB$3:$CI$3,G$4,$AB59:$CI59) -> 900000 | H59: =SUMIF($AB$3:$CI$3,H$4,$AB59:$CI59) -> 1500000 | I59: =SUMIF($AB$3:$CI$3,I$4,$AB59:$CI59) -> 2500000 | J59: =SUM(E59:I59) -> 5800000 | K59: =SUMIF($Q$3:$CN$3,K$4,$Q59:$CN59) -> 0 | L59: =SUMIF($Q$3:$CN$3,L$4,$Q59:$CN59) -> 0 | M59: =SUMIF($Q$3:$CN$3,M$4,$Q59:$CN59) -> 0 | N59: =SUMIF($Q$3:$CN$3,N$4,$Q59:$CN59) -> 0 | AB59: =ROUND(INDEX(販管費予算!$E$17:$I$17,MATCH(AB$3,販管費予算!$E$4:$I$4,0))/12,0)+IF(COUNTIF($AB$3:AB$3,AB$3)=12,INDEX(販管費予算!$E$17:$I$17,MATCH(AB$3,販管費予算!$E$4:$I$4,0))-12*ROUND(INDEX(販管費予算!$E$17:$I$17,MATCH(AB$3,販管費予算!$E$4:$I$4,0))/12,0),0) -> 25000 | AC59: =ROUND(INDEX(販管費予算!$E$17:$I$17,MATCH(AC$3,販管費予算!$E$4:$I$4,0))/12,0)+IF(COUNTIF($AB$3:AC$3,AC$3)=12,INDEX(販管費予算!$E$17:$I$17,MATCH(AC$3,販管費予算!$E$4:$I$4,0))-12*ROUND(INDEX(販管費予算!$E$17:$I$17,MATCH(AC$3,販管費予算!$E$4:$I$4,0))/12,0),0) -> 25000 | AD59: =ROUND(INDEX(販管費予算!$E$17:$I$17,MATCH(AD$3,販管費予算!$E$4:$I$4,0))/12,0)+IF(COUNTIF($AB$3:AD$3,AD$3)=12,INDEX(販管費予算!$E$17:$I$17,MATCH(AD$3,販管費予算!$E$4:$I$4,0))-12*ROUND(INDEX(販管費予算!$E$17:$I$17,MATCH(AD$3,販管費予算!$E$4:$I$4,0))/12,0),0) -> 25000 | AE59: =ROUND(INDEX(販管費予算!$E$17:$I$17,MATCH(AE$3,販管費予算!$E$4:$I$4,0))/12,0)+IF(COUNTIF($AB$3:AE$3,AE$3)=12,INDEX(販管費予算!$E$17:$I$17,MATCH(AE$3,販管費予算!$E$4:$I$4,0))-12*ROUND(INDEX(販管費予算!$E$17:$I$17,MATCH(AE$3,販管費予算!$E$4:$I$4,0))/12,0),0) -> 25000 | AF59: =ROUND(INDEX(販管費予算!$E$17:$I$17,MATCH(AF$3,販管費予算!$E$4:$I$4,0))/12,0)+IF(COUNTIF($AB$3:AF$3,AF$3)=12,INDEX(販管費予算!$E$17:$I$17,MATCH(AF$3,販管費予算!$E$4:$I$4,0))-12*ROUND(INDEX(販管費予算!$E$17:$I$17,MATCH(AF$3,販管費予算!$E$4:$I$4,0))/12,0),0) -> 25000 | AG59: =ROUND(INDEX(販管費予算!$E$17:$I$17,MATCH(AG$3,販管費予算!$E$4:$I$4,0))/12,0)+IF(COUNTIF($AB$3:AG$3,AG$3)=12,INDEX(販管費予算!$E$17:$I$17,MATCH(AG$3,販管費予算!$E$4:$I$4,0))-12*ROUND(INDEX(販管費予算!$E$17:$I$17,MATCH(AG$3,販管費予算!$E$4:$I$4,0))/12,0),0) -> 25000 | AH59: =ROUND(INDEX(販管費予算!$E$17:$I$17,MATCH(AH$3,販管費予算!$E$4:$I$4,0))/12,0)+IF(COUNTIF($AB$3:AH$3,AH$3)=12,INDEX(販管費予算!$E$17:$I$17,MATCH(AH$3,販管費予算!$E$4:$I$4,0))-12*ROUND(INDEX(販管費予算!$E$17:$I$17,MATCH(AH$3,販管費予算!$E$4:$I$4,0))/12,0),0) -> 25000 | AI59: =ROUND(INDEX(販管費予算!$E$17:$I$17,MATCH(AI$3,販管費予算!$E$4:$I$4,0))/12,0)+IF(COUNTIF($AB$3:AI$3,AI$3)=12,INDEX(販管費予算!$E$17:$I$17,MATCH(AI$3,販管費予算!$E$4:$I$4,0))-12*ROUND(INDEX(販管費予算!$E$17:$I$17,MATCH(AI$3,販管費予算!$E$4:$I$4,0))/12,0),0) -> 25000 | ... CI59: =ROUND(INDEX(販管費予算!$E$17:$I$17,MATCH(CI$3,販管費予算!$E$4:$I$4,0))/12,0)+IF(COUNTIF($AB$3:CI$3,CI$3)=12,INDEX(販管費予算!$E$17:$I$17,MATCH(CI$3,販管費予算!$E$4:$I$4,0))-12*ROUND(INDEX(販管費予算!$E$17:$I$17,MATCH(CI$3,販管費予算!$E$4:$I$4,0))/12,0),0) -> 208337
C60: プロダクト | E60: =SUMIF($AB$3:$CI$3,E$4,$AB60:$CI60) -> 0 | F60: =SUMIF($AB$3:$CI$3,F$4,$AB60:$CI60) -> 0 | G60: =SUMIF($AB$3:$CI$3,G$4,$AB60:$CI60) -> 0 | H60: =SUMIF($AB$3:$CI$3,H$4,$AB60:$CI60) -> 0 | I60: =SUMIF($AB$3:$CI$3,I$4,$AB60:$CI60) -> 0 | J60: =SUM(E60:I60) -> 0
B61: 消耗品費 | C61: 全社 | E61: =SUMIF($AB$3:$CI$3,E$4,$AB61:$CI61) -> 200000 | F61: =SUMIF($AB$3:$CI$3,F$4,$AB61:$CI61) -> 400000 | G61: =SUMIF($AB$3:$CI$3,G$4,$AB61:$CI61) -> 600000 | H61: =SUMIF($AB$3:$CI$3,H$4,$AB61:$CI61) -> 1000000 | I61: =SUMIF($AB$3:$CI$3,I$4,$AB61:$CI61) -> 2000000 | J61: =SUM(E61:I61) -> 4200000 | K61: =SUMIF($Q$3:$CN$3,K$4,$Q61:$CN61) -> 0 | L61: =SUMIF($Q$3:$CN$3,L$4,$Q61:$CN61) -> 0 | M61: =SUMIF($Q$3:$CN$3,M$4,$Q61:$CN61) -> 0 | N61: =SUMIF($Q$3:$CN$3,N$4,$Q61:$CN61) -> 0 | AB61: =ROUND(INDEX(販管費予算!$E$18:$I$18,MATCH(AB$3,販管費予算!$E$4:$I$4,0))/12,0)+IF(COUNTIF($AB$3:AB$3,AB$3)=12,INDEX(販管費予算!$E$18:$I$18,MATCH(AB$3,販管費予算!$E$4:$I$4,0))-12*ROUND(INDEX(販管費予算!$E$18:$I$18,MATCH(AB$3,販管費予算!$E$4:$I$4,0))/12,0),0) -> 16667 | AC61: =ROUND(INDEX(販管費予算!$E$18:$I$18,MATCH(AC$3,販管費予算!$E$4:$I$4,0))/12,0)+IF(COUNTIF($AB$3:AC$3,AC$3)=12,INDEX(販管費予算!$E$18:$I$18,MATCH(AC$3,販管費予算!$E$4:$I$4,0))-12*ROUND(INDEX(販管費予算!$E$18:$I$18,MATCH(AC$3,販管費予算!$E$4:$I$4,0))/12,0),0) -> 16667 | AD61: =ROUND(INDEX(販管費予算!$E$18:$I$18,MATCH(AD$3,販管費予算!$E$4:$I$4,0))/12,0)+IF(COUNTIF($AB$3:AD$3,AD$3)=12,INDEX(販管費予算!$E$18:$I$18,MATCH(AD$3,販管費予算!$E$4:$I$4,0))-12*ROUND(INDEX(販管費予算!$E$18:$I$18,MATCH(AD$3,販管費予算!$E$4:$I$4,0))/12,0),0) -> 16667 | AE61: =ROUND(INDEX(販管費予算!$E$18:$I$18,MATCH(AE$3,販管費予算!$E$4:$I$4,0))/12,0)+IF(COUNTIF($AB$3:AE$3,AE$3)=12,INDEX(販管費予算!$E$18:$I$18,MATCH(AE$3,販管費予算!$E$4:$I$4,0))-12*ROUND(INDEX(販管費予算!$E$18:$I$18,MATCH(AE$3,販管費予算!$E$4:$I$4,0))/12,0),0) -> 16667 | AF61: =ROUND(INDEX(販管費予算!$E$18:$I$18,MATCH(AF$3,販管費予算!$E$4:$I$4,0))/12,0)+IF(COUNTIF($AB$3:AF$3,AF$3)=12,INDEX(販管費予算!$E$18:$I$18,MATCH(AF$3,販管費予算!$E$4:$I$4,0))-12*ROUND(INDEX(販管費予算!$E$18:$I$18,MATCH(AF$3,販管費予算!$E$4:$I$4,0))/12,0),0) -> 16667 | AG61: =ROUND(INDEX(販管費予算!$E$18:$I$18,MATCH(AG$3,販管費予算!$E$4:$I$4,0))/12,0)+IF(COUNTIF($AB$3:AG$3,AG$3)=12,INDEX(販管費予算!$E$18:$I$18,MATCH(AG$3,販管費予算!$E$4:$I$4,0))-12*ROUND(INDEX(販管費予算!$E$18:$I$18,MATCH(AG$3,販管費予算!$E$4:$I$4,0))/12,0),0) -> 16667 | AH61: =ROUND(INDEX(販管費予算!$E$18:$I$18,MATCH(AH$3,販管費予算!$E$4:$I$4,0))/12,0)+IF(COUNTIF($AB$3:AH$3,AH$3)=12,INDEX(販管費予算!$E$18:$I$18,MATCH(AH$3,販管費予算!$E$4:$I$4,0))-12*ROUND(INDEX(販管費予算!$E$18:$I$18,MATCH(AH$3,販管費予算!$E$4:$I$4,0))/12,0),0) -> 16667 | AI61: =ROUND(INDEX(販管費予算!$E$18:$I$18,MATCH(AI$3,販管費予算!$E$4:$I$4,0))/12,0)+IF(COUNTIF($AB$3:AI$3,AI$3)=12,INDEX(販管費予算!$E$18:$I$18,MATCH(AI$3,販管費予算!$E$4:$I$4,0))-12*ROUND(INDEX(販管費予算!$E$18:$I$18,MATCH(AI$3,販管費予算!$E$4:$I$4,0))/12,0),0) -> 16667 | ... CI61: =ROUND(INDEX(販管費予算!$E$18:$I$18,MATCH(CI$3,販管費予算!$E$4:$I$4,0))/12,0)+IF(COUNTIF($AB$3:CI$3,CI$3)=12,INDEX(販管費予算!$E$18:$I$18,MATCH(CI$3,販管費予算!$E$4:$I$4,0))-12*ROUND(INDEX(販管費予算!$E$18:$I$18,MATCH(CI$3,販管費予算!$E$4:$I$4,0))/12,0),0) -> 166663
B62: 水道光熱費 | C62: 全社 | E62: =SUMIF($AB$3:$CI$3,E$4,$AB62:$CI62) -> 300000 | F62: =SUMIF($AB$3:$CI$3,F$4,$AB62:$CI62) -> 500000 | G62: =SUMIF($AB$3:$CI$3,G$4,$AB62:$CI62) -> 800000 | H62: =SUMIF($AB$3:$CI$3,H$4,$AB62:$CI62) -> 1200000 | I62: =SUMIF($AB$3:$CI$3,I$4,$AB62:$CI62) -> 2000000 | J62: =SUM(E62:I62) -> 4800000 | K62: =SUMIF($Q$3:$CN$3,K$4,$Q62:$CN62) -> 0 | L62: =SUMIF($Q$3:$CN$3,L$4,$Q62:$CN62) -> 0 | M62: =SUMIF($Q$3:$CN$3,M$4,$Q62:$CN62) -> 0 | N62: =SUMIF($Q$3:$CN$3,N$4,$Q62:$CN62) -> 0 | AB62: =ROUND(INDEX(販管費予算!$E$19:$I$19,MATCH(AB$3,販管費予算!$E$4:$I$4,0))/12,0)+IF(COUNTIF($AB$3:AB$3,AB$3)=12,INDEX(販管費予算!$E$19:$I$19,MATCH(AB$3,販管費予算!$E$4:$I$4,0))-12*ROUND(INDEX(販管費予算!$E$19:$I$19,MATCH(AB$3,販管費予算!$E$4:$I$4,0))/12,0),0) -> 25000 | AC62: =ROUND(INDEX(販管費予算!$E$19:$I$19,MATCH(AC$3,販管費予算!$E$4:$I$4,0))/12,0)+IF(COUNTIF($AB$3:AC$3,AC$3)=12,INDEX(販管費予算!$E$19:$I$19,MATCH(AC$3,販管費予算!$E$4:$I$4,0))-12*ROUND(INDEX(販管費予算!$E$19:$I$19,MATCH(AC$3,販管費予算!$E$4:$I$4,0))/12,0),0) -> 25000 | AD62: =ROUND(INDEX(販管費予算!$E$19:$I$19,MATCH(AD$3,販管費予算!$E$4:$I$4,0))/12,0)+IF(COUNTIF($AB$3:AD$3,AD$3)=12,INDEX(販管費予算!$E$19:$I$19,MATCH(AD$3,販管費予算!$E$4:$I$4,0))-12*ROUND(INDEX(販管費予算!$E$19:$I$19,MATCH(AD$3,販管費予算!$E$4:$I$4,0))/12,0),0) -> 25000 | AE62: =ROUND(INDEX(販管費予算!$E$19:$I$19,MATCH(AE$3,販管費予算!$E$4:$I$4,0))/12,0)+IF(COUNTIF($AB$3:AE$3,AE$3)=12,INDEX(販管費予算!$E$19:$I$19,MATCH(AE$3,販管費予算!$E$4:$I$4,0))-12*ROUND(INDEX(販管費予算!$E$19:$I$19,MATCH(AE$3,販管費予算!$E$4:$I$4,0))/12,0),0) -> 25000 | AF62: =ROUND(INDEX(販管費予算!$E$19:$I$19,MATCH(AF$3,販管費予算!$E$4:$I$4,0))/12,0)+IF(COUNTIF($AB$3:AF$3,AF$3)=12,INDEX(販管費予算!$E$19:$I$19,MATCH(AF$3,販管費予算!$E$4:$I$4,0))-12*ROUND(INDEX(販管費予算!$E$19:$I$19,MATCH(AF$3,販管費予算!$E$4:$I$4,0))/12,0),0) -> 25000 | AG62: =ROUND(INDEX(販管費予算!$E$19:$I$19,MATCH(AG$3,販管費予算!$E$4:$I$4,0))/12,0)+IF(COUNTIF($AB$3:AG$3,AG$3)=12,INDEX(販管費予算!$E$19:$I$19,MATCH(AG$3,販管費予算!$E$4:$I$4,0))-12*ROUND(INDEX(販管費予算!$E$19:$I$19,MATCH(AG$3,販管費予算!$E$4:$I$4,0))/12,0),0) -> 25000 | AH62: =ROUND(INDEX(販管費予算!$E$19:$I$19,MATCH(AH$3,販管費予算!$E$4:$I$4,0))/12,0)+IF(COUNTIF($AB$3:AH$3,AH$3)=12,INDEX(販管費予算!$E$19:$I$19,MATCH(AH$3,販管費予算!$E$4:$I$4,0))-12*ROUND(INDEX(販管費予算!$E$19:$I$19,MATCH(AH$3,販管費予算!$E$4:$I$4,0))/12,0),0) -> 25000 | AI62: =ROUND(INDEX(販管費予算!$E$19:$I$19,MATCH(AI$3,販管費予算!$E$4:$I$4,0))/12,0)+IF(COUNTIF($AB$3:AI$3,AI$3)=12,INDEX(販管費予算!$E$19:$I$19,MATCH(AI$3,販管費予算!$E$4:$I$4,0))-12*ROUND(INDEX(販管費予算!$E$19:$I$19,MATCH(AI$3,販管費予算!$E$4:$I$4,0))/12,0),0) -> 25000 | ... CI62: =ROUND(INDEX(販管費予算!$E$19:$I$19,MATCH(CI$3,販管費予算!$E$4:$I$4,0))/12,0)+IF(COUNTIF($AB$3:CI$3,CI$3)=12,INDEX(販管費予算!$E$19:$I$19,MATCH(CI$3,販管費予算!$E$4:$I$4,0))-12*ROUND(INDEX(販管費予算!$E$19:$I$19,MATCH(CI$3,販管費予算!$E$4:$I$4,0))/12,0),0) -> 166663
B63: 保険料 | C63: 全社 | E63: =SUMIF($AB$3:$CI$3,E$4,$AB63:$CI63) -> 500000 | F63: =SUMIF($AB$3:$CI$3,F$4,$AB63:$CI63) -> 700000 | G63: =SUMIF($AB$3:$CI$3,G$4,$AB63:$CI63) -> 1000000 | H63: =SUMIF($AB$3:$CI$3,H$4,$AB63:$CI63) -> 1500000 | I63: =SUMIF($AB$3:$CI$3,I$4,$AB63:$CI63) -> 2500000 | J63: =SUM(E63:I63) -> 6200000 | K63: =SUMIF($Q$3:$CN$3,K$4,$Q63:$CN63) -> 0 | L63: =SUMIF($Q$3:$CN$3,L$4,$Q63:$CN63) -> 0 | M63: =SUMIF($Q$3:$CN$3,M$4,$Q63:$CN63) -> 0 | N63: =SUMIF($Q$3:$CN$3,N$4,$Q63:$CN63) -> 0 | AB63: =ROUND(INDEX(販管費予算!$E$20:$I$20,MATCH(AB$3,販管費予算!$E$4:$I$4,0))/12,0)+IF(COUNTIF($AB$3:AB$3,AB$3)=12,INDEX(販管費予算!$E$20:$I$20,MATCH(AB$3,販管費予算!$E$4:$I$4,0))-12*ROUND(INDEX(販管費予算!$E$20:$I$20,MATCH(AB$3,販管費予算!$E$4:$I$4,0))/12,0),0) -> 41667 | AC63: =ROUND(INDEX(販管費予算!$E$20:$I$20,MATCH(AC$3,販管費予算!$E$4:$I$4,0))/12,0)+IF(COUNTIF($AB$3:AC$3,AC$3)=12,INDEX(販管費予算!$E$20:$I$20,MATCH(AC$3,販管費予算!$E$4:$I$4,0))-12*ROUND(INDEX(販管費予算!$E$20:$I$20,MATCH(AC$3,販管費予算!$E$4:$I$4,0))/12,0),0) -> 41667 | AD63: =ROUND(INDEX(販管費予算!$E$20:$I$20,MATCH(AD$3,販管費予算!$E$4:$I$4,0))/12,0)+IF(COUNTIF($AB$3:AD$3,AD$3)=12,INDEX(販管費予算!$E$20:$I$20,MATCH(AD$3,販管費予算!$E$4:$I$4,0))-12*ROUND(INDEX(販管費予算!$E$20:$I$20,MATCH(AD$3,販管費予算!$E$4:$I$4,0))/12,0),0) -> 41667 | AE63: =ROUND(INDEX(販管費予算!$E$20:$I$20,MATCH(AE$3,販管費予算!$E$4:$I$4,0))/12,0)+IF(COUNTIF($AB$3:AE$3,AE$3)=12,INDEX(販管費予算!$E$20:$I$20,MATCH(AE$3,販管費予算!$E$4:$I$4,0))-12*ROUND(INDEX(販管費予算!$E$20:$I$20,MATCH(AE$3,販管費予算!$E$4:$I$4,0))/12,0),0) -> 41667 | AF63: =ROUND(INDEX(販管費予算!$E$20:$I$20,MATCH(AF$3,販管費予算!$E$4:$I$4,0))/12,0)+IF(COUNTIF($AB$3:AF$3,AF$3)=12,INDEX(販管費予算!$E$20:$I$20,MATCH(AF$3,販管費予算!$E$4:$I$4,0))-12*ROUND(INDEX(販管費予算!$E$20:$I$20,MATCH(AF$3,販管費予算!$E$4:$I$4,0))/12,0),0) -> 41667 | AG63: =ROUND(INDEX(販管費予算!$E$20:$I$20,MATCH(AG$3,販管費予算!$E$4:$I$4,0))/12,0)+IF(COUNTIF($AB$3:AG$3,AG$3)=12,INDEX(販管費予算!$E$20:$I$20,MATCH(AG$3,販管費予算!$E$4:$I$4,0))-12*ROUND(INDEX(販管費予算!$E$20:$I$20,MATCH(AG$3,販管費予算!$E$4:$I$4,0))/12,0),0) -> 41667 | AH63: =ROUND(INDEX(販管費予算!$E$20:$I$20,MATCH(AH$3,販管費予算!$E$4:$I$4,0))/12,0)+IF(COUNTIF($AB$3:AH$3,AH$3)=12,INDEX(販管費予算!$E$20:$I$20,MATCH(AH$3,販管費予算!$E$4:$I$4,0))-12*ROUND(INDEX(販管費予算!$E$20:$I$20,MATCH(AH$3,販管費予算!$E$4:$I$4,0))/12,0),0) -> 41667 | AI63: =ROUND(INDEX(販管費予算!$E$20:$I$20,MATCH(AI$3,販管費予算!$E$4:$I$4,0))/12,0)+IF(COUNTIF($AB$3:AI$3,AI$3)=12,INDEX(販管費予算!$E$20:$I$20,MATCH(AI$3,販管費予算!$E$4:$I$4,0))-12*ROUND(INDEX(販管費予算!$E$20:$I$20,MATCH(AI$3,販管費予算!$E$4:$I$4,0))/12,0),0) -> 41667 | ... CI63: =ROUND(INDEX(販管費予算!$E$20:$I$20,MATCH(CI$3,販管費予算!$E$4:$I$4,0))/12,0)+IF(COUNTIF($AB$3:CI$3,CI$3)=12,INDEX(販管費予算!$E$20:$I$20,MATCH(CI$3,販管費予算!$E$4:$I$4,0))-12*ROUND(INDEX(販管費予算!$E$20:$I$20,MATCH(CI$3,販管費予算!$E$4:$I$4,0))/12,0),0) -> 208337
B64: 支払リース料 | C64: 全社 | E64: =SUMIF($AB$3:$CI$3,E$4,$AB64:$CI64) -> 0 | F64: =SUMIF($AB$3:$CI$3,F$4,$AB64:$CI64) -> 300000 | G64: =SUMIF($AB$3:$CI$3,G$4,$AB64:$CI64) -> 600000 | H64: =SUMIF($AB$3:$CI$3,H$4,$AB64:$CI64) -> 1000000 | I64: =SUMIF($AB$3:$CI$3,I$4,$AB64:$CI64) -> 2000000 | J64: =SUM(E64:I64) -> 3900000 | K64: =SUMIF($Q$3:$CN$3,K$4,$Q64:$CN64) -> 0 | L64: =SUMIF($Q$3:$CN$3,L$4,$Q64:$CN64) -> 0 | M64: =SUMIF($Q$3:$CN$3,M$4,$Q64:$CN64) -> 0 | N64: =SUMIF($Q$3:$CN$3,N$4,$Q64:$CN64) -> 0 | AB64: =ROUND(INDEX(販管費予算!$E$21:$I$21,MATCH(AB$3,販管費予算!$E$4:$I$4,0))/12,0)+IF(COUNTIF($AB$3:AB$3,AB$3)=12,INDEX(販管費予算!$E$21:$I$21,MATCH(AB$3,販管費予算!$E$4:$I$4,0))-12*ROUND(INDEX(販管費予算!$E$21:$I$21,MATCH(AB$3,販管費予算!$E$4:$I$4,0))/12,0),0) -> 0 | AC64: =ROUND(INDEX(販管費予算!$E$21:$I$21,MATCH(AC$3,販管費予算!$E$4:$I$4,0))/12,0)+IF(COUNTIF($AB$3:AC$3,AC$3)=12,INDEX(販管費予算!$E$21:$I$21,MATCH(AC$3,販管費予算!$E$4:$I$4,0))-12*ROUND(INDEX(販管費予算!$E$21:$I$21,MATCH(AC$3,販管費予算!$E$4:$I$4,0))/12,0),0) -> 0 | AD64: =ROUND(INDEX(販管費予算!$E$21:$I$21,MATCH(AD$3,販管費予算!$E$4:$I$4,0))/12,0)+IF(COUNTIF($AB$3:AD$3,AD$3)=12,INDEX(販管費予算!$E$21:$I$21,MATCH(AD$3,販管費予算!$E$4:$I$4,0))-12*ROUND(INDEX(販管費予算!$E$21:$I$21,MATCH(AD$3,販管費予算!$E$4:$I$4,0))/12,0),0) -> 0 | AE64: =ROUND(INDEX(販管費予算!$E$21:$I$21,MATCH(AE$3,販管費予算!$E$4:$I$4,0))/12,0)+IF(COUNTIF($AB$3:AE$3,AE$3)=12,INDEX(販管費予算!$E$21:$I$21,MATCH(AE$3,販管費予算!$E$4:$I$4,0))-12*ROUND(INDEX(販管費予算!$E$21:$I$21,MATCH(AE$3,販管費予算!$E$4:$I$4,0))/12,0),0) -> 0 | AF64: =ROUND(INDEX(販管費予算!$E$21:$I$21,MATCH(AF$3,販管費予算!$E$4:$I$4,0))/12,0)+IF(COUNTIF($AB$3:AF$3,AF$3)=12,INDEX(販管費予算!$E$21:$I$21,MATCH(AF$3,販管費予算!$E$4:$I$4,0))-12*ROUND(INDEX(販管費予算!$E$21:$I$21,MATCH(AF$3,販管費予算!$E$4:$I$4,0))/12,0),0) -> 0 | AG64: =ROUND(INDEX(販管費予算!$E$21:$I$21,MATCH(AG$3,販管費予算!$E$4:$I$4,0))/12,0)+IF(COUNTIF($AB$3:AG$3,AG$3)=12,INDEX(販管費予算!$E$21:$I$21,MATCH(AG$3,販管費予算!$E$4:$I$4,0))-12*ROUND(INDEX(販管費予算!$E$21:$I$21,MATCH(AG$3,販管費予算!$E$4:$I$4,0))/12,0),0) -> 0 | AH64: =ROUND(INDEX(販管費予算!$E$21:$I$21,MATCH(AH$3,販管費予算!$E$4:$I$4,0))/12,0)+IF(COUNTIF($AB$3:AH$3,AH$3)=12,INDEX(販管費予算!$E$21:$I$21,MATCH(AH$3,販管費予算!$E$4:$I$4,0))-12*ROUND(INDEX(販管費予算!$E$21:$I$21,MATCH(AH$3,販管費予算!$E$4:$I$4,0))/12,0),0) -> 0 | AI64: =ROUND(INDEX(販管費予算!$E$21:$I$21,MATCH(AI$3,販管費予算!$E$4:$I$4,0))/12,0)+IF(COUNTIF($AB$3:AI$3,AI$3)=12,INDEX(販管費予算!$E$21:$I$21,MATCH(AI$3,販管費予算!$E$4:$I$4,0))-12*ROUND(INDEX(販管費予算!$E$21:$I$21,MATCH(AI$3,販管費予算!$E$4:$I$4,0))/12,0),0) -> 0 | ... CI64: =ROUND(INDEX(販管費予算!$E$21:$I$21,MATCH(CI$3,販管費予算!$E$4:$I$4,0))/12,0)+IF(COUNTIF($AB$3:CI$3,CI$3)=12,INDEX(販管費予算!$E$21:$I$21,MATCH(CI$3,販管費予算!$E$4:$I$4,0))-12*ROUND(INDEX(販管費予算!$E$21:$I$21,MATCH(CI$3,販管費予算!$E$4:$I$4,0))/12,0),0) -> 166663
B65: 修繕費 | C65: 全社 | E65: =SUMIF($AB$3:$CI$3,E$4,$AB65:$CI65) -> 0 | F65: =SUMIF($AB$3:$CI$3,F$4,$AB65:$CI65) -> 0 | G65: =SUMIF($AB$3:$CI$3,G$4,$AB65:$CI65) -> 100000 | H65: =SUMIF($AB$3:$CI$3,H$4,$AB65:$CI65) -> 200000 | I65: =SUMIF($AB$3:$CI$3,I$4,$AB65:$CI65) -> 500000 | J65: =SUM(E65:I65) -> 800000 | K65: =SUMIF($Q$3:$CN$3,K$4,$Q65:$CN65) -> 0 | L65: =SUMIF($Q$3:$CN$3,L$4,$Q65:$CN65) -> 0 | M65: =SUMIF($Q$3:$CN$3,M$4,$Q65:$CN65) -> 0 | N65: =SUMIF($Q$3:$CN$3,N$4,$Q65:$CN65) -> 0 | AB65: =ROUND(INDEX(販管費予算!$E$22:$I$22,MATCH(AB$3,販管費予算!$E$4:$I$4,0))/12,0)+IF(COUNTIF($AB$3:AB$3,AB$3)=12,INDEX(販管費予算!$E$22:$I$22,MATCH(AB$3,販管費予算!$E$4:$I$4,0))-12*ROUND(INDEX(販管費予算!$E$22:$I$22,MATCH(AB$3,販管費予算!$E$4:$I$4,0))/12,0),0) -> 0 | AC65: =ROUND(INDEX(販管費予算!$E$22:$I$22,MATCH(AC$3,販管費予算!$E$4:$I$4,0))/12,0)+IF(COUNTIF($AB$3:AC$3,AC$3)=12,INDEX(販管費予算!$E$22:$I$22,MATCH(AC$3,販管費予算!$E$4:$I$4,0))-12*ROUND(INDEX(販管費予算!$E$22:$I$22,MATCH(AC$3,販管費予算!$E$4:$I$4,0))/12,0),0) -> 0 | AD65: =ROUND(INDEX(販管費予算!$E$22:$I$22,MATCH(AD$3,販管費予算!$E$4:$I$4,0))/12,0)+IF(COUNTIF($AB$3:AD$3,AD$3)=12,INDEX(販管費予算!$E$22:$I$22,MATCH(AD$3,販管費予算!$E$4:$I$4,0))-12*ROUND(INDEX(販管費予算!$E$22:$I$22,MATCH(AD$3,販管費予算!$E$4:$I$4,0))/12,0),0) -> 0 | AE65: =ROUND(INDEX(販管費予算!$E$22:$I$22,MATCH(AE$3,販管費予算!$E$4:$I$4,0))/12,0)+IF(COUNTIF($AB$3:AE$3,AE$3)=12,INDEX(販管費予算!$E$22:$I$22,MATCH(AE$3,販管費予算!$E$4:$I$4,0))-12*ROUND(INDEX(販管費予算!$E$22:$I$22,MATCH(AE$3,販管費予算!$E$4:$I$4,0))/12,0),0) -> 0 | AF65: =ROUND(INDEX(販管費予算!$E$22:$I$22,MATCH(AF$3,販管費予算!$E$4:$I$4,0))/12,0)+IF(COUNTIF($AB$3:AF$3,AF$3)=12,INDEX(販管費予算!$E$22:$I$22,MATCH(AF$3,販管費予算!$E$4:$I$4,0))-12*ROUND(INDEX(販管費予算!$E$22:$I$22,MATCH(AF$3,販管費予算!$E$4:$I$4,0))/12,0),0) -> 0 | AG65: =ROUND(INDEX(販管費予算!$E$22:$I$22,MATCH(AG$3,販管費予算!$E$4:$I$4,0))/12,0)+IF(COUNTIF($AB$3:AG$3,AG$3)=12,INDEX(販管費予算!$E$22:$I$22,MATCH(AG$3,販管費予算!$E$4:$I$4,0))-12*ROUND(INDEX(販管費予算!$E$22:$I$22,MATCH(AG$3,販管費予算!$E$4:$I$4,0))/12,0),0) -> 0 | AH65: =ROUND(INDEX(販管費予算!$E$22:$I$22,MATCH(AH$3,販管費予算!$E$4:$I$4,0))/12,0)+IF(COUNTIF($AB$3:AH$3,AH$3)=12,INDEX(販管費予算!$E$22:$I$22,MATCH(AH$3,販管費予算!$E$4:$I$4,0))-12*ROUND(INDEX(販管費予算!$E$22:$I$22,MATCH(AH$3,販管費予算!$E$4:$I$4,0))/12,0),0) -> 0 | AI65: =ROUND(INDEX(販管費予算!$E$22:$I$22,MATCH(AI$3,販管費予算!$E$4:$I$4,0))/12,0)+IF(COUNTIF($AB$3:AI$3,AI$3)=12,INDEX(販管費予算!$E$22:$I$22,MATCH(AI$3,販管費予算!$E$4:$I$4,0))-12*ROUND(INDEX(販管費予算!$E$22:$I$22,MATCH(AI$3,販管費予算!$E$4:$I$4,0))/12,0),0) -> 0 | ... CI65: =ROUND(INDEX(販管費予算!$E$22:$I$22,MATCH(CI$3,販管費予算!$E$4:$I$4,0))/12,0)+IF(COUNTIF($AB$3:CI$3,CI$3)=12,INDEX(販管費予算!$E$22:$I$22,MATCH(CI$3,販管費予算!$E$4:$I$4,0))-12*ROUND(INDEX(販管費予算!$E$22:$I$22,MATCH(CI$3,販管費予算!$E$4:$I$4,0))/12,0),0) -> 41663
B66: 新聞図書費 | C66: 全社 | E66: =SUMIF($AB$3:$CI$3,E$4,$AB66:$CI66) -> 200000 | F66: =SUMIF($AB$3:$CI$3,F$4,$AB66:$CI66) -> 300000 | G66: =SUMIF($AB$3:$CI$3,G$4,$AB66:$CI66) -> 500000 | H66: =SUMIF($AB$3:$CI$3,H$4,$AB66:$CI66) -> 700000 | I66: =SUMIF($AB$3:$CI$3,I$4,$AB66:$CI66) -> 1000000 | J66: =SUM(E66:I66) -> 2700000 | K66: =SUMIF($Q$3:$CN$3,K$4,$Q66:$CN66) -> 0 | L66: =SUMIF($Q$3:$CN$3,L$4,$Q66:$CN66) -> 0 | M66: =SUMIF($Q$3:$CN$3,M$4,$Q66:$CN66) -> 0 | N66: =SUMIF($Q$3:$CN$3,N$4,$Q66:$CN66) -> 0 | AB66: =ROUND(INDEX(販管費予算!$E$23:$I$23,MATCH(AB$3,販管費予算!$E$4:$I$4,0))/12,0)+IF(COUNTIF($AB$3:AB$3,AB$3)=12,INDEX(販管費予算!$E$23:$I$23,MATCH(AB$3,販管費予算!$E$4:$I$4,0))-12*ROUND(INDEX(販管費予算!$E$23:$I$23,MATCH(AB$3,販管費予算!$E$4:$I$4,0))/12,0),0) -> 16667 | AC66: =ROUND(INDEX(販管費予算!$E$23:$I$23,MATCH(AC$3,販管費予算!$E$4:$I$4,0))/12,0)+IF(COUNTIF($AB$3:AC$3,AC$3)=12,INDEX(販管費予算!$E$23:$I$23,MATCH(AC$3,販管費予算!$E$4:$I$4,0))-12*ROUND(INDEX(販管費予算!$E$23:$I$23,MATCH(AC$3,販管費予算!$E$4:$I$4,0))/12,0),0) -> 16667 | AD66: =ROUND(INDEX(販管費予算!$E$23:$I$23,MATCH(AD$3,販管費予算!$E$4:$I$4,0))/12,0)+IF(COUNTIF($AB$3:AD$3,AD$3)=12,INDEX(販管費予算!$E$23:$I$23,MATCH(AD$3,販管費予算!$E$4:$I$4,0))-12*ROUND(INDEX(販管費予算!$E$23:$I$23,MATCH(AD$3,販管費予算!$E$4:$I$4,0))/12,0),0) -> 16667 | AE66: =ROUND(INDEX(販管費予算!$E$23:$I$23,MATCH(AE$3,販管費予算!$E$4:$I$4,0))/12,0)+IF(COUNTIF($AB$3:AE$3,AE$3)=12,INDEX(販管費予算!$E$23:$I$23,MATCH(AE$3,販管費予算!$E$4:$I$4,0))-12*ROUND(INDEX(販管費予算!$E$23:$I$23,MATCH(AE$3,販管費予算!$E$4:$I$4,0))/12,0),0) -> 16667 | AF66: =ROUND(INDEX(販管費予算!$E$23:$I$23,MATCH(AF$3,販管費予算!$E$4:$I$4,0))/12,0)+IF(COUNTIF($AB$3:AF$3,AF$3)=12,INDEX(販管費予算!$E$23:$I$23,MATCH(AF$3,販管費予算!$E$4:$I$4,0))-12*ROUND(INDEX(販管費予算!$E$23:$I$23,MATCH(AF$3,販管費予算!$E$4:$I$4,0))/12,0),0) -> 16667 | AG66: =ROUND(INDEX(販管費予算!$E$23:$I$23,MATCH(AG$3,販管費予算!$E$4:$I$4,0))/12,0)+IF(COUNTIF($AB$3:AG$3,AG$3)=12,INDEX(販管費予算!$E$23:$I$23,MATCH(AG$3,販管費予算!$E$4:$I$4,0))-12*ROUND(INDEX(販管費予算!$E$23:$I$23,MATCH(AG$3,販管費予算!$E$4:$I$4,0))/12,0),0) -> 16667 | AH66: =ROUND(INDEX(販管費予算!$E$23:$I$23,MATCH(AH$3,販管費予算!$E$4:$I$4,0))/12,0)+IF(COUNTIF($AB$3:AH$3,AH$3)=12,INDEX(販管費予算!$E$23:$I$23,MATCH(AH$3,販管費予算!$E$4:$I$4,0))-12*ROUND(INDEX(販管費予算!$E$23:$I$23,MATCH(AH$3,販管費予算!$E$4:$I$4,0))/12,0),0) -> 16667 | AI66: =ROUND(INDEX(販管費予算!$E$23:$I$23,MATCH(AI$3,販管費予算!$E$4:$I$4,0))/12,0)+IF(COUNTIF($AB$3:AI$3,AI$3)=12,INDEX(販管費予算!$E$23:$I$23,MATCH(AI$3,販管費予算!$E$4:$I$4,0))-12*ROUND(INDEX(販管費予算!$E$23:$I$23,MATCH(AI$3,販管費予算!$E$4:$I$4,0))/12,0),0) -> 16667 | ... CI66: =ROUND(INDEX(販管費予算!$E$23:$I$23,MATCH(CI$3,販管費予算!$E$4:$I$4,0))/12,0)+IF(COUNTIF($AB$3:CI$3,CI$3)=12,INDEX(販管費予算!$E$23:$I$23,MATCH(CI$3,販管費予算!$E$4:$I$4,0))-12*ROUND(INDEX(販管費予算!$E$23:$I$23,MATCH(CI$3,販管費予算!$E$4:$I$4,0))/12,0),0) -> 83337
B67: 支払手数料 | C67: 全社 | E67: =SUMIF($AB$3:$CI$3,E$4,$AB67:$CI67) -> 1000000 | F67: =SUMIF($AB$3:$CI$3,F$4,$AB67:$CI67) -> 2000000 | G67: =SUMIF($AB$3:$CI$3,G$4,$AB67:$CI67) -> 5000000 | H67: =SUMIF($AB$3:$CI$3,H$4,$AB67:$CI67) -> 8000000 | I67: =SUMIF($AB$3:$CI$3,I$4,$AB67:$CI67) -> 15000000 | J67: =SUM(E67:I67) -> 31000000 | K67: =SUMIF($Q$3:$CN$3,K$4,$Q67:$CN67) -> 0 | L67: =SUMIF($Q$3:$CN$3,L$4,$Q67:$CN67) -> 0 | M67: =SUMIF($Q$3:$CN$3,M$4,$Q67:$CN67) -> 0 | N67: =SUMIF($Q$3:$CN$3,N$4,$Q67:$CN67) -> 0 | AB67: =ROUND(INDEX(販管費予算!$E$24:$I$24,MATCH(AB$3,販管費予算!$E$4:$I$4,0))/12,0)+IF(COUNTIF($AB$3:AB$3,AB$3)=12,INDEX(販管費予算!$E$24:$I$24,MATCH(AB$3,販管費予算!$E$4:$I$4,0))-12*ROUND(INDEX(販管費予算!$E$24:$I$24,MATCH(AB$3,販管費予算!$E$4:$I$4,0))/12,0),0) -> 83333 | AC67: =ROUND(INDEX(販管費予算!$E$24:$I$24,MATCH(AC$3,販管費予算!$E$4:$I$4,0))/12,0)+IF(COUNTIF($AB$3:AC$3,AC$3)=12,INDEX(販管費予算!$E$24:$I$24,MATCH(AC$3,販管費予算!$E$4:$I$4,0))-12*ROUND(INDEX(販管費予算!$E$24:$I$24,MATCH(AC$3,販管費予算!$E$4:$I$4,0))/12,0),0) -> 83333 | AD67: =ROUND(INDEX(販管費予算!$E$24:$I$24,MATCH(AD$3,販管費予算!$E$4:$I$4,0))/12,0)+IF(COUNTIF($AB$3:AD$3,AD$3)=12,INDEX(販管費予算!$E$24:$I$24,MATCH(AD$3,販管費予算!$E$4:$I$4,0))-12*ROUND(INDEX(販管費予算!$E$24:$I$24,MATCH(AD$3,販管費予算!$E$4:$I$4,0))/12,0),0) -> 83333 | AE67: =ROUND(INDEX(販管費予算!$E$24:$I$24,MATCH(AE$3,販管費予算!$E$4:$I$4,0))/12,0)+IF(COUNTIF($AB$3:AE$3,AE$3)=12,INDEX(販管費予算!$E$24:$I$24,MATCH(AE$3,販管費予算!$E$4:$I$4,0))-12*ROUND(INDEX(販管費予算!$E$24:$I$24,MATCH(AE$3,販管費予算!$E$4:$I$4,0))/12,0),0) -> 83333 | AF67: =ROUND(INDEX(販管費予算!$E$24:$I$24,MATCH(AF$3,販管費予算!$E$4:$I$4,0))/12,0)+IF(COUNTIF($AB$3:AF$3,AF$3)=12,INDEX(販管費予算!$E$24:$I$24,MATCH(AF$3,販管費予算!$E$4:$I$4,0))-12*ROUND(INDEX(販管費予算!$E$24:$I$24,MATCH(AF$3,販管費予算!$E$4:$I$4,0))/12,0),0) -> 83333 | AG67: =ROUND(INDEX(販管費予算!$E$24:$I$24,MATCH(AG$3,販管費予算!$E$4:$I$4,0))/12,0)+IF(COUNTIF($AB$3:AG$3,AG$3)=12,INDEX(販管費予算!$E$24:$I$24,MATCH(AG$3,販管費予算!$E$4:$I$4,0))-12*ROUND(INDEX(販管費予算!$E$24:$I$24,MATCH(AG$3,販管費予算!$E$4:$I$4,0))/12,0),0) -> 83333 | AH67: =ROUND(INDEX(販管費予算!$E$24:$I$24,MATCH(AH$3,販管費予算!$E$4:$I$4,0))/12,0)+IF(COUNTIF($AB$3:AH$3,AH$3)=12,INDEX(販管費予算!$E$24:$I$24,MATCH(AH$3,販管費予算!$E$4:$I$4,0))-12*ROUND(INDEX(販管費予算!$E$24:$I$24,MATCH(AH$3,販管費予算!$E$4:$I$4,0))/12,0),0) -> 83333 | AI67: =ROUND(INDEX(販管費予算!$E$24:$I$24,MATCH(AI$3,販管費予算!$E$4:$I$4,0))/12,0)+IF(COUNTIF($AB$3:AI$3,AI$3)=12,INDEX(販管費予算!$E$24:$I$24,MATCH(AI$3,販管費予算!$E$4:$I$4,0))-12*ROUND(INDEX(販管費予算!$E$24:$I$24,MATCH(AI$3,販管費予算!$E$4:$I$4,0))/12,0),0) -> 83333 | ... CI67: =ROUND(INDEX(販管費予算!$E$24:$I$24,MATCH(CI$3,販管費予算!$E$4:$I$4,0))/12,0)+IF(COUNTIF($AB$3:CI$3,CI$3)=12,INDEX(販管費予算!$E$24:$I$24,MATCH(CI$3,販管費予算!$E$4:$I$4,0))-12*ROUND(INDEX(販管費予算!$E$24:$I$24,MATCH(CI$3,販管費予算!$E$4:$I$4,0))/12,0),0) -> 1250000
B68: 地代家賃 | C68: 全社 | E68: =SUMIF($AB$3:$CI$3,E$4,$AB68:$CI68) -> 2400000 | F68: =SUMIF($AB$3:$CI$3,F$4,$AB68:$CI68) -> 4800000 | G68: =SUMIF($AB$3:$CI$3,G$4,$AB68:$CI68) -> 7200000 | H68: =SUMIF($AB$3:$CI$3,H$4,$AB68:$CI68) -> 12000000 | I68: =SUMIF($AB$3:$CI$3,I$4,$AB68:$CI68) -> 18000000 | J68: =SUM(E68:I68) -> 44400000 | K68: =SUMIF($Q$3:$CN$3,K$4,$Q68:$CN68) -> 0 | L68: =SUMIF($Q$3:$CN$3,L$4,$Q68:$CN68) -> 0 | M68: =SUMIF($Q$3:$CN$3,M$4,$Q68:$CN68) -> 0 | N68: =SUMIF($Q$3:$CN$3,N$4,$Q68:$CN68) -> 0 | AB68: =ROUND(INDEX(販管費予算!$E$25:$I$25,MATCH(AB$3,販管費予算!$E$4:$I$4,0))/12,0)+IF(COUNTIF($AB$3:AB$3,AB$3)=12,INDEX(販管費予算!$E$25:$I$25,MATCH(AB$3,販管費予算!$E$4:$I$4,0))-12*ROUND(INDEX(販管費予算!$E$25:$I$25,MATCH(AB$3,販管費予算!$E$4:$I$4,0))/12,0),0) -> 200000 | AC68: =ROUND(INDEX(販管費予算!$E$25:$I$25,MATCH(AC$3,販管費予算!$E$4:$I$4,0))/12,0)+IF(COUNTIF($AB$3:AC$3,AC$3)=12,INDEX(販管費予算!$E$25:$I$25,MATCH(AC$3,販管費予算!$E$4:$I$4,0))-12*ROUND(INDEX(販管費予算!$E$25:$I$25,MATCH(AC$3,販管費予算!$E$4:$I$4,0))/12,0),0) -> 200000 | AD68: =ROUND(INDEX(販管費予算!$E$25:$I$25,MATCH(AD$3,販管費予算!$E$4:$I$4,0))/12,0)+IF(COUNTIF($AB$3:AD$3,AD$3)=12,INDEX(販管費予算!$E$25:$I$25,MATCH(AD$3,販管費予算!$E$4:$I$4,0))-12*ROUND(INDEX(販管費予算!$E$25:$I$25,MATCH(AD$3,販管費予算!$E$4:$I$4,0))/12,0),0) -> 200000 | AE68: =ROUND(INDEX(販管費予算!$E$25:$I$25,MATCH(AE$3,販管費予算!$E$4:$I$4,0))/12,0)+IF(COUNTIF($AB$3:AE$3,AE$3)=12,INDEX(販管費予算!$E$25:$I$25,MATCH(AE$3,販管費予算!$E$4:$I$4,0))-12*ROUND(INDEX(販管費予算!$E$25:$I$25,MATCH(AE$3,販管費予算!$E$4:$I$4,0))/12,0),0) -> 200000 | AF68: =ROUND(INDEX(販管費予算!$E$25:$I$25,MATCH(AF$3,販管費予算!$E$4:$I$4,0))/12,0)+IF(COUNTIF($AB$3:AF$3,AF$3)=12,INDEX(販管費予算!$E$25:$I$25,MATCH(AF$3,販管費予算!$E$4:$I$4,0))-12*ROUND(INDEX(販管費予算!$E$25:$I$25,MATCH(AF$3,販管費予算!$E$4:$I$4,0))/12,0),0) -> 200000 | AG68: =ROUND(INDEX(販管費予算!$E$25:$I$25,MATCH(AG$3,販管費予算!$E$4:$I$4,0))/12,0)+IF(COUNTIF($AB$3:AG$3,AG$3)=12,INDEX(販管費予算!$E$25:$I$25,MATCH(AG$3,販管費予算!$E$4:$I$4,0))-12*ROUND(INDEX(販管費予算!$E$25:$I$25,MATCH(AG$3,販管費予算!$E$4:$I$4,0))/12,0),0) -> 200000 | AH68: =ROUND(INDEX(販管費予算!$E$25:$I$25,MATCH(AH$3,販管費予算!$E$4:$I$4,0))/12,0)+IF(COUNTIF($AB$3:AH$3,AH$3)=12,INDEX(販管費予算!$E$25:$I$25,MATCH(AH$3,販管費予算!$E$4:$I$4,0))-12*ROUND(INDEX(販管費予算!$E$25:$I$25,MATCH(AH$3,販管費予算!$E$4:$I$4,0))/12,0),0) -> 200000 | AI68: =ROUND(INDEX(販管費予算!$E$25:$I$25,MATCH(AI$3,販管費予算!$E$4:$I$4,0))/12,0)+IF(COUNTIF($AB$3:AI$3,AI$3)=12,INDEX(販管費予算!$E$25:$I$25,MATCH(AI$3,販管費予算!$E$4:$I$4,0))-12*ROUND(INDEX(販管費予算!$E$25:$I$25,MATCH(AI$3,販管費予算!$E$4:$I$4,0))/12,0),0) -> 200000 | ... CI68: =ROUND(INDEX(販管費予算!$E$25:$I$25,MATCH(CI$3,販管費予算!$E$4:$I$4,0))/12,0)+IF(COUNTIF($AB$3:CI$3,CI$3)=12,INDEX(販管費予算!$E$25:$I$25,MATCH(CI$3,販管費予算!$E$4:$I$4,0))-12*ROUND(INDEX(販管費予算!$E$25:$I$25,MATCH(CI$3,販管費予算!$E$4:$I$4,0))/12,0),0) -> 1500000
B69: 賃借料 | C69: 全社 | E69: =SUMIF($AB$3:$CI$3,E$4,$AB69:$CI69) -> 300000 | F69: =SUMIF($AB$3:$CI$3,F$4,$AB69:$CI69) -> 500000 | G69: =SUMIF($AB$3:$CI$3,G$4,$AB69:$CI69) -> 700000 | H69: =SUMIF($AB$3:$CI$3,H$4,$AB69:$CI69) -> 1000000 | I69: =SUMIF($AB$3:$CI$3,I$4,$AB69:$CI69) -> 2000000 | J69: =SUM(E69:I69) -> 4500000 | K69: =SUMIF($Q$3:$CN$3,K$4,$Q69:$CN69) -> 0 | L69: =SUMIF($Q$3:$CN$3,L$4,$Q69:$CN69) -> 0 | M69: =SUMIF($Q$3:$CN$3,M$4,$Q69:$CN69) -> 0 | N69: =SUMIF($Q$3:$CN$3,N$4,$Q69:$CN69) -> 0 | AB69: =ROUND(INDEX(販管費予算!$E$26:$I$26,MATCH(AB$3,販管費予算!$E$4:$I$4,0))/12,0)+IF(COUNTIF($AB$3:AB$3,AB$3)=12,INDEX(販管費予算!$E$26:$I$26,MATCH(AB$3,販管費予算!$E$4:$I$4,0))-12*ROUND(INDEX(販管費予算!$E$26:$I$26,MATCH(AB$3,販管費予算!$E$4:$I$4,0))/12,0),0) -> 25000 | AC69: =ROUND(INDEX(販管費予算!$E$26:$I$26,MATCH(AC$3,販管費予算!$E$4:$I$4,0))/12,0)+IF(COUNTIF($AB$3:AC$3,AC$3)=12,INDEX(販管費予算!$E$26:$I$26,MATCH(AC$3,販管費予算!$E$4:$I$4,0))-12*ROUND(INDEX(販管費予算!$E$26:$I$26,MATCH(AC$3,販管費予算!$E$4:$I$4,0))/12,0),0) -> 25000 | AD69: =ROUND(INDEX(販管費予算!$E$26:$I$26,MATCH(AD$3,販管費予算!$E$4:$I$4,0))/12,0)+IF(COUNTIF($AB$3:AD$3,AD$3)=12,INDEX(販管費予算!$E$26:$I$26,MATCH(AD$3,販管費予算!$E$4:$I$4,0))-12*ROUND(INDEX(販管費予算!$E$26:$I$26,MATCH(AD$3,販管費予算!$E$4:$I$4,0))/12,0),0) -> 25000 | AE69: =ROUND(INDEX(販管費予算!$E$26:$I$26,MATCH(AE$3,販管費予算!$E$4:$I$4,0))/12,0)+IF(COUNTIF($AB$3:AE$3,AE$3)=12,INDEX(販管費予算!$E$26:$I$26,MATCH(AE$3,販管費予算!$E$4:$I$4,0))-12*ROUND(INDEX(販管費予算!$E$26:$I$26,MATCH(AE$3,販管費予算!$E$4:$I$4,0))/12,0),0) -> 25000 | AF69: =ROUND(INDEX(販管費予算!$E$26:$I$26,MATCH(AF$3,販管費予算!$E$4:$I$4,0))/12,0)+IF(COUNTIF($AB$3:AF$3,AF$3)=12,INDEX(販管費予算!$E$26:$I$26,MATCH(AF$3,販管費予算!$E$4:$I$4,0))-12*ROUND(INDEX(販管費予算!$E$26:$I$26,MATCH(AF$3,販管費予算!$E$4:$I$4,0))/12,0),0) -> 25000 | AG69: =ROUND(INDEX(販管費予算!$E$26:$I$26,MATCH(AG$3,販管費予算!$E$4:$I$4,0))/12,0)+IF(COUNTIF($AB$3:AG$3,AG$3)=12,INDEX(販管費予算!$E$26:$I$26,MATCH(AG$3,販管費予算!$E$4:$I$4,0))-12*ROUND(INDEX(販管費予算!$E$26:$I$26,MATCH(AG$3,販管費予算!$E$4:$I$4,0))/12,0),0) -> 25000 | AH69: =ROUND(INDEX(販管費予算!$E$26:$I$26,MATCH(AH$3,販管費予算!$E$4:$I$4,0))/12,0)+IF(COUNTIF($AB$3:AH$3,AH$3)=12,INDEX(販管費予算!$E$26:$I$26,MATCH(AH$3,販管費予算!$E$4:$I$4,0))-12*ROUND(INDEX(販管費予算!$E$26:$I$26,MATCH(AH$3,販管費予算!$E$4:$I$4,0))/12,0),0) -> 25000 | AI69: =ROUND(INDEX(販管費予算!$E$26:$I$26,MATCH(AI$3,販管費予算!$E$4:$I$4,0))/12,0)+IF(COUNTIF($AB$3:AI$3,AI$3)=12,INDEX(販管費予算!$E$26:$I$26,MATCH(AI$3,販管費予算!$E$4:$I$4,0))-12*ROUND(INDEX(販管費予算!$E$26:$I$26,MATCH(AI$3,販管費予算!$E$4:$I$4,0))/12,0),0) -> 25000 | ... CI69: =ROUND(INDEX(販管費予算!$E$26:$I$26,MATCH(CI$3,販管費予算!$E$4:$I$4,0))/12,0)+IF(COUNTIF($AB$3:CI$3,CI$3)=12,INDEX(販管費予算!$E$26:$I$26,MATCH(CI$3,販管費予算!$E$4:$I$4,0))-12*ROUND(INDEX(販管費予算!$E$26:$I$26,MATCH(CI$3,販管費予算!$E$4:$I$4,0))/12,0),0) -> 166663
B70: 租税公課 | C70: 全社 | E70: =SUMIF($AB$3:$CI$3,E$4,$AB70:$CI70) -> 300000 | F70: =SUMIF($AB$3:$CI$3,F$4,$AB70:$CI70) -> 500000 | G70: =SUMIF($AB$3:$CI$3,G$4,$AB70:$CI70) -> 1000000 | H70: =SUMIF($AB$3:$CI$3,H$4,$AB70:$CI70) -> 2000000 | I70: =SUMIF($AB$3:$CI$3,I$4,$AB70:$CI70) -> 3500000 | J70: =SUM(E70:I70) -> 7300000 | K70: =SUMIF($Q$3:$CN$3,K$4,$Q70:$CN70) -> 0 | L70: =SUMIF($Q$3:$CN$3,L$4,$Q70:$CN70) -> 0 | M70: =SUMIF($Q$3:$CN$3,M$4,$Q70:$CN70) -> 0 | N70: =SUMIF($Q$3:$CN$3,N$4,$Q70:$CN70) -> 0 | AB70: =ROUND(INDEX(販管費予算!$E$27:$I$27,MATCH(AB$3,販管費予算!$E$4:$I$4,0))/12,0)+IF(COUNTIF($AB$3:AB$3,AB$3)=12,INDEX(販管費予算!$E$27:$I$27,MATCH(AB$3,販管費予算!$E$4:$I$4,0))-12*ROUND(INDEX(販管費予算!$E$27:$I$27,MATCH(AB$3,販管費予算!$E$4:$I$4,0))/12,0),0) -> 25000 | AC70: =ROUND(INDEX(販管費予算!$E$27:$I$27,MATCH(AC$3,販管費予算!$E$4:$I$4,0))/12,0)+IF(COUNTIF($AB$3:AC$3,AC$3)=12,INDEX(販管費予算!$E$27:$I$27,MATCH(AC$3,販管費予算!$E$4:$I$4,0))-12*ROUND(INDEX(販管費予算!$E$27:$I$27,MATCH(AC$3,販管費予算!$E$4:$I$4,0))/12,0),0) -> 25000 | AD70: =ROUND(INDEX(販管費予算!$E$27:$I$27,MATCH(AD$3,販管費予算!$E$4:$I$4,0))/12,0)+IF(COUNTIF($AB$3:AD$3,AD$3)=12,INDEX(販管費予算!$E$27:$I$27,MATCH(AD$3,販管費予算!$E$4:$I$4,0))-12*ROUND(INDEX(販管費予算!$E$27:$I$27,MATCH(AD$3,販管費予算!$E$4:$I$4,0))/12,0),0) -> 25000 | AE70: =ROUND(INDEX(販管費予算!$E$27:$I$27,MATCH(AE$3,販管費予算!$E$4:$I$4,0))/12,0)+IF(COUNTIF($AB$3:AE$3,AE$3)=12,INDEX(販管費予算!$E$27:$I$27,MATCH(AE$3,販管費予算!$E$4:$I$4,0))-12*ROUND(INDEX(販管費予算!$E$27:$I$27,MATCH(AE$3,販管費予算!$E$4:$I$4,0))/12,0),0) -> 25000 | AF70: =ROUND(INDEX(販管費予算!$E$27:$I$27,MATCH(AF$3,販管費予算!$E$4:$I$4,0))/12,0)+IF(COUNTIF($AB$3:AF$3,AF$3)=12,INDEX(販管費予算!$E$27:$I$27,MATCH(AF$3,販管費予算!$E$4:$I$4,0))-12*ROUND(INDEX(販管費予算!$E$27:$I$27,MATCH(AF$3,販管費予算!$E$4:$I$4,0))/12,0),0) -> 25000 | AG70: =ROUND(INDEX(販管費予算!$E$27:$I$27,MATCH(AG$3,販管費予算!$E$4:$I$4,0))/12,0)+IF(COUNTIF($AB$3:AG$3,AG$3)=12,INDEX(販管費予算!$E$27:$I$27,MATCH(AG$3,販管費予算!$E$4:$I$4,0))-12*ROUND(INDEX(販管費予算!$E$27:$I$27,MATCH(AG$3,販管費予算!$E$4:$I$4,0))/12,0),0) -> 25000 | AH70: =ROUND(INDEX(販管費予算!$E$27:$I$27,MATCH(AH$3,販管費予算!$E$4:$I$4,0))/12,0)+IF(COUNTIF($AB$3:AH$3,AH$3)=12,INDEX(販管費予算!$E$27:$I$27,MATCH(AH$3,販管費予算!$E$4:$I$4,0))-12*ROUND(INDEX(販管費予算!$E$27:$I$27,MATCH(AH$3,販管費予算!$E$4:$I$4,0))/12,0),0) -> 25000 | AI70: =ROUND(INDEX(販管費予算!$E$27:$I$27,MATCH(AI$3,販管費予算!$E$4:$I$4,0))/12,0)+IF(COUNTIF($AB$3:AI$3,AI$3)=12,INDEX(販管費予算!$E$27:$I$27,MATCH(AI$3,販管費予算!$E$4:$I$4,0))-12*ROUND(INDEX(販管費予算!$E$27:$I$27,MATCH(AI$3,販管費予算!$E$4:$I$4,0))/12,0),0) -> 25000 | ... CI70: =ROUND(INDEX(販管費予算!$E$27:$I$27,MATCH(CI$3,販管費予算!$E$4:$I$4,0))/12,0)+IF(COUNTIF($AB$3:CI$3,CI$3)=12,INDEX(販管費予算!$E$27:$I$27,MATCH(CI$3,販管費予算!$E$4:$I$4,0))-12*ROUND(INDEX(販管費予算!$E$27:$I$27,MATCH(CI$3,販管費予算!$E$4:$I$4,0))/12,0),0) -> 291663
B71: 支払報酬料 | C71: 全社 | E71: =SUMIF($AB$3:$CI$3,E$4,$AB71:$CI71) -> 2000000 | F71: =SUMIF($AB$3:$CI$3,F$4,$AB71:$CI71) -> 4000000 | G71: =SUMIF($AB$3:$CI$3,G$4,$AB71:$CI71) -> 8000000 | H71: =SUMIF($AB$3:$CI$3,H$4,$AB71:$CI71) -> 12000000 | I71: =SUMIF($AB$3:$CI$3,I$4,$AB71:$CI71) -> 18000000 | J71: =SUM(E71:I71) -> 44000000 | K71: =SUMIF($Q$3:$CN$3,K$4,$Q71:$CN71) -> 0 | L71: =SUMIF($Q$3:$CN$3,L$4,$Q71:$CN71) -> 0 | M71: =SUMIF($Q$3:$CN$3,M$4,$Q71:$CN71) -> 0 | N71: =SUMIF($Q$3:$CN$3,N$4,$Q71:$CN71) -> 0 | AB71: =ROUND(INDEX(販管費予算!$E$28:$I$28,MATCH(AB$3,販管費予算!$E$4:$I$4,0))/12,0)+IF(COUNTIF($AB$3:AB$3,AB$3)=12,INDEX(販管費予算!$E$28:$I$28,MATCH(AB$3,販管費予算!$E$4:$I$4,0))-12*ROUND(INDEX(販管費予算!$E$28:$I$28,MATCH(AB$3,販管費予算!$E$4:$I$4,0))/12,0),0) -> 166667 | AC71: =ROUND(INDEX(販管費予算!$E$28:$I$28,MATCH(AC$3,販管費予算!$E$4:$I$4,0))/12,0)+IF(COUNTIF($AB$3:AC$3,AC$3)=12,INDEX(販管費予算!$E$28:$I$28,MATCH(AC$3,販管費予算!$E$4:$I$4,0))-12*ROUND(INDEX(販管費予算!$E$28:$I$28,MATCH(AC$3,販管費予算!$E$4:$I$4,0))/12,0),0) -> 166667 | AD71: =ROUND(INDEX(販管費予算!$E$28:$I$28,MATCH(AD$3,販管費予算!$E$4:$I$4,0))/12,0)+IF(COUNTIF($AB$3:AD$3,AD$3)=12,INDEX(販管費予算!$E$28:$I$28,MATCH(AD$3,販管費予算!$E$4:$I$4,0))-12*ROUND(INDEX(販管費予算!$E$28:$I$28,MATCH(AD$3,販管費予算!$E$4:$I$4,0))/12,0),0) -> 166667 | AE71: =ROUND(INDEX(販管費予算!$E$28:$I$28,MATCH(AE$3,販管費予算!$E$4:$I$4,0))/12,0)+IF(COUNTIF($AB$3:AE$3,AE$3)=12,INDEX(販管費予算!$E$28:$I$28,MATCH(AE$3,販管費予算!$E$4:$I$4,0))-12*ROUND(INDEX(販管費予算!$E$28:$I$28,MATCH(AE$3,販管費予算!$E$4:$I$4,0))/12,0),0) -> 166667 | AF71: =ROUND(INDEX(販管費予算!$E$28:$I$28,MATCH(AF$3,販管費予算!$E$4:$I$4,0))/12,0)+IF(COUNTIF($AB$3:AF$3,AF$3)=12,INDEX(販管費予算!$E$28:$I$28,MATCH(AF$3,販管費予算!$E$4:$I$4,0))-12*ROUND(INDEX(販管費予算!$E$28:$I$28,MATCH(AF$3,販管費予算!$E$4:$I$4,0))/12,0),0) -> 166667 | AG71: =ROUND(INDEX(販管費予算!$E$28:$I$28,MATCH(AG$3,販管費予算!$E$4:$I$4,0))/12,0)+IF(COUNTIF($AB$3:AG$3,AG$3)=12,INDEX(販管費予算!$E$28:$I$28,MATCH(AG$3,販管費予算!$E$4:$I$4,0))-12*ROUND(INDEX(販管費予算!$E$28:$I$28,MATCH(AG$3,販管費予算!$E$4:$I$4,0))/12,0),0) -> 166667 | AH71: =ROUND(INDEX(販管費予算!$E$28:$I$28,MATCH(AH$3,販管費予算!$E$4:$I$4,0))/12,0)+IF(COUNTIF($AB$3:AH$3,AH$3)=12,INDEX(販管費予算!$E$28:$I$28,MATCH(AH$3,販管費予算!$E$4:$I$4,0))-12*ROUND(INDEX(販管費予算!$E$28:$I$28,MATCH(AH$3,販管費予算!$E$4:$I$4,0))/12,0),0) -> 166667 | AI71: =ROUND(INDEX(販管費予算!$E$28:$I$28,MATCH(AI$3,販管費予算!$E$4:$I$4,0))/12,0)+IF(COUNTIF($AB$3:AI$3,AI$3)=12,INDEX(販管費予算!$E$28:$I$28,MATCH(AI$3,販管費予算!$E$4:$I$4,0))-12*ROUND(INDEX(販管費予算!$E$28:$I$28,MATCH(AI$3,販管費予算!$E$4:$I$4,0))/12,0),0) -> 166667 | ... CI71: =ROUND(INDEX(販管費予算!$E$28:$I$28,MATCH(CI$3,販管費予算!$E$4:$I$4,0))/12,0)+IF(COUNTIF($AB$3:CI$3,CI$3)=12,INDEX(販管費予算!$E$28:$I$28,MATCH(CI$3,販管費予算!$E$4:$I$4,0))-12*ROUND(INDEX(販管費予算!$E$28:$I$28,MATCH(CI$3,販管費予算!$E$4:$I$4,0))/12,0),0) -> 1500000
B72: 減価償却費 | E72: =SUMIF($AB$3:$CI$3,E$4,$AB72:$CI72) -> 0 | F72: =SUMIF($AB$3:$CI$3,F$4,$AB72:$CI72) -> 500000 | G72: =SUMIF($AB$3:$CI$3,G$4,$AB72:$CI72) -> 1000000 | H72: =SUMIF($AB$3:$CI$3,H$4,$AB72:$CI72) -> 2000000 | I72: =SUMIF($AB$3:$CI$3,I$4,$AB72:$CI72) -> 4000000 | J72: =SUM(E72:I72) -> 7500000 | K72: =SUMIF($Q$3:$CN$3,K$4,$Q72:$CN72) -> 0 | L72: =SUMIF($Q$3:$CN$3,L$4,$Q72:$CN72) -> 0 | M72: =SUMIF($Q$3:$CN$3,M$4,$Q72:$CN72) -> 0 | N72: =SUMIF($Q$3:$CN$3,N$4,$Q72:$CN72) -> 0 | AB72: =SUM(AB73:AB74) -> 0 | AC72: =SUM(AC73:AC74) -> 0 | AD72: =SUM(AD73:AD74) -> 0 | AE72: =SUM(AE73:AE74) -> 0 | AF72: =SUM(AF73:AF74) -> 0 | AG72: =SUM(AG73:AG74) -> 0 | AH72: =SUM(AH73:AH74) -> 0 | AI72: =SUM(AI73:AI74) -> 0 | ... CI72: =SUM(CI73:CI74) -> 333337
C73: 全社 | E73: =SUMIF($AB$3:$CI$3,E$4,$AB73:$CI73) -> 0 | F73: =SUMIF($AB$3:$CI$3,F$4,$AB73:$CI73) -> 500000 | G73: =SUMIF($AB$3:$CI$3,G$4,$AB73:$CI73) -> 1000000 | H73: =SUMIF($AB$3:$CI$3,H$4,$AB73:$CI73) -> 2000000 | I73: =SUMIF($AB$3:$CI$3,I$4,$AB73:$CI73) -> 4000000 | J73: =SUM(E73:I73) -> 7500000 | AB73: =ROUND(INDEX(販管費予算!$E$29:$I$29,MATCH(AB$3,販管費予算!$E$4:$I$4,0))/12,0)+IF(COUNTIF($AB$3:AB$3,AB$3)=12,INDEX(販管費予算!$E$29:$I$29,MATCH(AB$3,販管費予算!$E$4:$I$4,0))-12*ROUND(INDEX(販管費予算!$E$29:$I$29,MATCH(AB$3,販管費予算!$E$4:$I$4,0))/12,0),0) -> 0 | AC73: =ROUND(INDEX(販管費予算!$E$29:$I$29,MATCH(AC$3,販管費予算!$E$4:$I$4,0))/12,0)+IF(COUNTIF($AB$3:AC$3,AC$3)=12,INDEX(販管費予算!$E$29:$I$29,MATCH(AC$3,販管費予算!$E$4:$I$4,0))-12*ROUND(INDEX(販管費予算!$E$29:$I$29,MATCH(AC$3,販管費予算!$E$4:$I$4,0))/12,0),0) -> 0 | AD73: =ROUND(INDEX(販管費予算!$E$29:$I$29,MATCH(AD$3,販管費予算!$E$4:$I$4,0))/12,0)+IF(COUNTIF($AB$3:AD$3,AD$3)=12,INDEX(販管費予算!$E$29:$I$29,MATCH(AD$3,販管費予算!$E$4:$I$4,0))-12*ROUND(INDEX(販管費予算!$E$29:$I$29,MATCH(AD$3,販管費予算!$E$4:$I$4,0))/12,0),0) -> 0 | AE73: =ROUND(INDEX(販管費予算!$E$29:$I$29,MATCH(AE$3,販管費予算!$E$4:$I$4,0))/12,0)+IF(COUNTIF($AB$3:AE$3,AE$3)=12,INDEX(販管費予算!$E$29:$I$29,MATCH(AE$3,販管費予算!$E$4:$I$4,0))-12*ROUND(INDEX(販管費予算!$E$29:$I$29,MATCH(AE$3,販管費予算!$E$4:$I$4,0))/12,0),0) -> 0 | AF73: =ROUND(INDEX(販管費予算!$E$29:$I$29,MATCH(AF$3,販管費予算!$E$4:$I$4,0))/12,0)+IF(COUNTIF($AB$3:AF$3,AF$3)=12,INDEX(販管費予算!$E$29:$I$29,MATCH(AF$3,販管費予算!$E$4:$I$4,0))-12*ROUND(INDEX(販管費予算!$E$29:$I$29,MATCH(AF$3,販管費予算!$E$4:$I$4,0))/12,0),0) -> 0 | AG73: =ROUND(INDEX(販管費予算!$E$29:$I$29,MATCH(AG$3,販管費予算!$E$4:$I$4,0))/12,0)+IF(COUNTIF($AB$3:AG$3,AG$3)=12,INDEX(販管費予算!$E$29:$I$29,MATCH(AG$3,販管費予算!$E$4:$I$4,0))-12*ROUND(INDEX(販管費予算!$E$29:$I$29,MATCH(AG$3,販管費予算!$E$4:$I$4,0))/12,0),0) -> 0 | AH73: =ROUND(INDEX(販管費予算!$E$29:$I$29,MATCH(AH$3,販管費予算!$E$4:$I$4,0))/12,0)+IF(COUNTIF($AB$3:AH$3,AH$3)=12,INDEX(販管費予算!$E$29:$I$29,MATCH(AH$3,販管費予算!$E$4:$I$4,0))-12*ROUND(INDEX(販管費予算!$E$29:$I$29,MATCH(AH$3,販管費予算!$E$4:$I$4,0))/12,0),0) -> 0 | AI73: =ROUND(INDEX(販管費予算!$E$29:$I$29,MATCH(AI$3,販管費予算!$E$4:$I$4,0))/12,0)+IF(COUNTIF($AB$3:AI$3,AI$3)=12,INDEX(販管費予算!$E$29:$I$29,MATCH(AI$3,販管費予算!$E$4:$I$4,0))-12*ROUND(INDEX(販管費予算!$E$29:$I$29,MATCH(AI$3,販管費予算!$E$4:$I$4,0))/12,0),0) -> 0 | ... CI73: =ROUND(INDEX(販管費予算!$E$29:$I$29,MATCH(CI$3,販管費予算!$E$4:$I$4,0))/12,0)+IF(COUNTIF($AB$3:CI$3,CI$3)=12,INDEX(販管費予算!$E$29:$I$29,MATCH(CI$3,販管費予算!$E$4:$I$4,0))-12*ROUND(INDEX(販管費予算!$E$29:$I$29,MATCH(CI$3,販管費予算!$E$4:$I$4,0))/12,0),0) -> 333337
C74: プロダクト | E74: =SUMIF($AB$3:$CI$3,E$4,$AB74:$CI74) -> 0 | F74: =SUMIF($AB$3:$CI$3,F$4,$AB74:$CI74) -> 0 | G74: =SUMIF($AB$3:$CI$3,G$4,$AB74:$CI74) -> 0 | H74: =SUMIF($AB$3:$CI$3,H$4,$AB74:$CI74) -> 0 | I74: =SUMIF($AB$3:$CI$3,I$4,$AB74:$CI74) -> 0 | J74: =SUM(E74:I74) -> 0
B75: 研究開発費 | E75: =SUMIF($AB$3:$CI$3,E$4,$AB75:$CI75) -> 6000000 | F75: =SUMIF($AB$3:$CI$3,F$4,$AB75:$CI75) -> 12000000 | G75: =SUMIF($AB$3:$CI$3,G$4,$AB75:$CI75) -> 24000000 | H75: =SUMIF($AB$3:$CI$3,H$4,$AB75:$CI75) -> 36000000 | I75: =SUMIF($AB$3:$CI$3,I$4,$AB75:$CI75) -> 60000000 | J75: =SUM(E75:I75) -> 138000000 | K75: =SUMIF($Q$3:$CN$3,K$4,$Q75:$CN75) -> 0 | L75: =SUMIF($Q$3:$CN$3,L$4,$Q75:$CN75) -> 0 | M75: =SUMIF($Q$3:$CN$3,M$4,$Q75:$CN75) -> 0 | N75: =SUMIF($Q$3:$CN$3,N$4,$Q75:$CN75) -> 0 | AB75: =SUM(AB76:AB77) -> 500000 | AC75: =SUM(AC76:AC77) -> 500000 | AD75: =SUM(AD76:AD77) -> 500000 | AE75: =SUM(AE76:AE77) -> 500000 | AF75: =SUM(AF76:AF77) -> 500000 | AG75: =SUM(AG76:AG77) -> 500000 | AH75: =SUM(AH76:AH77) -> 500000 | AI75: =SUM(AI76:AI77) -> 500000 | ... CI75: =SUM(CI76:CI77) -> 5000000
C76: 全社 | E76: =SUMIF($AB$3:$CI$3,E$4,$AB76:$CI76) -> 6000000 | F76: =SUMIF($AB$3:$CI$3,F$4,$AB76:$CI76) -> 12000000 | G76: =SUMIF($AB$3:$CI$3,G$4,$AB76:$CI76) -> 24000000 | H76: =SUMIF($AB$3:$CI$3,H$4,$AB76:$CI76) -> 36000000 | I76: =SUMIF($AB$3:$CI$3,I$4,$AB76:$CI76) -> 60000000 | J76: =SUM(E76:I76) -> 138000000 | K76: =SUMIF($Q$3:$CN$3,K$4,$Q76:$CN76) -> 0 | L76: =SUMIF($Q$3:$CN$3,L$4,$Q76:$CN76) -> 0 | M76: =SUMIF($Q$3:$CN$3,M$4,$Q76:$CN76) -> 0 | N76: =SUMIF($Q$3:$CN$3,N$4,$Q76:$CN76) -> 0 | AB76: =ROUND(INDEX(販管費予算!$E$30:$I$30,MATCH(AB$3,販管費予算!$E$4:$I$4,0))/12,0)+IF(COUNTIF($AB$3:AB$3,AB$3)=12,INDEX(販管費予算!$E$30:$I$30,MATCH(AB$3,販管費予算!$E$4:$I$4,0))-12*ROUND(INDEX(販管費予算!$E$30:$I$30,MATCH(AB$3,販管費予算!$E$4:$I$4,0))/12,0),0) -> 500000 | AC76: =ROUND(INDEX(販管費予算!$E$30:$I$30,MATCH(AC$3,販管費予算!$E$4:$I$4,0))/12,0)+IF(COUNTIF($AB$3:AC$3,AC$3)=12,INDEX(販管費予算!$E$30:$I$30,MATCH(AC$3,販管費予算!$E$4:$I$4,0))-12*ROUND(INDEX(販管費予算!$E$30:$I$30,MATCH(AC$3,販管費予算!$E$4:$I$4,0))/12,0),0) -> 500000 | AD76: =ROUND(INDEX(販管費予算!$E$30:$I$30,MATCH(AD$3,販管費予算!$E$4:$I$4,0))/12,0)+IF(COUNTIF($AB$3:AD$3,AD$3)=12,INDEX(販管費予算!$E$30:$I$30,MATCH(AD$3,販管費予算!$E$4:$I$4,0))-12*ROUND(INDEX(販管費予算!$E$30:$I$30,MATCH(AD$3,販管費予算!$E$4:$I$4,0))/12,0),0) -> 500000 | AE76: =ROUND(INDEX(販管費予算!$E$30:$I$30,MATCH(AE$3,販管費予算!$E$4:$I$4,0))/12,0)+IF(COUNTIF($AB$3:AE$3,AE$3)=12,INDEX(販管費予算!$E$30:$I$30,MATCH(AE$3,販管費予算!$E$4:$I$4,0))-12*ROUND(INDEX(販管費予算!$E$30:$I$30,MATCH(AE$3,販管費予算!$E$4:$I$4,0))/12,0),0) -> 500000 | AF76: =ROUND(INDEX(販管費予算!$E$30:$I$30,MATCH(AF$3,販管費予算!$E$4:$I$4,0))/12,0)+IF(COUNTIF($AB$3:AF$3,AF$3)=12,INDEX(販管費予算!$E$30:$I$30,MATCH(AF$3,販管費予算!$E$4:$I$4,0))-12*ROUND(INDEX(販管費予算!$E$30:$I$30,MATCH(AF$3,販管費予算!$E$4:$I$4,0))/12,0),0) -> 500000 | AG76: =ROUND(INDEX(販管費予算!$E$30:$I$30,MATCH(AG$3,販管費予算!$E$4:$I$4,0))/12,0)+IF(COUNTIF($AB$3:AG$3,AG$3)=12,INDEX(販管費予算!$E$30:$I$30,MATCH(AG$3,販管費予算!$E$4:$I$4,0))-12*ROUND(INDEX(販管費予算!$E$30:$I$30,MATCH(AG$3,販管費予算!$E$4:$I$4,0))/12,0),0) -> 500000 | AH76: =ROUND(INDEX(販管費予算!$E$30:$I$30,MATCH(AH$3,販管費予算!$E$4:$I$4,0))/12,0)+IF(COUNTIF($AB$3:AH$3,AH$3)=12,INDEX(販管費予算!$E$30:$I$30,MATCH(AH$3,販管費予算!$E$4:$I$4,0))-12*ROUND(INDEX(販管費予算!$E$30:$I$30,MATCH(AH$3,販管費予算!$E$4:$I$4,0))/12,0),0) -> 500000 | AI76: =ROUND(INDEX(販管費予算!$E$30:$I$30,MATCH(AI$3,販管費予算!$E$4:$I$4,0))/12,0)+IF(COUNTIF($AB$3:AI$3,AI$3)=12,INDEX(販管費予算!$E$30:$I$30,MATCH(AI$3,販管費予算!$E$4:$I$4,0))-12*ROUND(INDEX(販管費予算!$E$30:$I$30,MATCH(AI$3,販管費予算!$E$4:$I$4,0))/12,0),0) -> 500000 | ... CI76: =ROUND(INDEX(販管費予算!$E$30:$I$30,MATCH(CI$3,販管費予算!$E$4:$I$4,0))/12,0)+IF(COUNTIF($AB$3:CI$3,CI$3)=12,INDEX(販管費予算!$E$30:$I$30,MATCH(CI$3,販管費予算!$E$4:$I$4,0))-12*ROUND(INDEX(販管費予算!$E$30:$I$30,MATCH(CI$3,販管費予算!$E$4:$I$4,0))/12,0),0) -> 5000000
C77: プロダクト | E77: =SUMIF($AB$3:$CI$3,E$4,$AB77:$CI77) -> 0 | F77: =SUMIF($AB$3:$CI$3,F$4,$AB77:$CI77) -> 0 | G77: =SUMIF($AB$3:$CI$3,G$4,$AB77:$CI77) -> 0 | H77: =SUMIF($AB$3:$CI$3,H$4,$AB77:$CI77) -> 0 | I77: =SUMIF($AB$3:$CI$3,I$4,$AB77:$CI77) -> 0 | J77: =SUM(E77:I77) -> 0 | K77: =SUMIF($Q$3:$CN$3,K$4,$Q77:$CN77) -> 0 | L77: =SUMIF($Q$3:$CN$3,L$4,$Q77:$CN77) -> 0 | M77: =SUMIF($Q$3:$CN$3,M$4,$Q77:$CN77) -> 0 | N77: =SUMIF($Q$3:$CN$3,N$4,$Q77:$CN77) -> 0
B78: 諸会費 | C78: 全社 | E78: =SUMIF($AB$3:$CI$3,E$4,$AB78:$CI78) -> 300000 | F78: =SUMIF($AB$3:$CI$3,F$4,$AB78:$CI78) -> 500000 | G78: =SUMIF($AB$3:$CI$3,G$4,$AB78:$CI78) -> 800000 | H78: =SUMIF($AB$3:$CI$3,H$4,$AB78:$CI78) -> 1000000 | I78: =SUMIF($AB$3:$CI$3,I$4,$AB78:$CI78) -> 2000000 | J78: =SUM(E78:I78) -> 4600000 | K78: =SUMIF($Q$3:$CN$3,K$4,$Q78:$CN78) -> 0 | L78: =SUMIF($Q$3:$CN$3,L$4,$Q78:$CN78) -> 0 | M78: =SUMIF($Q$3:$CN$3,M$4,$Q78:$CN78) -> 0 | N78: =SUMIF($Q$3:$CN$3,N$4,$Q78:$CN78) -> 0 | AB78: =ROUND(INDEX(販管費予算!$E$31:$I$31,MATCH(AB$3,販管費予算!$E$4:$I$4,0))/12,0)+IF(COUNTIF($AB$3:AB$3,AB$3)=12,INDEX(販管費予算!$E$31:$I$31,MATCH(AB$3,販管費予算!$E$4:$I$4,0))-12*ROUND(INDEX(販管費予算!$E$31:$I$31,MATCH(AB$3,販管費予算!$E$4:$I$4,0))/12,0),0) -> 25000 | AC78: =ROUND(INDEX(販管費予算!$E$31:$I$31,MATCH(AC$3,販管費予算!$E$4:$I$4,0))/12,0)+IF(COUNTIF($AB$3:AC$3,AC$3)=12,INDEX(販管費予算!$E$31:$I$31,MATCH(AC$3,販管費予算!$E$4:$I$4,0))-12*ROUND(INDEX(販管費予算!$E$31:$I$31,MATCH(AC$3,販管費予算!$E$4:$I$4,0))/12,0),0) -> 25000 | AD78: =ROUND(INDEX(販管費予算!$E$31:$I$31,MATCH(AD$3,販管費予算!$E$4:$I$4,0))/12,0)+IF(COUNTIF($AB$3:AD$3,AD$3)=12,INDEX(販管費予算!$E$31:$I$31,MATCH(AD$3,販管費予算!$E$4:$I$4,0))-12*ROUND(INDEX(販管費予算!$E$31:$I$31,MATCH(AD$3,販管費予算!$E$4:$I$4,0))/12,0),0) -> 25000 | AE78: =ROUND(INDEX(販管費予算!$E$31:$I$31,MATCH(AE$3,販管費予算!$E$4:$I$4,0))/12,0)+IF(COUNTIF($AB$3:AE$3,AE$3)=12,INDEX(販管費予算!$E$31:$I$31,MATCH(AE$3,販管費予算!$E$4:$I$4,0))-12*ROUND(INDEX(販管費予算!$E$31:$I$31,MATCH(AE$3,販管費予算!$E$4:$I$4,0))/12,0),0) -> 25000 | AF78: =ROUND(INDEX(販管費予算!$E$31:$I$31,MATCH(AF$3,販管費予算!$E$4:$I$4,0))/12,0)+IF(COUNTIF($AB$3:AF$3,AF$3)=12,INDEX(販管費予算!$E$31:$I$31,MATCH(AF$3,販管費予算!$E$4:$I$4,0))-12*ROUND(INDEX(販管費予算!$E$31:$I$31,MATCH(AF$3,販管費予算!$E$4:$I$4,0))/12,0),0) -> 25000 | AG78: =ROUND(INDEX(販管費予算!$E$31:$I$31,MATCH(AG$3,販管費予算!$E$4:$I$4,0))/12,0)+IF(COUNTIF($AB$3:AG$3,AG$3)=12,INDEX(販管費予算!$E$31:$I$31,MATCH(AG$3,販管費予算!$E$4:$I$4,0))-12*ROUND(INDEX(販管費予算!$E$31:$I$31,MATCH(AG$3,販管費予算!$E$4:$I$4,0))/12,0),0) -> 25000 | AH78: =ROUND(INDEX(販管費予算!$E$31:$I$31,MATCH(AH$3,販管費予算!$E$4:$I$4,0))/12,0)+IF(COUNTIF($AB$3:AH$3,AH$3)=12,INDEX(販管費予算!$E$31:$I$31,MATCH(AH$3,販管費予算!$E$4:$I$4,0))-12*ROUND(INDEX(販管費予算!$E$31:$I$31,MATCH(AH$3,販管費予算!$E$4:$I$4,0))/12,0),0) -> 25000 | AI78: =ROUND(INDEX(販管費予算!$E$31:$I$31,MATCH(AI$3,販管費予算!$E$4:$I$4,0))/12,0)+IF(COUNTIF($AB$3:AI$3,AI$3)=12,INDEX(販管費予算!$E$31:$I$31,MATCH(AI$3,販管費予算!$E$4:$I$4,0))-12*ROUND(INDEX(販管費予算!$E$31:$I$31,MATCH(AI$3,販管費予算!$E$4:$I$4,0))/12,0),0) -> 25000 | ... CI78: =ROUND(INDEX(販管費予算!$E$31:$I$31,MATCH(CI$3,販管費予算!$E$4:$I$4,0))/12,0)+IF(COUNTIF($AB$3:CI$3,CI$3)=12,INDEX(販管費予算!$E$31:$I$31,MATCH(CI$3,販管費予算!$E$4:$I$4,0))-12*ROUND(INDEX(販管費予算!$E$31:$I$31,MATCH(CI$3,販管費予算!$E$4:$I$4,0))/12,0),0) -> 166663
B79: 雑費 | C79: 全社 | E79: =SUMIF($AB$3:$CI$3,E$4,$AB79:$CI79) -> 200000 | F79: =SUMIF($AB$3:$CI$3,F$4,$AB79:$CI79) -> 300000 | G79: =SUMIF($AB$3:$CI$3,G$4,$AB79:$CI79) -> 500000 | H79: =SUMIF($AB$3:$CI$3,H$4,$AB79:$CI79) -> 700000 | I79: =SUMIF($AB$3:$CI$3,I$4,$AB79:$CI79) -> 1000000 | J79: =SUM(E79:I79) -> 2700000 | K79: =SUMIF($Q$3:$CN$3,K$4,$Q79:$CN79) -> 0 | L79: =SUMIF($Q$3:$CN$3,L$4,$Q79:$CN79) -> 0 | M79: =SUMIF($Q$3:$CN$3,M$4,$Q79:$CN79) -> 0 | N79: =SUMIF($Q$3:$CN$3,N$4,$Q79:$CN79) -> 0 | AB79: =ROUND(INDEX(販管費予算!$E$32:$I$32,MATCH(AB$3,販管費予算!$E$4:$I$4,0))/12,0)+IF(COUNTIF($AB$3:AB$3,AB$3)=12,INDEX(販管費予算!$E$32:$I$32,MATCH(AB$3,販管費予算!$E$4:$I$4,0))-12*ROUND(INDEX(販管費予算!$E$32:$I$32,MATCH(AB$3,販管費予算!$E$4:$I$4,0))/12,0),0) -> 16667 | AC79: =ROUND(INDEX(販管費予算!$E$32:$I$32,MATCH(AC$3,販管費予算!$E$4:$I$4,0))/12,0)+IF(COUNTIF($AB$3:AC$3,AC$3)=12,INDEX(販管費予算!$E$32:$I$32,MATCH(AC$3,販管費予算!$E$4:$I$4,0))-12*ROUND(INDEX(販管費予算!$E$32:$I$32,MATCH(AC$3,販管費予算!$E$4:$I$4,0))/12,0),0) -> 16667 | AD79: =ROUND(INDEX(販管費予算!$E$32:$I$32,MATCH(AD$3,販管費予算!$E$4:$I$4,0))/12,0)+IF(COUNTIF($AB$3:AD$3,AD$3)=12,INDEX(販管費予算!$E$32:$I$32,MATCH(AD$3,販管費予算!$E$4:$I$4,0))-12*ROUND(INDEX(販管費予算!$E$32:$I$32,MATCH(AD$3,販管費予算!$E$4:$I$4,0))/12,0),0) -> 16667 | AE79: =ROUND(INDEX(販管費予算!$E$32:$I$32,MATCH(AE$3,販管費予算!$E$4:$I$4,0))/12,0)+IF(COUNTIF($AB$3:AE$3,AE$3)=12,INDEX(販管費予算!$E$32:$I$32,MATCH(AE$3,販管費予算!$E$4:$I$4,0))-12*ROUND(INDEX(販管費予算!$E$32:$I$32,MATCH(AE$3,販管費予算!$E$4:$I$4,0))/12,0),0) -> 16667 | AF79: =ROUND(INDEX(販管費予算!$E$32:$I$32,MATCH(AF$3,販管費予算!$E$4:$I$4,0))/12,0)+IF(COUNTIF($AB$3:AF$3,AF$3)=12,INDEX(販管費予算!$E$32:$I$32,MATCH(AF$3,販管費予算!$E$4:$I$4,0))-12*ROUND(INDEX(販管費予算!$E$32:$I$32,MATCH(AF$3,販管費予算!$E$4:$I$4,0))/12,0),0) -> 16667 | AG79: =ROUND(INDEX(販管費予算!$E$32:$I$32,MATCH(AG$3,販管費予算!$E$4:$I$4,0))/12,0)+IF(COUNTIF($AB$3:AG$3,AG$3)=12,INDEX(販管費予算!$E$32:$I$32,MATCH(AG$3,販管費予算!$E$4:$I$4,0))-12*ROUND(INDEX(販管費予算!$E$32:$I$32,MATCH(AG$3,販管費予算!$E$4:$I$4,0))/12,0),0) -> 16667 | AH79: =ROUND(INDEX(販管費予算!$E$32:$I$32,MATCH(AH$3,販管費予算!$E$4:$I$4,0))/12,0)+IF(COUNTIF($AB$3:AH$3,AH$3)=12,INDEX(販管費予算!$E$32:$I$32,MATCH(AH$3,販管費予算!$E$4:$I$4,0))-12*ROUND(INDEX(販管費予算!$E$32:$I$32,MATCH(AH$3,販管費予算!$E$4:$I$4,0))/12,0),0) -> 16667 | AI79: =ROUND(INDEX(販管費予算!$E$32:$I$32,MATCH(AI$3,販管費予算!$E$4:$I$4,0))/12,0)+IF(COUNTIF($AB$3:AI$3,AI$3)=12,INDEX(販管費予算!$E$32:$I$32,MATCH(AI$3,販管費予算!$E$4:$I$4,0))-12*ROUND(INDEX(販管費予算!$E$32:$I$32,MATCH(AI$3,販管費予算!$E$4:$I$4,0))/12,0),0) -> 16667 | ... CI79: =ROUND(INDEX(販管費予算!$E$32:$I$32,MATCH(CI$3,販管費予算!$E$4:$I$4,0))/12,0)+IF(COUNTIF($AB$3:CI$3,CI$3)=12,INDEX(販管費予算!$E$32:$I$32,MATCH(CI$3,販管費予算!$E$4:$I$4,0))-12*ROUND(INDEX(販管費予算!$E$32:$I$32,MATCH(CI$3,販管費予算!$E$4:$I$4,0))/12,0),0) -> 83337
A80: 営業損益 | D80: 円 | E80: =E23-E25 -> -33249571 | F80: =F23-F25 -> -11905996 | G80: =G23-G25 -> -4146493.8 | H80: =H23-H25 -> 4344500.1 | I80: =I23-I25 -> -59169880 | J80: =J23-J25 -> -1.0412744e+08 | K80: =K23-K25 -> 0 | L80: =L23-L25 -> 0 | ... N80: =N23-N25 -> 0 | AB80: =AB23-AB25 -> -4583335 | AC80: =AC23-AC25 -> -4530080.1 | AD80: =AD23-AD25 -> -4271608 | AE80: =AE23-AE25 -> -4017747.4 | AF80: =AF23-AF25 -> -3777519.6 | AG80: =AG23-AG25 -> -3497287 | AH80: =AH23-AH25 -> -2891704.8 | AI80: =AI23-AI25 -> -2290696.6 | ... CI80: =CI23-CI25 -> 1323631.3
C81: 前期比 | D81: ％ | F81: =IF(E80>0,(F80-E80)/E80,"-") -> - | G81: =IF(F80>0,(G80-F80)/F80,"-") -> - | H81: =IF(G80>0,(H80-G80)/G80,"-") -> - | I81: =IF(H80>0,(I80-H80)/H80,"-") -> -14.619491 | J81: =IFERROR((I80/E80)^(1/4)-1,"-") -> 0.15499116 | K81: =IF(K80>0,(K80-J80)/J80,"-") -> - | L81: =IF(L80>0,(L80-K80)/K80,"-") -> - | M81: =IF(M80>0,(M80-L80)/L80,"-") -> - | N81: =IF(N80>0,(N80-M80)/M80,"-") -> -
A83: 検証
O84: PL帳簿 | AB84: 6308793 | AC84: 14260707 | AD84: 11407872 | AE84: 13767658 | AF84: 11673679
AB85: =AB80-AB84 -> -10892128 | AC85: =AC80-AC84 -> -18790787 | AD85: =AD80-AD84 -> -15679480 | AE85: =AE80-AE84 -> -17785405 | AF85: =AF80-AF84 -> -15451199
A87: ■ 営業外損益〜当期純利益（営業損益 80行 から続く）
A88: 営業外収益 | D88: 円 | E88: =SUMIF($AB$3:$CI$3,E$4,$AB88:$CI88) -> 0 | F88: =SUMIF($AB$3:$CI$3,F$4,$AB88:$CI88) -> 0 | G88: =SUMIF($AB$3:$CI$3,G$4,$AB88:$CI88) -> 0 | H88: =SUMIF($AB$3:$CI$3,H$4,$AB88:$CI88) -> 0 | I88: =SUMIF($AB$3:$CI$3,I$4,$AB88:$CI88) -> 0 | J88: =SUM(E88:I88) -> 0 | AB88: =ROUND(INDEX(販管費予算!$E$36:$I$36,MATCH(AB$3,販管費予算!$E$4:$I$4,0))/12,0)+IF(COUNTIF($AB$3:AB$3,AB$3)=12,INDEX(販管費予算!$E$36:$I$36,MATCH(AB$3,販管費予算!$E$4:$I$4,0))-12*ROUND(INDEX(販管費予算!$E$36:$I$36,MATCH(AB$3,販管費予算!$E$4:$I$4,0))/12,0),0) -> 0 | AC88: =ROUND(INDEX(販管費予算!$E$36:$I$36,MATCH(AC$3,販管費予算!$E$4:$I$4,0))/12,0)+IF(COUNTIF($AB$3:AC$3,AC$3)=12,INDEX(販管費予算!$E$36:$I$36,MATCH(AC$3,販管費予算!$E$4:$I$4,0))-12*ROUND(INDEX(販管費予算!$E$36:$I$36,MATCH(AC$3,販管費予算!$E$4:$I$4,0))/12,0),0) -> 0 | AD88: =ROUND(INDEX(販管費予算!$E$36:$I$36,MATCH(AD$3,販管費予算!$E$4:$I$4,0))/12,0)+IF(COUNTIF($AB$3:AD$3,AD$3)=12,INDEX(販管費予算!$E$36:$I$36,MATCH(AD$3,販管費予算!$E$4:$I$4,0))-12*ROUND(INDEX(販管費予算!$E$36:$I$36,MATCH(AD$3,販管費予算!$E$4:$I$4,0))/12,0),0) -> 0 | AE88: =ROUND(INDEX(販管費予算!$E$36:$I$36,MATCH(AE$3,販管費予算!$E$4:$I$4,0))/12,0)+IF(COUNTIF($AB$3:AE$3,AE$3)=12,INDEX(販管費予算!$E$36:$I$36,MATCH(AE$3,販管費予算!$E$4:$I$4,0))-12*ROUND(INDEX(販管費予算!$E$36:$I$36,MATCH(AE$3,販管費予算!$E$4:$I$4,0))/12,0),0) -> 0 | AF88: =ROUND(INDEX(販管費予算!$E$36:$I$36,MATCH(AF$3,販管費予算!$E$4:$I$4,0))/12,0)+IF(COUNTIF($AB$3:AF$3,AF$3)=12,INDEX(販管費予算!$E$36:$I$36,MATCH(AF$3,販管費予算!$E$4:$I$4,0))-12*ROUND(INDEX(販管費予算!$E$36:$I$36,MATCH(AF$3,販管費予算!$E$4:$I$4,0))/12,0),0) -> 0 | AG88: =ROUND(INDEX(販管費予算!$E$36:$I$36,MATCH(AG$3,販管費予算!$E$4:$I$4,0))/12,0)+IF(COUNTIF($AB$3:AG$3,AG$3)=12,INDEX(販管費予算!$E$36:$I$36,MATCH(AG$3,販管費予算!$E$4:$I$4,0))-12*ROUND(INDEX(販管費予算!$E$36:$I$36,MATCH(AG$3,販管費予算!$E$4:$I$4,0))/12,0),0) -> 0 | AH88: =ROUND(INDEX(販管費予算!$E$36:$I$36,MATCH(AH$3,販管費予算!$E$4:$I$4,0))/12,0)+IF(COUNTIF($AB$3:AH$3,AH$3)=12,INDEX(販管費予算!$E$36:$I$36,MATCH(AH$3,販管費予算!$E$4:$I$4,0))-12*ROUND(INDEX(販管費予算!$E$36:$I$36,MATCH(AH$3,販管費予算!$E$4:$I$4,0))/12,0),0) -> 0 | AI88: =ROUND(INDEX(販管費予算!$E$36:$I$36,MATCH(AI$3,販管費予算!$E$4:$I$4,0))/12,0)+IF(COUNTIF($AB$3:AI$3,AI$3)=12,INDEX(販管費予算!$E$36:$I$36,MATCH(AI$3,販管費予算!$E$4:$I$4,0))-12*ROUND(INDEX(販管費予算!$E$36:$I$36,MATCH(AI$3,販管費予算!$E$4:$I$4,0))/12,0),0) -> 0 | ... CI88: =ROUND(INDEX(販管費予算!$E$36:$I$36,MATCH(CI$3,販管費予算!$E$4:$I$4,0))/12,0)+IF(COUNTIF($AB$3:CI$3,CI$3)=12,INDEX(販管費予算!$E$36:$I$36,MATCH(CI$3,販管費予算!$E$4:$I$4,0))-12*ROUND(INDEX(販管費予算!$E$36:$I$36,MATCH(CI$3,販管費予算!$E$4:$I$4,0))/12,0),0) -> 0
A89: 営業外費用 | D89: 円 | E89: =SUMIF($AB$3:$CI$3,E$4,$AB89:$CI89) -> 0 | F89: =SUMIF($AB$3:$CI$3,F$4,$AB89:$CI89) -> 0 | G89: =SUMIF($AB$3:$CI$3,G$4,$AB89:$CI89) -> 0 | H89: =SUMIF($AB$3:$CI$3,H$4,$AB89:$CI89) -> 0 | I89: =SUMIF($AB$3:$CI$3,I$4,$AB89:$CI89) -> 0 | J89: =SUM(E89:I89) -> 0 | AB89: =ROUND(INDEX(販管費予算!$E$37:$I$37,MATCH(AB$3,販管費予算!$E$4:$I$4,0))/12,0)+IF(COUNTIF($AB$3:AB$3,AB$3)=12,INDEX(販管費予算!$E$37:$I$37,MATCH(AB$3,販管費予算!$E$4:$I$4,0))-12*ROUND(INDEX(販管費予算!$E$37:$I$37,MATCH(AB$3,販管費予算!$E$4:$I$4,0))/12,0),0) -> 0 | AC89: =ROUND(INDEX(販管費予算!$E$37:$I$37,MATCH(AC$3,販管費予算!$E$4:$I$4,0))/12,0)+IF(COUNTIF($AB$3:AC$3,AC$3)=12,INDEX(販管費予算!$E$37:$I$37,MATCH(AC$3,販管費予算!$E$4:$I$4,0))-12*ROUND(INDEX(販管費予算!$E$37:$I$37,MATCH(AC$3,販管費予算!$E$4:$I$4,0))/12,0),0) -> 0 | AD89: =ROUND(INDEX(販管費予算!$E$37:$I$37,MATCH(AD$3,販管費予算!$E$4:$I$4,0))/12,0)+IF(COUNTIF($AB$3:AD$3,AD$3)=12,INDEX(販管費予算!$E$37:$I$37,MATCH(AD$3,販管費予算!$E$4:$I$4,0))-12*ROUND(INDEX(販管費予算!$E$37:$I$37,MATCH(AD$3,販管費予算!$E$4:$I$4,0))/12,0),0) -> 0 | AE89: =ROUND(INDEX(販管費予算!$E$37:$I$37,MATCH(AE$3,販管費予算!$E$4:$I$4,0))/12,0)+IF(COUNTIF($AB$3:AE$3,AE$3)=12,INDEX(販管費予算!$E$37:$I$37,MATCH(AE$3,販管費予算!$E$4:$I$4,0))-12*ROUND(INDEX(販管費予算!$E$37:$I$37,MATCH(AE$3,販管費予算!$E$4:$I$4,0))/12,0),0) -> 0 | AF89: =ROUND(INDEX(販管費予算!$E$37:$I$37,MATCH(AF$3,販管費予算!$E$4:$I$4,0))/12,0)+IF(COUNTIF($AB$3:AF$3,AF$3)=12,INDEX(販管費予算!$E$37:$I$37,MATCH(AF$3,販管費予算!$E$4:$I$4,0))-12*ROUND(INDEX(販管費予算!$E$37:$I$37,MATCH(AF$3,販管費予算!$E$4:$I$4,0))/12,0),0) -> 0 | AG89: =ROUND(INDEX(販管費予算!$E$37:$I$37,MATCH(AG$3,販管費予算!$E$4:$I$4,0))/12,0)+IF(COUNTIF($AB$3:AG$3,AG$3)=12,INDEX(販管費予算!$E$37:$I$37,MATCH(AG$3,販管費予算!$E$4:$I$4,0))-12*ROUND(INDEX(販管費予算!$E$37:$I$37,MATCH(AG$3,販管費予算!$E$4:$I$4,0))/12,0),0) -> 0 | AH89: =ROUND(INDEX(販管費予算!$E$37:$I$37,MATCH(AH$3,販管費予算!$E$4:$I$4,0))/12,0)+IF(COUNTIF($AB$3:AH$3,AH$3)=12,INDEX(販管費予算!$E$37:$I$37,MATCH(AH$3,販管費予算!$E$4:$I$4,0))-12*ROUND(INDEX(販管費予算!$E$37:$I$37,MATCH(AH$3,販管費予算!$E$4:$I$4,0))/12,0),0) -> 0 | AI89: =ROUND(INDEX(販管費予算!$E$37:$I$37,MATCH(AI$3,販管費予算!$E$4:$I$4,0))/12,0)+IF(COUNTIF($AB$3:AI$3,AI$3)=12,INDEX(販管費予算!$E$37:$I$37,MATCH(AI$3,販管費予算!$E$4:$I$4,0))-12*ROUND(INDEX(販管費予算!$E$37:$I$37,MATCH(AI$3,販管費予算!$E$4:$I$4,0))/12,0),0) -> 0 | ... CI89: =ROUND(INDEX(販管費予算!$E$37:$I$37,MATCH(CI$3,販管費予算!$E$4:$I$4,0))/12,0)+IF(COUNTIF($AB$3:CI$3,CI$3)=12,INDEX(販管費予算!$E$37:$I$37,MATCH(CI$3,販管費予算!$E$4:$I$4,0))-12*ROUND(INDEX(販管費予算!$E$37:$I$37,MATCH(CI$3,販管費予算!$E$4:$I$4,0))/12,0),0) -> 0
A90: 経常利益 | D90: 円 | E90: =E80+E88-E89 -> -33249571 | F90: =F80+F88-F89 -> -11905996 | G90: =G80+G88-G89 -> -4146493.8 | H90: =H80+H88-H89 -> 4344500.1 | I90: =I80+I88-I89 -> -59169880 | J90: =J80+J88-J89 -> -1.0412744e+08 | AB90: =AB80+AB88-AB89 -> -4583335 | AC90: =AC80+AC88-AC89 -> -4530080.1 | AD90: =AD80+AD88-AD89 -> -4271608 | AE90: =AE80+AE88-AE89 -> -4017747.4 | AF90: =AF80+AF88-AF89 -> -3777519.6 | AG90: =AG80+AG88-AG89 -> -3497287 | AH90: =AH80+AH88-AH89 -> -2891704.8 | AI90: =AI80+AI88-AI89 -> -2290696.6 | ... CI90: =CI80+CI88-CI89 -> 1323631.3
C91: 前期比 | D91: ％ | F91: =IF(E90>0,(F90-E90)/E90,"-") -> - | G91: =IF(F90>0,(G90-F90)/F90,"-") -> - | H91: =IF(G90>0,(H90-G90)/G90,"-") -> - | I91: =IF(H90>0,(I90-H90)/H90,"-") -> -14.619491 | J91: =IFERROR((I90/E90)^(1/4)-1,"-") -> 0.15499116
A92: 税引前当期純利益 | C92: （特別損益なし：経常利益と同額） | D92: 円 | E92: =E90 -> -33249571 | F92: =F90 -> -11905996 | G92: =G90 -> -4146493.8 | H92: =H90 -> 4344500.1 | I92: =I90 -> -59169880 | J92: =J90 -> -1.0412744e+08 | AB92: =AB90 -> -4583335 | AC92: =AC90 -> -4530080.1 | AD92: =AD90 -> -4271608 | AE92: =AE90 -> -4017747.4 | AF92: =AF90 -> -3777519.6 | AG92: =AG90 -> -3497287 | AH92: =AH90 -> -2891704.8 | AI92: =AI90 -> -2290696.6 | ... CI92: =CI90 -> 1323631.3
A93: 法人税等 | D93: 円 | E93: =SUMIF($AB$3:$CI$3,E$4,$AB93:$CI93) -> 0 | F93: =SUMIF($AB$3:$CI$3,F$4,$AB93:$CI93) -> 0 | G93: =SUMIF($AB$3:$CI$3,G$4,$AB93:$CI93) -> 0 | H93: =SUMIF($AB$3:$CI$3,H$4,$AB93:$CI93) -> 0 | I93: =SUMIF($AB$3:$CI$3,I$4,$AB93:$CI93) -> 0 | J93: =SUM(E93:I93) -> 0 | AB93: =INDEX($E$113:$I$113,MATCH(AB$3,$E$4:$I$4,0))/12 -> 0 | AC93: =INDEX($E$113:$I$113,MATCH(AC$3,$E$4:$I$4,0))/12 -> 0 | AD93: =INDEX($E$113:$I$113,MATCH(AD$3,$E$4:$I$4,0))/12 -> 0 | AE93: =INDEX($E$113:$I$113,MATCH(AE$3,$E$4:$I$4,0))/12 -> 0 | AF93: =INDEX($E$113:$I$113,MATCH(AF$3,$E$4:$I$4,0))/12 -> 0 | AG93: =INDEX($E$113:$I$113,MATCH(AG$3,$E$4:$I$4,0))/12 -> 0 | AH93: =INDEX($E$113:$I$113,MATCH(AH$3,$E$4:$I$4,0))/12 -> 0 | AI93: =INDEX($E$113:$I$113,MATCH(AI$3,$E$4:$I$4,0))/12 -> 0 | ... CI93: =INDEX($E$113:$I$113,MATCH(CI$3,$E$4:$I$4,0))/12 -> 0
A94: 当期純利益 | D94: 円 | E94: =E92-E93 -> -33249571 | F94: =F92-F93 -> -11905996 | G94: =G92-G93 -> -4146493.8 | H94: =H92-H93 -> 4344500.1 | I94: =I92-I93 -> -59169880 | J94: =J92-J93 -> -1.0412744e+08 | AB94: =AB92-AB93 -> -4583335 | AC94: =AC92-AC93 -> -4530080.1 | AD94: =AD92-AD93 -> -4271608 | AE94: =AE92-AE93 -> -4017747.4 | AF94: =AF92-AF93 -> -3777519.6 | AG94: =AG92-AG93 -> -3497287 | AH94: =AH92-AH93 -> -2891704.8 | AI94: =AI92-AI93 -> -2290696.6 | ... CI94: =CI92-CI93 -> 1323631.3
C95: 前期比 | D95: ％ | F95: =IF(E94>0,(F94-E94)/E94,"-") -> - | G95: =IF(F94>0,(G94-F94)/F94,"-") -> - | H95: =IF(G94>0,(H94-G94)/G94,"-") -> - | I95: =IF(H94>0,(I94-H94)/H94,"-") -> -14.619491 | J95: =IFERROR((I94/E94)^(1/4)-1,"-") -> 0.15499116
B96: KPI | C96: 営業利益率 | D96: ％ | E96: =IFERROR(E80/E5,"-") -> -1.439326 | F96: =IFERROR(F80/F5,"-") -> -0.11065225 | G96: =IFERROR(G80/G5,"-") -> -0.019021923 | H96: =IFERROR(H80/H5,"-") -> 0.012517965 | I96: =IFERROR(I80/I5,"-") -> -0.11785901 | J96: =IFERROR(J80/J5,"-") -> -0.086933343 | AB96: =IFERROR(AB80/AB5,"-") -> - | AC96: =IFERROR(AC80/AC5,"-") -> -80.038984 | AD96: =IFERROR(AD80/AD5,"-") -> -12.877095 | AE96: =IFERROR(AE80/AE5,"-") -> -6.6751105 | AF96: =IFERROR(AF80/AF5,"-") -> -4.390569 | AG96: =IFERROR(AG80/AG5,"-") -> -2.9871741 | AH96: =IFERROR(AH80/AH5,"-") -> -1.6015414 | AI96: =IFERROR(AI80/AI5,"-") -> -0.94077334 | ... CI96: =IFERROR(CI80/CI5,"-") -> 0.027299973
B97: KPI | C97: 当期純利益率 | D97: ％ | E97: =IFERROR(E94/E5,"-") -> -1.439326 | F97: =IFERROR(F94/F5,"-") -> -0.11065225 | G97: =IFERROR(G94/G5,"-") -> -0.019021923 | H97: =IFERROR(H94/H5,"-") -> 0.012517965 | I97: =IFERROR(I94/I5,"-") -> -0.11785901 | J97: =IFERROR(J94/J5,"-") -> -0.086933343 | AB97: =IFERROR(AB94/AB5,"-") -> - | AC97: =IFERROR(AC94/AC5,"-") -> -80.038984 | AD97: =IFERROR(AD94/AD5,"-") -> -12.877095 | AE97: =IFERROR(AE94/AE5,"-") -> -6.6751105 | AF97: =IFERROR(AF94/AF5,"-") -> -4.390569 | AG97: =IFERROR(AG94/AG5,"-") -> -2.9871741 | AH97: =IFERROR(AH94/AH5,"-") -> -1.6015414 | AI97: =IFERROR(AI94/AI5,"-") -> -0.94077334 | ... CI97: =IFERROR(CI94/CI5,"-") -> 0.027299973
A99: ■ 事業別売上・SaaS KPI
B100: 事業別 | C100: SaaS事業 | E100: =SUMIF($AB$3:$CI$3,E$4,$AB100:$CI100) -> 13155039 | F100: =SUMIF($AB$3:$CI$3,F$4,$AB100:$CI100) -> 54970475 | G100: =SUMIF($AB$3:$CI$3,G$4,$AB100:$CI100) -> 1.1300102e+08 | H100: =SUMIF($AB$3:$CI$3,H$4,$AB100:$CI100) -> 1.8562995e+08 | I100: =SUMIF($AB$3:$CI$3,I$4,$AB100:$CI100) -> 2.7676127e+08 | J100: =SUM(E100:I100) -> 6.4351776e+08 | AB100: =SUMIF($B$6:$B$12,"SaaS事業",AB$6:AB$12) -> 0 | AC100: =SUMIF($B$6:$B$12,"SaaS事業",AC$6:AC$12) -> 42876.146 | AD100: =SUMIF($B$6:$B$12,"SaaS事業",AD$6:AD$12) -> 256399.35 | AE100: =SUMIF($B$6:$B$12,"SaaS事業",AE$6:AE$12) -> 465652.1 | AF100: =SUMIF($B$6:$B$12,"SaaS事業",AF$6:AF$12) -> 670719.79 | AG100: =SUMIF($B$6:$B$12,"SaaS事業",AG$6:AG$12) -> 914562.27 | AH100: =SUMIF($B$6:$B$12,"SaaS事業",AH$6:AH$12) -> 1153527.9 | AI100: =SUMIF($B$6:$B$12,"SaaS事業",AI$6:AI$12) -> 1387714.2 | ... CI100: =SUMIF($B$6:$B$12,"SaaS事業",CI$6:CI$12) -> 27073469
B101: 事業別 | C101: 紹介事業 | E101: =SUMIF($AB$3:$CI$3,E$4,$AB101:$CI101) -> 3202637.7 | F101: =SUMIF($AB$3:$CI$3,F$4,$AB101:$CI101) -> 12865449 | G101: =SUMIF($AB$3:$CI$3,G$4,$AB101:$CI101) -> 25619622 | H101: =SUMIF($AB$3:$CI$3,H$4,$AB101:$CI101) -> 40934827 | I101: =SUMIF($AB$3:$CI$3,I$4,$AB101:$CI101) -> 59945550 | J101: =SUM(E101:I101) -> 1.4256809e+08 | AB101: =SUMIF($B$6:$B$12,"紹介事業",AB$6:AB$12) -> 0 | AC101: =SUMIF($B$6:$B$12,"紹介事業",AC$6:AC$12) -> 11907.875 | AD101: =SUMIF($B$6:$B$12,"紹介事業",AD$6:AD$12) -> 65379.125 | AE101: =SUMIF($B$6:$B$12,"紹介事業",AE$6:AE$12) -> 118338.82 | AF101: =SUMIF($B$6:$B$12,"紹介事業",AF$6:AF$12) -> 164843.24 | AG101: =SUMIF($B$6:$B$12,"紹介事業",AG$6:AG$12) -> 222821.33 | AH101: =SUMIF($B$6:$B$12,"紹介事業",AH$6:AH$12) -> 280259.71 | AI101: =SUMIF($B$6:$B$12,"紹介事業",AI$6:AI$12) -> 337169.17 | ... CI101: =SUMIF($B$6:$B$12,"紹介事業",CI$6:CI$12) -> 5829504.7
B102: 事業別 | C102: 仲介事業 | E102: =SUMIF($AB$3:$CI$3,E$4,$AB102:$CI102) -> 473115.28 | F102: =SUMIF($AB$3:$CI$3,F$4,$AB102:$CI102) -> 1812400.3 | G102: =SUMIF($AB$3:$CI$3,G$4,$AB102:$CI102) -> 3464352.7 | H102: =SUMIF($AB$3:$CI$3,H$4,$AB102:$CI102) -> 5326427.4 | I102: =SUMIF($AB$3:$CI$3,I$4,$AB102:$CI102) -> 7592704.8 | J102: =SUM(E102:I102) -> 18669001 | AB102: =SUMIF($B$6:$B$12,"仲介事業",AB$6:AB$12) -> 0 | AC102: =SUMIF($B$6:$B$12,"仲介事業",AC$6:AC$12) -> 1814.4 | AD102: =SUMIF($B$6:$B$12,"仲介事業",AD$6:AD$12) -> 9942.912 | AE102: =SUMIF($B$6:$B$12,"仲介事業",AE$6:AE$12) -> 17908.854 | AF102: =SUMIF($B$6:$B$12,"仲介事業",AF$6:AF$12) -> 24808.277 | AG102: =SUMIF($B$6:$B$12,"仲介事業",AG$6:AG$12) -> 33384.111 | AH102: =SUMIF($B$6:$B$12,"仲介事業",AH$6:AH$12) -> 41788.429 | AI102: =SUMIF($B$6:$B$12,"仲介事業",AI$6:AI$12) -> 50024.66 | ... CI102: =SUMIF($B$6:$B$12,"仲介事業",CI$6:CI$12) -> 731737.12
B103: 事業別 | C103: コンサルティング事業 | E103: =SUMIF($AB$3:$CI$3,E$4,$AB103:$CI103) -> 6270000 | F103: =SUMIF($AB$3:$CI$3,F$4,$AB103:$CI103) -> 37950000 | G103: =SUMIF($AB$3:$CI$3,G$4,$AB103:$CI103) -> 75900000 | H103: =SUMIF($AB$3:$CI$3,H$4,$AB103:$CI103) -> 115170000 | I103: =SUMIF($AB$3:$CI$3,I$4,$AB103:$CI103) -> 157740000 | J103: =SUM(E103:I103) -> 393030000 | AB103: =SUMIF($B$6:$B$12,"コンサルティング事業",AB$6:AB$12) -> 0 | AC103: =SUMIF($B$6:$B$12,"コンサルティング事業",AC$6:AC$12) -> 0 | AD103: =SUMIF($B$6:$B$12,"コンサルティング事業",AD$6:AD$12) -> 0 | AE103: =SUMIF($B$6:$B$12,"コンサルティング事業",AE$6:AE$12) -> 0 | AF103: =SUMIF($B$6:$B$12,"コンサルティング事業",AF$6:AF$12) -> 0 | AG103: =SUMIF($B$6:$B$12,"コンサルティング事業",AG$6:AG$12) -> 0 | AH103: =SUMIF($B$6:$B$12,"コンサルティング事業",AH$6:AH$12) -> 330000 | AI103: =SUMIF($B$6:$B$12,"コンサルティング事業",AI$6:AI$12) -> 660000 | ... CI103: =SUMIF($B$6:$B$12,"コンサルティング事業",CI$6:CI$12) -> 14850000
...

Sheet SaaS
C4: 指標 | D4: メモ | F4: M1 | G4: M2 | H4: M3 | I4: M4 | J4: M5 | K4: M6 | L4: M7 | M4: M8 | N4: M9 | O4: M10 | P4: M11 | Q4: M12 | R4: M13 | S4: M1４ | T4: M15 | U4: M16 | V4: M17 | W4: M18 | X4: M19 | Y4: M20 | Z4: M21 | AA4: M22 | AB4: M23 | AC4: M24 | AD4: M25 | AE4: M26 | AF4: M27 | AG4: M28 | AH4: M29 | AI4: M30 | AJ4: M31 | AK4: M32 | AL4: M33 | AM4: M34 | AN4: M35 | AO4: M36 | AP4: M37 | AQ4: M38 | AR4: M39 | AS4: M40 | AT4: M41 | AU4: M42 | AV4: M43 | AW4: M44 | AX4: M45 | AY4: M46 | AZ4: M47 | BA4: M48 | BB4: M49 | BC4: M50 | BD4: M51 | BE4: M52 | BF4: M53 | BG4: M54 | BH4: M55 | BI4: M56 | BJ4: M57 | BK4: M58 | BL4: M59 | BM4: M60 | BN4: Y0 | BO4: Y2 | BP4: Y3 | BQ4: Y4 | BR4: Y5
C5: SAAS売上 | F5: =F6+F10 -> 0 | G5: =G6+G10 -> 42876.146 | H5: =H6+H10 -> 256399.35 | I5: =I6+I10 -> 465652.1 | J5: =J6+J10 -> 670719.79 | K5: =K6+K10 -> 914562.27 | L5: =L6+L10 -> 1153527.9 | M5: =M6+M10 -> 1387714.2 | ... BM5: =BM6+BM10 -> 27073469 | BN5: =SUM(F5:Q5) -> 13155039 | BO5: =SUM(R5:AC5) -> 54970475 | BP5: =SUM(AD5:AO5) -> 1.1300102e+08 | BQ5: =SUM(AP5:BA5) -> 1.8562995e+08 | BR5: =SUM(BB5:BM5) -> 2.7676127e+08
C6: プレミアムプラン売上 | F6: =F7*F8 -> 0 | G6: =G7*G8 -> 7200 | H6: =H7*H8 -> 43056 | I6: =I7*I8 -> 78194.88 | J6: =J7*J8 -> 112630.98 | K6: =K7*K8 -> 153578.36 | L6: =L7*L8 -> 193706.8 | M6: =M7*M8 -> 233032.66 | ... BM6: =BM7*BM8 -> 4546326.9 | BN6: =SUM(F6:Q6) -> 2209067 | BO6: =SUM(R6:AC6) -> 9230946.6 | BP6: =SUM(AD6:AO6) -> 18975758 | BQ6: =SUM(AP6:BA6) -> 31172009 | BR6: =SUM(BB6:BM6) -> 46475286
C7: プレミアムプラン追加費用 | F7: 30000 | G7: 30000 | H7: 30000 | I7: 30000 | J7: 30000 | K7: 30000 | L7: 30000 | M7: 30000 | N7: 30000 | O7: 30000 | P7: 30000 | Q7: 30000 | R7: 30000 | S7: 30000 | T7: 30000 | U7: 30000 | V7: 30000 | W7: 30000 | X7: 30000 | Y7: 30000 | Z7: 30000 | AA7: 30000 | AB7: 30000 | AC7: 30000 | AD7: 30000 | AE7: 30000 | AF7: 30000 | AG7: 30000 | AH7: 30000 | AI7: 30000 | AJ7: 30000 | AK7: 30000 | AL7: 30000 | AM7: 30000 | AN7: 30000 | AO7: 30000 | AP7: 30000 | AQ7: 30000 | AR7: 30000 | AS7: 30000 | AT7: 30000 | AU7: 30000 | AV7: 30000 | AW7: 30000 | AX7: 30000 | AY7: 30000 | AZ7: 30000 | BA7: 30000 | BB7: 30000 | BC7: 30000 | BD7: 30000 | BE7: 30000 | BF7: 30000 | BG7: 30000 | BH7: 30000 | BI7: 30000 | BJ7: 30000 | BK7: 30000 | BL7: 30000 | BM7: 30000 | BN7: 30000 | BO7: 30000 | BP7: 30000 | BQ7: 30000 | BR7: 30000
C8: プレミアムプラン加入数 | F8: =F9*F17 -> 0 | G8: =G9*G17 -> 0.24 | H8: =H9*H17 -> 1.4352 | I8: =I9*I17 -> 2.606496 | J8: =J9*J17 -> 3.7543661 | K8: =K9*K17 -> 5.1192788 | L8: =L9*L17 -> 6.4568932 | M8: =M9*M17 -> 7.7677553 | ... BR8: =BR9*BR17 -> 151.54423
C9: プレミアムプラン加入率 | D9: 税理士ドットコム実働率24% | F9: 0.24 | G9: 0.24 | H9: 0.24 | I9: 0.24 | J9: 0.24 | K9: 0.24 | L9: 0.24 | M9: 0.24 | N9: 0.24 | O9: 0.24 | P9: 0.24 | Q9: 0.24 | R9: 0.24 | S9: 0.24 | T9: 0.24 | U9: 0.24 | V9: 0.24 | W9: 0.24 | X9: 0.24 | Y9: 0.24 | Z9: 0.24 | AA9: 0.24 | AB9: 0.24 | AC9: 0.24 | AD9: 0.24 | AE9: 0.24 | AF9: 0.24 | AG9: 0.24 | AH9: 0.24 | AI9: 0.24 | AJ9: 0.24 | AK9: 0.24 | AL9: 0.24 | AM9: 0.24 | AN9: 0.24 | AO9: 0.24 | AP9: 0.24 | AQ9: 0.24 | AR9: 0.24 | AS9: 0.24 | AT9: 0.24 | AU9: 0.24 | AV9: 0.24 | AW9: 0.24 | AX9: 0.24 | AY9: 0.24 | AZ9: 0.24 | BA9: 0.24 | BB9: 0.24 | BC9: 0.24 | BD9: 0.24 | BE9: 0.24 | BF9: 0.24 | BG9: 0.24 | BH9: 0.24 | BI9: 0.24 | BJ9: 0.24 | BK9: 0.24 | BL9: 0.24 | BM9: 0.24 | BN9: 0.24 | BO9: 0.24 | BP9: 0.24 | BQ9: 0.24 | BR9: 0.24
C10: 通常プラン売上 | F10: =F11*F12 -> 0 | G10: =G11*G12 -> 35676.146 | H10: =H11*H12 -> 213343.35 | I10: =I11*I12 -> 387457.22 | J10: =J11*J12 -> 558088.8 | K10: =K11*K12 -> 760983.9 | L10: =L11*L12 -> 959821.1 | M10: =M11*M12 -> 1154681.6 | ... BM10: =BM11*BM12 -> 22527142 | BN10: =SUM(F10:Q10) -> 10945972 | BO10: =SUM(R10:AC10) -> 45739528 | BP10: =SUM(AD10:AO10) -> 94025265 | BQ10: =SUM(AP10:BA10) -> 1.5445794e+08 | BR10: =SUM(BB10:BM10) -> 2.3028599e+08
C11: システム利用料アカウント単価 | F11: 19800 | G11: 19800 | H11: 19800 | I11: 19800 | J11: 19800 | K11: 19800 | L11: 19800 | M11: 19800 | N11: 19800 | O11: 19800 | P11: 19800 | Q11: 19800 | R11: 19800 | S11: 19800 | T11: 19800 | U11: 19800 | V11: 19800 | W11: 19800 | X11: 19800 | Y11: 19800 | Z11: 19800 | AA11: 19800 | AB11: 19800 | AC11: 19800 | AD11: 19800 | AE11: 19800 | AF11: 19800 | AG11: 19800 | AH11: 19800 | AI11: 19800 | AJ11: 19800 | AK11: 19800 | AL11: 19800 | AM11: 19800 | AN11: 19800 | AO11: 19800 | AP11: 19800 | AQ11: 19800 | AR11: 19800 | AS11: 19800 | AT11: 19800 | AU11: 19800 | AV11: 19800 | AW11: 19800 | AX11: 19800 | AY11: 19800 | AZ11: 19800 | BA11: 19800 | BB11: 19800 | BC11: 19800 | BD11: 19800 | BE11: 19800 | BF11: 19800 | BG11: 19800 | BH11: 19800 | BI11: 19800 | BJ11: 19800 | BK11: 19800 | BL11: 19800 | BM11: 19800 | BN11: 19800 | BO11: 19800 | BP11: 19800 | BQ11: 19800 | BR11: 19800
C12: アカウント数 | F12: =F14*F17+F15*F17*F16 -> 0 | G12: =G14*G17+G15*G17*G16 -> 1.8018256 | H12: =H14*H17+H15*H17*H16 -> 10.774917 | I12: =I14*I17+I15*I17*I16 -> 19.568546 | J12: =J14*J17+J15*J17*J16 -> 28.186303 | K12: =K14*K17+K15*K17*K16 -> 38.433531 | L12: =L14*L17+L15*L17*L16 -> 48.475813 | M12: =M14*M17+M15*M17*M16 -> 58.31725 | ... BM12: =BM14*BM17+BM15*BM17*BM16 -> 1137.7344 | BN12: =Q12 -> 104.54946 | BO12: =AC12 -> 274.35954 | BP12: =AO12 -> 505.70145 | BQ12: =BQ14*BQ17+BQ15*BQ17*BQ16 -> 778.36853 | BR12: =BR14*BR17+BR15*BR17*BR16 -> 1137.7344
C13: 税理士登録者 | D13: 82276 | F13: 0.99964753 | G13: 0.99964753 | H13: 0.99964753 | I13: 0.99964753 | J13: 0.99964753 | K13: 0.99964753 | L13: 0.99964753 | M13: 0.99964753 | N13: 0.99964753 | O13: 0.99964753 | P13: 0.99964753 | Q13: 0.99964753 | R13: 0.99964753 | S13: 0.99964753 | T13: 0.99964753 | U13: 0.99964753 | V13: 0.99964753 | W13: 0.99964753 | X13: 0.99964753 | Y13: 0.99964753 | Z13: 0.99964753 | AA13: 0.99964753 | AB13: 0.99964753 | AC13: 0.99964753 | AD13: 0.99964753 | AE13: 0.99964753 | AF13: 0.99964753 | AG13: 0.99964753 | AH13: 0.99964753 | AI13: 0.99964753 | AJ13: 0.99964753 | AK13: 0.99964753 | AL13: 0.99964753 | AM13: 0.99964753 | AN13: 0.99964753 | AO13: 0.99964753 | AP13: 0.99964753 | AQ13: 0.99964753 | AR13: 0.99964753 | AS13: 0.99964753 | AT13: 0.99964753 | AU13: 0.99964753 | AV13: 0.99964753 | AW13: 0.99964753 | AX13: 0.99964753 | AY13: 0.99964753 | AZ13: 0.99964753 | BA13: 0.99964753 | BB13: 0.99964753 | BC13: 0.99964753 | BD13: 0.99964753 | BE13: 0.99964753 | BF13: 0.99964753 | BG13: 0.99964753 | BH13: 0.99964753 | BI13: 0.99964753 | BJ13: 0.99964753 | BK13: 0.99964753 | BL13: 0.99964753 | BM13: 0.99964753 | BN13: 0.99964753 | BO13: 0.99964753 | BP13: 0.99964753 | BQ13: 0.99964753 | BR13: 0.99964753
C14: ├ 開業税理士（個人事務所の所長） | D14: 55847 | F14: 0.67877631 | G14: 0.67877631 | H14: 0.67877631 | I14: 0.67877631 | J14: 0.67877631 | K14: 0.67877631 | L14: 0.67877631 | M14: 0.67877631 | N14: 0.67877631 | O14: 0.67877631 | P14: 0.67877631 | Q14: 0.67877631 | R14: 0.67877631 | S14: 0.67877631 | T14: 0.67877631 | U14: 0.67877631 | V14: 0.67877631 | W14: 0.67877631 | X14: 0.67877631 | Y14: 0.67877631 | Z14: 0.67877631 | AA14: 0.67877631 | AB14: 0.67877631 | AC14: 0.67877631 | AD14: 0.67877631 | AE14: 0.67877631 | AF14: 0.67877631 | AG14: 0.67877631 | AH14: 0.67877631 | AI14: 0.67877631 | AJ14: 0.67877631 | AK14: 0.67877631 | AL14: 0.67877631 | AM14: 0.67877631 | AN14: 0.67877631 | AO14: 0.67877631 | AP14: 0.67877631 | AQ14: 0.67877631 | AR14: 0.67877631 | AS14: 0.67877631 | AT14: 0.67877631 | AU14: 0.67877631 | AV14: 0.67877631 | AW14: 0.67877631 | AX14: 0.67877631 | AY14: 0.67877631 | AZ14: 0.67877631 | BA14: 0.67877631 | BB14: 0.67877631 | BC14: 0.67877631 | BD14: 0.67877631 | BE14: 0.67877631 | BF14: 0.67877631 | BG14: 0.67877631 | BH14: 0.67877631 | BI14: 0.67877631 | BJ14: 0.67877631 | BK14: 0.67877631 | BL14: 0.67877631 | BM14: 0.67877631 | BN14: 0.67877631 | BO14: 0.67877631 | BP14: 0.67877631 | BQ14: 0.67877631 | BR14: 0.67877631
C15: ├ うち法人・勤務系 | D15: 26400 | F15: 0.32087121 | G15: 0.32087121 | H15: 0.32087121 | I15: 0.32087121 | J15: 0.32087121 | K15: 0.32087121 | L15: 0.32087121 | M15: 0.32087121 | N15: 0.32087121 | O15: 0.32087121 | P15: 0.32087121 | Q15: 0.32087121 | R15: 0.32087121 | S15: 0.32087121 | T15: 0.32087121 | U15: 0.32087121 | V15: 0.32087121 | W15: 0.32087121 | X15: 0.32087121 | Y15: 0.32087121 | Z15: 0.32087121 | AA15: 0.32087121 | AB15: 0.32087121 | AC15: 0.32087121 | AD15: 0.32087121 | AE15: 0.32087121 | AF15: 0.32087121 | AG15: 0.32087121 | AH15: 0.32087121 | AI15: 0.32087121 | AJ15: 0.32087121 | AK15: 0.32087121 | AL15: 0.32087121 | AM15: 0.32087121 | AN15: 0.32087121 | AO15: 0.32087121 | AP15: 0.32087121 | AQ15: 0.32087121 | AR15: 0.32087121 | AS15: 0.32087121 | AT15: 0.32087121 | AU15: 0.32087121 | AV15: 0.32087121 | AW15: 0.32087121 | AX15: 0.32087121 | AY15: 0.32087121 | AZ15: 0.32087121 | BA15: 0.32087121 | BB15: 0.32087121 | BC15: 0.32087121 | BD15: 0.32087121 | BE15: 0.32087121 | BF15: 0.32087121 | BG15: 0.32087121 | BH15: 0.32087121 | BI15: 0.32087121 | BJ15: 0.32087121 | BK15: 0.32087121 | BL15: 0.32087121 | BM15: 0.32087121 | BN15: 0.32087121 | BO15: 0.32087121 | BP15: 0.32087121 | BQ15: 0.32087121 | BR15: 0.32087121
C16: └ 法人拠点あたり税理士 | D16: 3.5 | F16: 3.5 | G16: 3.5 | H16: 3.5 | I16: 3.5 | J16: 3.5 | K16: 3.5 | L16: 3.5 | M16: 3.5 | N16: 3.5 | O16: 3.5 | P16: 3.5 | Q16: 3.5 | R16: 3.5 | S16: 3.5 | T16: 3.5 | U16: 3.5 | V16: 3.5 | W16: 3.5 | X16: 3.5 | Y16: 3.5 | Z16: 3.5 | AA16: 3.5 | AB16: 3.5 | AC16: 3.5 | AD16: 3.5 | AE16: 3.5 | AF16: 3.5 | AG16: 3.5 | AH16: 3.5 | AI16: 3.5 | AJ16: 3.5 | AK16: 3.5 | AL16: 3.5 | AM16: 3.5 | AN16: 3.5 | AO16: 3.5 | AP16: 3.5 | AQ16: 3.5 | AR16: 3.5 | AS16: 3.5 | AT16: 3.5 | AU16: 3.5 | AV16: 3.5 | AW16: 3.5 | AX16: 3.5 | AY16: 3.5 | AZ16: 3.5 | BA16: 3.5 | BB16: 3.5 | BC16: 3.5 | BD16: 3.5 | BE16: 3.5 | BF16: 3.5 | BG16: 3.5 | BH16: 3.5 | BI16: 3.5 | BJ16: 3.5 | BK16: 3.5 | BL16: 3.5 | BM16: 3.5 | BN16: 3.5 | BO16: 3.5 | BP16: 3.5 | BQ16: 3.5 | BR16: 3.5
C17: 契約事務所 | F17: =(E17*(1-F20))+F18 -> 0 | G17: =(F17*(1-G20))+G18 -> 1 | H17: =(G17*(1-H20))+H18 -> 5.98 | I17: =(H17*(1-I20))+I18 -> 10.8604 | J17: =(I17*(1-J20))+J18 -> 15.643192 | K17: =(J17*(1-K20))+K18 -> 21.330328 | L17: =(K17*(1-L20))+L18 -> 26.903722 | M17: =(L17*(1-M20))+M18 -> 32.365647 | ... BM17: =(BL17*(1-BM20))+BM18 -> 631.43429 | BN17: =Q17 -> 58.024186 | BO17: =AC17 -> 152.26753 | BP17: =AO17 -> 280.6606 | BQ17: =BA17 -> 431.98884 | BR17: =BM17 -> 631.43429
C18: 新規 | F18: 0 | G18: 1 | H18: 5 | I18: 5 | J18: 5 | K18: =H18+1 -> 6 | L18: =I18+1 -> 6 | M18: =J18+1 -> 6 | N18: =K18+1 -> 7 | O18: =L18+1 -> 7 | P18: =M18+1 -> 7 | Q18: =N18+1 -> 8 | R18: =O18+1 -> 8 | ... BM18: =BJ18+1 -> 24 | BN18: =SUM(F18:Q18) -> 63 | BO18: =SUM(R18:AC18) -> 118 | BP18: =SUM(AD18:AO18) -> 166 | BQ18: =SUM(AP18:BA18) -> 214 | BR18: =SUM(BB18:BM18) -> 262
C19: 解約 | F19: =F17*F20 -> 0 | G19: =G17*G20 -> 0.02 | H19: =H17*H20 -> 0.1196 | I19: =I17*I20 -> 0.217208 | J19: =J17*J20 -> 0.31286384 | K19: =K17*K20 -> 0.42660656 | L19: =L17*L20 -> 0.53807443 | M19: =M17*M20 -> 0.64731294 | ... BM19: =BM17*BM20 -> 6.3143429 | BN19: =SUM(F19:Q19) -> 6.1362973 | BO19: =SUM(R19:AC19) -> 25.641518 | BP19: =SUM(AD19:AO19) -> 39.532829 | BQ19: =SUM(AP19:BA19) -> 64.941686 | BR19: =SUM(BB19:BM19) -> 64.549009
C20: 解約率 | D20: F&M オフィスステーション1.01% | F20: 0.02 | G20: 0.02 | H20: 0.02 | I20: 0.02 | J20: 0.02 | K20: 0.02 | L20: 0.02 | M20: 0.02 | N20: 0.02 | O20: 0.02 | P20: 0.02 | Q20: 0.02 | R20: 0.02 | S20: 0.02 | T20: 0.02 | U20: 0.02 | V20: 0.02 | W20: 0.02 | X20: 0.02 | Y20: 0.02 | Z20: 0.02 | AA20: 0.02 | AB20: 0.02 | AC20: 0.02 | AD20: 0.015 | AE20: 0.015 | AF20: 0.015 | AG20: 0.015 | AH20: 0.015 | AI20: 0.015 | AJ20: 0.015 | AK20: 0.015 | AL20: 0.015 | AM20: 0.015 | AN20: 0.015 | AO20: 0.015 | AP20: 0.015 | AQ20: 0.015 | AR20: 0.015 | AS20: 0.015 | AT20: 0.015 | AU20: 0.015 | AV20: 0.015 | AW20: 0.015 | AX20: 0.015 | AY20: 0.015 | AZ20: 0.015 | BA20: 0.015 | BB20: 0.01 | BC20: 0.01 | BD20: 0.01 | BE20: 0.01 | BF20: 0.01 | BG20: 0.01 | BH20: 0.01 | BI20: 0.01 | BJ20: 0.01 | BK20: 0.01 | BL20: 0.01 | BM20: 0.01 | BN20: =BN19/(BN19+BN17) -> 0.095639823 | BO20: =BO19/(BO19+BO17) -> 0.14412711 | BP20: =BP19/(BP19+BP17) -> 0.12346546 | BQ20: =BQ19/(BQ19+BQ17) -> 0.13068565 | BR20: =BR19/(BR19+BR17) -> 0.092745055
C24: 原価
C25: サーバー・DB費 | D25: Railway/Supabase→スケールで段階増。推定 | F25: 50000 | G25: 50000 | H25: 50000 | I25: 50000 | J25: 50000 | K25: 50000 | L25: 50000 | M25: 50000 | N25: 50000 | O25: 50000 | P25: 50000 | Q25: 50000 | R25: 150000 | S25: 150000 | T25: 150000 | U25: 150000 | V25: 150000 | W25: 150000 | X25: 150000 | Y25: 150000 | Z25: 150000 | AA25: 150000 | AB25: 150000 | AC25: 150000 | AD25: 300000 | AE25: 300000 | AF25: 300000 | AG25: 300000 | AH25: 300000 | AI25: 300000 | AJ25: 300000 | AK25: 300000 | AL25: 300000 | AM25: 300000 | AN25: 300000 | AO25: 300000 | AP25: 500000 | AQ25: 500000 | AR25: 500000 | AS25: 500000 | AT25: 500000 | AU25: 500000 | AV25: 500000 | AW25: 500000 | AX25: 500000 | AY25: 500000 | AZ25: 500000 | BA25: 500000 | BB25: 800000 | BC25: 800000 | BD25: 800000 | BE25: 800000 | BF25: 800000 | BG25: 800000 | BH25: 800000 | BI25: 800000 | BJ25: 800000 | BK25: 800000 | BL25: 800000 | BM25: 800000 | BN25: =SUM(F25:Q25) -> 600000 | BO25: =SUM(R25:AC25) -> 1800000 | BP25: =SUM(AD25:AO25) -> 3600000 | BQ25: =SUM(AP25:BA25) -> 6000000 | BR25: =SUM(BB25:BM25) -> 9600000
C26: 決済手数料 | D26: Stripe 3.6%×SaaS売上 | F26: =F5*0.036 -> 0 | G26: =G5*0.036 -> 1543.5413 | H26: =H5*0.036 -> 9230.3767 | I26: =I5*0.036 -> 16763.476 | J26: =J5*0.036 -> 24145.912 | K26: =K5*0.036 -> 32924.242 | L26: =L5*0.036 -> 41527.004 | M26: =M5*0.036 -> 49957.712 | ... BM26: =BM5*0.036 -> 974644.87 | BN26: =SUM(F26:Q26) -> 473581.4 | BO26: =SUM(R26:AC26) -> 1978937.1 | BP26: =SUM(AD26:AO26) -> 4068036.8 | BQ26: =SUM(AP26:BA26) -> 6682678.2 | BR26: =SUM(BB26:BM26) -> 9963405.8
C27: コンサル直接経費 | D27: 交通費・資料等 コンサル売上の5%。推定 | F27: ='事業・組織再生コンサル'!F4*0.05 -> 0 | G27: ='事業・組織再生コンサル'!G4*0.05 -> 0 | H27: ='事業・組織再生コンサル'!H4*0.05 -> 0 | I27: ='事業・組織再生コンサル'!I4*0.05 -> 0 | J27: ='事業・組織再生コンサル'!J4*0.05 -> 0 | K27: ='事業・組織再生コンサル'!K4*0.05 -> 0 | L27: ='事業・組織再生コンサル'!L4*0.05 -> 16500 | M27: ='事業・組織再生コンサル'!M4*0.05 -> 33000 | ... BM27: ='事業・組織再生コンサル'!BM4*0.05 -> 742500 | BN27: =SUM(F27:Q27) -> 313500 | BO27: =SUM(R27:AC27) -> 1897500 | BP27: =SUM(AD27:AO27) -> 3795000 | BQ27: =SUM(AP27:BA27) -> 5758500 | BR27: =SUM(BB27:BM27) -> 7887000
C28: COGS合計 | F28: =SUM(F24:F27) -> 50000 | G28: =SUM(G24:G27) -> 51543.541 | H28: =SUM(H24:H27) -> 59230.377 | I28: =SUM(I24:I27) -> 66763.476 | J28: =SUM(J24:J27) -> 74145.912 | K28: =SUM(K24:K27) -> 82924.242 | L28: =SUM(L24:L27) -> 108027 | M28: =SUM(M24:M27) -> 132957.71 | ... BM28: =SUM(BM24:BM27) -> 2517144.9 | BN28: =SUM(F28:Q28) -> 1387081.4 | BO28: =SUM(R28:AC28) -> 5676437.1 | BP28: =SUM(AD28:AO28) -> 11463037 | BQ28: =SUM(AP28:BA28) -> 18441178 | BR28: =SUM(BB28:BM28) -> 27450406
C33: 役員報酬
C34: 給与手当
C35: 賞与手当
C36: 法定福利費
C37: 福利厚生費
C38: 採用教育費
C39: 広告宣伝費
C40: 荷造包装費
C41: 外注費
C42: 交際費
C43: 会議費
C44: 旅費交通費
... C60: 雑費

Sheet 事業・組織再生コンサル
C3: 指標 | D3: メモ | F3: M1 | G3: M2 | H3: M3 | I3: M4 | J3: M5 | K3: M6 | L3: M7 | M3: M8 | N3: M9 | O3: M10 | P3: M11 | Q3: M12 | R3: M13 | S3: M1４ | T3: M15 | U3: M16 | V3: M17 | W3: M18 | X3: M19 | Y3: M20 | Z3: M21 | AA3: M22 | AB3: M23 | AC3: M24 | AD3: M25 | AE3: M26 | AF3: M27 | AG3: M28 | AH3: M29 | AI3: M30 | AJ3: M31 | AK3: M32 | AL3: M33 | AM3: M34 | AN3: M35 | AO3: M36 | AP3: M37 | AQ3: M38 | AR3: M39 | AS3: M40 | AT3: M41 | AU3: M42 | AV3: M43 | AW3: M44 | AX3: M45 | AY3: M46 | AZ3: M47 | BA3: M48 | BB3: M49 | BC3: M50 | BD3: M51 | BE3: M52 | BF3: M53 | BG3: M54 | BH3: M55 | BI3: M56 | BJ3: M57 | BK3: M58 | BL3: M59 | BM3: M60 | BN3: Y0 | BO3: Y2 | BP3: Y3 | BQ3: Y4 | BR3: Y5
C4: コンサル売上 | F4: =F6*F9 -> 0 | G4: =G6*G9 -> 0 | H4: =H6*H9 -> 0 | I4: =I6*I9 -> 0 | J4: =J6*J9 -> 0 | K4: =K6*K9 -> 0 | L4: =L6*L9 -> 330000 | M4: =M6*M9 -> 660000 | ... BM4: =BM6*BM9 -> 14850000 | BN4: =SUM(F4:Q4) -> 6270000 | BO4: =SUM(R4:AC4) -> 37950000 | BP4: =SUM(AD4:AO4) -> 75900000 | BQ4: =SUM(AP4:BA4) -> 115170000 | BR4: =SUM(BB4:BM4) -> 157740000
C5: 提案獲得LT（ヶ月） | F5: 3 | G5: 3 | H5: 3 | I5: 3 | J5: 3 | K5: 3 | L5: 3 | M5: 3 | N5: 3 | O5: 3 | P5: 3 | Q5: 3 | R5: 3 | S5: 3 | T5: 3 | U5: 3 | V5: 3 | W5: 3 | X5: 3 | Y5: 3 | Z5: 3 | AA5: 3 | AB5: 3 | AC5: 3 | AD5: 3 | AE5: 3 | AF5: 3 | AG5: 3 | AH5: 3 | AI5: 3 | AJ5: 3 | AK5: 3 | AL5: 3 | AM5: 3 | AN5: 3 | AO5: 3 | AP5: 3 | AQ5: 3 | AR5: 3 | AS5: 3 | AT5: 3 | AU5: 3 | AV5: 3 | AW5: 3 | AX5: 3 | AY5: 3 | AZ5: 3 | BA5: 3 | BB5: 3 | BC5: 3 | BD5: 3 | BE5: 3 | BF5: 3 | BG5: 3 | BH5: 3 | BI5: 3 | BJ5: 3 | BK5: 3 | BL5: 3 | BM5: 3 | BN5: 3 | BO5: 3 | BP5: 3 | BQ5: 3 | BR5: 3
C6: コンサル単価 | F6: 330000 | G6: 330000 | H6: 330000 | I6: 330000 | J6: 330000 | K6: 330000 | L6: 330000 | M6: 330000 | N6: 330000 | O6: 330000 | P6: 330000 | Q6: 330000 | R6: 330000 | S6: 330000 | T6: 330000 | U6: 330000 | V6: 330000 | W6: 330000 | X6: 330000 | Y6: 330000 | Z6: 330000 | AA6: 330000 | AB6: 330000 | AC6: 330000 | AD6: 330000 | AE6: 330000 | AF6: 330000 | AG6: 330000 | AH6: 330000 | AI6: 330000 | AJ6: 330000 | AK6: 330000 | AL6: 330000 | AM6: 330000 | AN6: 330000 | AO6: 330000 | AP6: 330000 | AQ6: 330000 | AR6: 330000 | AS6: 330000 | AT6: 330000 | AU6: 330000 | AV6: 330000 | AW6: 330000 | AX6: 330000 | AY6: 330000 | AZ6: 330000 | BA6: 330000 | BB6: 330000 | BC6: 330000 | BD6: 330000 | BE6: 330000 | BF6: 330000 | BG6: 330000 | BH6: 330000 | BI6: 330000 | BJ6: 330000 | BK6: 330000 | BL6: 330000 | BM6: 330000 | BN6: 330000 | BO6: 330000 | BP6: 330000 | BQ6: 330000 | BR6: 330000
C7: 契約コンサル案件 | F7: =E7-F11+F8 -> 0 | G7: =F7-G11+G8 -> 0 | H7: =G7-H11+H8 -> 0 | I7: =H7-I11+I8 -> 0 | J7: =I7-J11+J8 -> 0.1365 | K7: =J7-K11+K8 -> 0.812175 | L7: =K7-L11+L8 -> 1.4540662 | M7: =L7-M11+M8 -> 2.0638629 | ... BM7: =BL7-BM11+BM8 -> 44.94101 | BN7: =Q7 -> 4.8559169 | BO7: =AC7 -> 13.969548 | BP7: =AO7 -> 23.913458 | BQ7: =BA7 -> 34.306018 | BR7: =BM7 -> 44.94101
C8: 新規契約コンサル案件 | F8: =F12*F13 -> 0 | G8: =G12*G13 -> 0 | H8: =H12*H13 -> 0 | I8: =I12*I13 -> 0 | J8: =J12*J13 -> 0.1365 | K8: =K12*K13 -> 0.6825 | L8: =L12*L13 -> 0.6825 | M8: =M12*M13 -> 0.6825 | ... BM8: =BM12*BM13 -> 3.1395 | BN8: =SUM(F8:Q8) -> 5.5965 | BO8: =SUM(R8:AC8) -> 14.469 | BP8: =SUM(AD8:AO8) -> 21.021 | BQ8: =SUM(AP8:BA8) -> 27.573 | BR8: =SUM(BB8:BM8) -> 34.125
C9: 新規契約コンサル案件(本イキ) | F9: 0 | G9: 0 | H9: 0 | I9: 0 | J9: 0 | K9: 0 | L9: 1 | M9: 2 | N9: 3 | O9: 4 | P9: 4 | Q9: 5 | R9: 5 | S9: 6 | T9: 7 | U9: 8 | V9: 8 | W9: 9 | X9: 10 | Y9: 11 | Z9: 12 | AA9: 12 | AB9: 13 | AC9: 14 | AD9: 15 | AE9: 15 | AF9: 16 | AG9: 17 | AH9: 18 | AI9: 19 | AJ9: 20 | AK9: 20 | AL9: 21 | AM9: 22 | AN9: 23 | AO9: 24 | AP9: 24 | AQ9: 25 | AR9: 26 | AS9: 27 | AT9: 28 | AU9: 29 | AV9: 30 | AW9: 30 | AX9: 31 | AY9: 32 | AZ9: 33 | BA9: 34 | BB9: 35 | BC9: 36 | BD9: 37 | BE9: 38 | BF9: 38 | BG9: 39 | BH9: 40 | BI9: 41 | BJ9: 42 | BK9: 43 | BL9: 44 | BM9: 45
C10: 解約率 | D10: 株式会社承知いたしました一年後解約率 | F10: 0.05 | G10: 0.05 | H10: 0.05 | I10: 0.05 | J10: 0.05 | K10: 0.05 | L10: 0.05 | M10: 0.05 | N10: 0.05 | O10: 0.05 | P10: 0.05 | Q10: 0.05 | R10: 0.05 | S10: 0.05 | T10: 0.05 | U10: 0.05 | V10: 0.05 | W10: 0.05 | X10: 0.05 | Y10: 0.05 | Z10: 0.05 | AA10: 0.05 | AB10: 0.05 | AC10: 0.05 | AD10: 0.05 | AE10: 0.05 | AF10: 0.05 | AG10: 0.05 | AH10: 0.05 | AI10: 0.05 | AJ10: 0.05 | AK10: 0.05 | AL10: 0.05 | AM10: 0.05 | AN10: 0.05 | AO10: 0.05 | AP10: 0.05 | AQ10: 0.05 | AR10: 0.05 | AS10: 0.05 | AT10: 0.05 | AU10: 0.05 | AV10: 0.05 | AW10: 0.05 | AX10: 0.05 | AY10: 0.05 | AZ10: 0.05 | BA10: 0.05 | BB10: 0.05 | BC10: 0.05 | BD10: 0.05 | BE10: 0.05 | BF10: 0.05 | BG10: 0.05 | BH10: 0.05 | BI10: 0.05 | BJ10: 0.05 | BK10: 0.05 | BL10: 0.05 | BM10: 0.05 | BN10: =BN11/(BN7+BN8) -> 0.070852811 | BO10: =BO11/(BO7+BO8) -> 0.18831374 | BP10: =BP11/(BP7+BP8) -> 0.2465166 | BQ10: =BQ11/(BQ7+BQ8) -> 0.27764565 | BR10: =BR11/(BR7+BR8) -> 0.29709362
C11: 解約数 | F11: =E7*(F10) -> 0 | G11: =F7*(G10) -> 0 | H11: =G7*(H10) -> 0 | I11: =H7*(I10) -> 0 | J11: =I7*(J10) -> 0 | K11: =J7*(K10) -> 0.006825 | L11: =K7*(L10) -> 0.04060875 | M11: =L7*(M10) -> 0.072703313 | ... BM11: =BL7*(BM10) -> 2.2000795 | BN11: =SUM(F11:Q11) -> 0.74058311 | BO11: =SUM(R11:AC11) -> 5.3553692 | BP11: =SUM(AD11:AO11) -> 11.07709 | BQ11: =SUM(AP11:BA11) -> 17.18044 | BR11: =SUM(BB11:BM11) -> 23.490008
C12: 受注率 | D12: 株式会社承知いたしました受注率２０％ | F12: 0.05 | G12: 0.05 | H12: 0.05 | I12: 0.05 | J12: 0.05 | K12: 0.05 | L12: 0.05 | M12: 0.05 | N12: 0.05 | O12: 0.05 | P12: 0.05 | Q12: 0.05 | R12: 0.05 | S12: 0.05 | T12: 0.05 | U12: 0.05 | V12: 0.05 | W12: 0.05 | X12: 0.05 | Y12: 0.05 | Z12: 0.05 | AA12: 0.05 | AB12: 0.05 | AC12: 0.05 | AD12: 0.05 | AE12: 0.05 | AF12: 0.05 | AG12: 0.05 | AH12: 0.05 | AI12: 0.05 | AJ12: 0.05 | AK12: 0.05 | AL12: 0.05 | AM12: 0.05 | AN12: 0.05 | AO12: 0.05 | AP12: 0.05 | AQ12: 0.05 | AR12: 0.05 | AS12: 0.05 | AT12: 0.05 | AU12: 0.05 | AV12: 0.05 | AW12: 0.05 | AX12: 0.05 | AY12: 0.05 | AZ12: 0.05 | BA12: 0.05 | BB12: 0.05 | BC12: 0.05 | BD12: 0.05 | BE12: 0.05 | BF12: 0.05 | BG12: 0.05 | BH12: 0.05 | BI12: 0.05 | BJ12: 0.05 | BK12: 0.05 | BL12: 0.05 | BM12: 0.05 | BN12: 0.05 | BO12: 0.05 | BP12: 0.05 | BQ12: 0.05 | BR12: 0.05
C13: リード数 | F13: 0 | G13: 0 | H13: 0 | I13: 0 | J13: 2.73 | K13: 13.65 | L13: 13.65 | M13: 13.65 | N13: 16.38 | O13: 16.38 | P13: 16.38 | Q13: 19.11 | R13: 19.11 | S13: 19.11 | T13: 21.84 | U13: 21.84 | V13: 21.84 | W13: 24.57 | X13: 24.57 | Y13: 24.57 | Z13: 27.3 | AA13: 27.3 | AB13: 27.3 | AC13: 30.03 | AD13: 30.03 | AE13: 30.03 | AF13: 32.76 | AG13: 32.76 | AH13: 32.76 | AI13: 35.49 | AJ13: 35.49 | AK13: 35.49 | AL13: 38.22 | AM13: 38.22 | AN13: 38.22 | AO13: 40.95 | AP13: 40.95 | AQ13: 40.95 | AR13: 43.68 | AS13: 43.68 | AT13: 43.68 | AU13: 46.41 | AV13: 46.41 | AW13: 46.41 | AX13: 49.14 | AY13: 49.14 | AZ13: 49.14 | BA13: 51.87 | BB13: 51.87 | BC13: 51.87 | BD13: 54.6 | BE13: 54.6 | BF13: 54.6 | BG13: 57.33 | BH13: 57.33 | BI13: 57.33 | BJ13: 60.06 | BK13: 60.06 | BL13: 60.06 | BM13: 62.79 | BN13: 111.93 | BO13: 289.38 | BP13: 420.42 | BQ13: 551.46 | BR13: 682.5
C14: リード化率 | F14: 0.2 | G14: 0.2 | H14: 0.2 | I14: 0.2 | J14: 0.2 | K14: 0.2 | L14: 0.2 | M14: 0.2 | N14: 0.2 | O14: 0.2 | P14: 0.2 | Q14: 0.2 | R14: 0.2 | S14: 0.2 | T14: 0.2 | U14: 0.2 | V14: 0.2 | W14: 0.2 | X14: 0.2 | Y14: 0.2 | Z14: 0.2 | AA14: 0.2 | AB14: 0.2 | AC14: 0.2 | AD14: 0.2 | AE14: 0.2 | AF14: 0.2 | AG14: 0.2 | AH14: 0.2 | AI14: 0.2 | AJ14: 0.2 | AK14: 0.2 | AL14: 0.2 | AM14: 0.2 | AN14: 0.2 | AO14: 0.2 | AP14: 0.2 | AQ14: 0.2 | AR14: 0.2 | AS14: 0.2 | AT14: 0.2 | AU14: 0.2 | AV14: 0.2 | AW14: 0.2 | AX14: 0.2 | AY14: 0.2 | AZ14: 0.2 | BA14: 0.2 | BB14: 0.2 | BC14: 0.2 | BD14: 0.2 | BE14: 0.2 | BF14: 0.2 | BG14: 0.2 | BH14: 0.2 | BI14: 0.2 | BJ14: 0.2 | BK14: 0.2 | BL14: 0.2 | BM14: 0.2 | BN14: 0.2 | BO14: 0.2 | BP14: 0.2 | BQ14: 0.2 | BR14: 0.2
C15: ポテンシャルリード | F15: {=IFERROR(F17*OFFSET(F27,,F5*-1,,)*F16,0)} -> 0 | G15: {=IFERROR(G17*OFFSET(G27,,G5*-1,,)*G16,0)} -> 0 | H15: {=IFERROR(H17*OFFSET(H27,,H5*-1,,)*H16,0)} -> 0 | I15: {=IFERROR(I17*OFFSET(I27,,I5*-1,,)*I16,0)} -> 0 | J15: {=IFERROR(J17*OFFSET(J27,,J5*-1,,)*J16,0)} -> 13.65 | K15: {=IFERROR(K17*OFFSET(K27,,K5*-1,,)*K16,0)} -> 68.25 | L15: {=IFERROR(L17*OFFSET(L27,,L5*-1,,)*L16,0)} -> 68.25 | M15: {=IFERROR(M17*OFFSET(M27,,M5*-1,,)*M16,0)} -> 68.25 | ... BR15: {=IFERROR(BR17*OFFSET(BR27,,BR5*-1,,)*BR16,0)} -> 1610.7
C16: 黒字会社 | F16: 0.39 | G16: 0.39 | H16: 0.39 | I16: 0.39 | J16: 0.39 | K16: 0.39 | L16: 0.39 | M16: 0.39 | N16: 0.39 | O16: 0.39 | P16: 0.39 | Q16: 0.39 | R16: 0.39 | S16: 0.39 | T16: 0.39 | U16: 0.39 | V16: 0.39 | W16: 0.39 | X16: 0.39 | Y16: 0.39 | Z16: 0.39 | AA16: 0.39 | AB16: 0.39 | AC16: 0.39 | AD16: 0.39 | AE16: 0.39 | AF16: 0.39 | AG16: 0.39 | AH16: 0.39 | AI16: 0.39 | AJ16: 0.39 | AK16: 0.39 | AL16: 0.39 | AM16: 0.39 | AN16: 0.39 | AO16: 0.39 | AP16: 0.39 | AQ16: 0.39 | AR16: 0.39 | AS16: 0.39 | AT16: 0.39 | AU16: 0.39 | AV16: 0.39 | AW16: 0.39 | AX16: 0.39 | AY16: 0.39 | AZ16: 0.39 | BA16: 0.39 | BB16: 0.39 | BC16: 0.39 | BD16: 0.39 | BE16: 0.39 | BF16: 0.39 | BG16: 0.39 | BH16: 0.39 | BI16: 0.39 | BJ16: 0.39 | BK16: 0.39 | BL16: 0.39 | BM16: 0.39 | BN16: 0.39 | BO16: 0.39 | BP16: 0.39 | BQ16: 0.39 | BR16: 0.39
C17: 1税理士あたりの担当法人 | D17: 日税連 第6回税理士実態調査 | F17: 35 | G17: 35 | H17: 35 | I17: 35 | J17: 35 | K17: 35 | L17: 35 | M17: 35 | N17: 35 | O17: 35 | P17: 35 | Q17: 35 | R17: 35 | S17: 35 | T17: 35 | U17: 35 | V17: 35 | W17: 35 | X17: 35 | Y17: 35 | Z17: 35 | AA17: 35 | AB17: 35 | AC17: 35 | AD17: 35 | AE17: 35 | AF17: 35 | AG17: 35 | AH17: 35 | AI17: 35 | AJ17: 35 | AK17: 35 | AL17: 35 | AM17: 35 | AN17: 35 | AO17: 35 | AP17: 35 | AQ17: 35 | AR17: 35 | AS17: 35 | AT17: 35 | AU17: 35 | AV17: 35 | AW17: 35 | AX17: 35 | AY17: 35 | AZ17: 35 | BA17: 35 | BB17: 35 | BC17: 35 | BD17: 35 | BE17: 35 | BF17: 35 | BG17: 35 | BH17: 35 | BI17: 35 | BJ17: 35 | BK17: 35 | BL17: 35 | BM17: 35 | BN17: 35 | BO17: 35 | BP17: 35 | BQ17: 35 | BR17: 35
C18: 新規 | F18: 0 | G18: 1 | H18: 5 | I18: 5 | J18: 5 | K18: =H18+1 -> 6 | L18: =I18+1 -> 6 | M18: =J18+1 -> 6 | N18: =K18+1 -> 7 | O18: =L18+1 -> 7 | P18: =M18+1 -> 7 | Q18: =N18+1 -> 8 | R18: =O18+1 -> 8 | ... BM18: =BJ18+1 -> 24 | BN18: =SUM(F18:Q18) -> 63 | BO18: =SUM(R18:AC18) -> 118 | BP18: =SUM(AD18:AO18) -> 166 | BQ18: =SUM(AP18:BA18) -> 214 | BR18: =SUM(BB18:BM18) -> 262
C27: 新規 | F27: 0 | G27: 1 | H27: 5 | I27: 5 | J27: 5 | K27: =H27+1 -> 6 | L27: =I27+1 -> 6 | M27: =J27+1 -> 6 | N27: =K27+1 -> 7 | O27: =L27+1 -> 7 | P27: =M27+1 -> 7 | Q27: =N27+1 -> 8 | R27: =O27+1 -> 8 | ... BM27: =BJ27+1 -> 24 | BN27: =SUM(F27:Q27) -> 63 | BO27: =SUM(R27:AC27) -> 118 | BP27: =SUM(AD27:AO27) -> 166 | BQ27: =SUM(AP27:BA27) -> 214 | BR27: =SUM(BB27:BM27) -> 262

Sheet ビジとり
C4: ■ ① ビジとり（旅費規程） | F4: Y1_M1 | G4: Y1_M2 | H4: Y1_M3 | I4: Y1_M4 | J4: Y1_M5 | K4: Y1_M6 | L4: Y1_M7 | M4: Y1_M8 | N4: Y1_M9 | O4: Y1_M10 | P4: Y1_M11 | Q4: Y1_M12 | R4: Y2_M1 | S4: Y2_M2 | T4: Y2_M3 | U4: Y2_M4 | V4: Y2_M5 | W4: Y2_M6 | X4: Y2_M7 | Y4: Y2_M8 | Z4: Y2_M9 | AA4: Y2_M10 | AB4: Y2_M11 | AC4: Y2_M12 | AD4: Y3_M1 | AE4: Y3_M2 | AF4: Y3_M3 | AG4: Y3_M4 | AH4: Y3_M5 | AI4: Y3_M6 | AJ4: Y3_M7 | AK4: Y3_M8 | AL4: Y3_M9 | AM4: Y3_M10 | AN4: Y3_M11 | AO4: Y3_M12 | AP4: Y4_M1 | AQ4: Y4_M2 | AR4: Y4_M3 | AS4: Y4_M4 | AT4: Y4_M5 | AU4: Y4_M6 | AV4: Y4_M7 | AW4: Y4_M8 | AX4: Y4_M9 | AY4: Y4_M10 | AZ4: Y4_M11 | BA4: Y4_M12 | BB4: Y5_M1 | BC4: Y5_M2 | BD4: Y5_M3 | BE4: Y5_M4 | BF4: Y5_M5 | BG4: Y5_M6 | BH4: Y5_M7 | BI4: Y5_M8 | BJ4: Y5_M9 | BK4: Y5_M10 | BL4: Y5_M11 | BM4: Y5_M12 | BN4: Y1 | BO4: Y2 | BP4: Y3 | BQ4: Y4 | BR4: Y5
C5: 売上 | F5: =F25*F14 -> 0 | G5: =G25*G14 -> 1929.375 | H5: =H25*H14 -> 10572.975 | I5: =I25*I14 -> 19043.703 | J5: =J25*J14 -> 26380.329 | K5: =K25*K14 -> 35499.597 | L5: =L25*L14 -> 44436.48 | M5: =M25*M14 -> 53194.626 | ... BM5: =BM25*BM14 -> 778105.88 | BN5: =SUM(F5:Q5) -> 503095.67 | BO5: =SUM(R5:AC5) -> 1927248.6 | BP5: =SUM(AD5:AO5) -> 3683882 | BQ5: =SUM(AP5:BA5) -> 5663952.8 | BR5: =SUM(BB5:BM5) -> 8073839.8
A6: KPI | C6: 顧問先 | F6: =35*F17 -> 0 | G6: =35*G17 -> 70 | H6: =35*H17 -> 385 | I6: =35*I17 -> 700 | J6: =35*J17 -> 980 | K6: =35*K17 -> 1330 | L6: =35*L17 -> 1680 | M6: =35*M17 -> 2030 | ... BR6: =35*BR17 -> 39830
C7: 役員報酬250万円以上割合 | F7: 0.75 | G7: 0.75 | H7: 0.75 | I7: 0.75 | J7: 0.75 | K7: 0.75 | L7: 0.75 | M7: 0.75 | N7: 0.75 | O7: 0.75 | P7: 0.75 | Q7: 0.75 | R7: 0.75 | S7: 0.75 | T7: 0.75 | U7: 0.75 | V7: 0.75 | W7: 0.75 | X7: 0.75 | Y7: 0.75 | Z7: 0.75 | AA7: 0.75 | AB7: 0.75 | AC7: 0.75 | AD7: 0.75 | AE7: 0.75 | AF7: 0.75 | AG7: 0.75 | AH7: 0.75 | AI7: 0.75 | AJ7: 0.75 | AK7: 0.75 | AL7: 0.75 | AM7: 0.75 | AN7: 0.75 | AO7: 0.75 | AP7: 0.75 | AQ7: 0.75 | AR7: 0.75 | AS7: 0.75 | AT7: 0.75 | AU7: 0.75 | AV7: 0.75 | AW7: 0.75 | AX7: 0.75 | AY7: 0.75 | AZ7: 0.75 | BA7: 0.75 | BB7: 0.75 | BC7: 0.75 | BD7: 0.75 | BE7: 0.75 | BF7: 0.75 | BG7: 0.75 | BH7: 0.75 | BI7: 0.75 | BJ7: 0.75 | BK7: 0.75 | BL7: 0.75 | BM7: 0.75 | BN7: 0.75 | BO7: 0.75 | BP7: 0.75 | BQ7: 0.75 | BR7: 0.75
C8: 出張・営業活動がある割アリ | F8: 0.7 | G8: 0.7 | H8: 0.7 | I8: 0.7 | J8: 0.7 | K8: 0.7 | L8: 0.7 | M8: 0.7 | N8: 0.7 | O8: 0.7 | P8: 0.7 | Q8: 0.7 | R8: 0.7 | S8: 0.7 | T8: 0.7 | U8: 0.7 | V8: 0.7 | W8: 0.7 | X8: 0.7 | Y8: 0.7 | Z8: 0.7 | AA8: 0.7 | AB8: 0.7 | AC8: 0.7 | AD8: 0.7 | AE8: 0.7 | AF8: 0.7 | AG8: 0.7 | AH8: 0.7 | AI8: 0.7 | AJ8: 0.7 | AK8: 0.7 | AL8: 0.7 | AM8: 0.7 | AN8: 0.7 | AO8: 0.7 | AP8: 0.7 | AQ8: 0.7 | AR8: 0.7 | AS8: 0.7 | AT8: 0.7 | AU8: 0.7 | AV8: 0.7 | AW8: 0.7 | AX8: 0.7 | AY8: 0.7 | AZ8: 0.7 | BA8: 0.7 | BB8: 0.7 | BC8: 0.7 | BD8: 0.7 | BE8: 0.7 | BF8: 0.7 | BG8: 0.7 | BH8: 0.7 | BI8: 0.7 | BJ8: 0.7 | BK8: 0.7 | BL8: 0.7 | BM8: 0.7 | BN8: 0.7 | BO8: 0.7 | BP8: 0.7 | BQ8: 0.7 | BR8: 0.7
C9: 旅費規程が未整備 | F9: 0.7 | G9: 0.7 | H9: 0.7 | I9: 0.7 | J9: 0.7 | K9: 0.7 | L9: 0.7 | M9: 0.7 | N9: 0.7 | O9: 0.7 | P9: 0.7 | Q9: 0.7 | R9: 0.7 | S9: 0.7 | T9: 0.7 | U9: 0.7 | V9: 0.7 | W9: 0.7 | X9: 0.7 | Y9: 0.7 | Z9: 0.7 | AA9: 0.7 | AB9: 0.7 | AC9: 0.7 | AD9: 0.7 | AE9: 0.7 | AF9: 0.7 | AG9: 0.7 | AH9: 0.7 | AI9: 0.7 | AJ9: 0.7 | AK9: 0.7 | AL9: 0.7 | AM9: 0.7 | AN9: 0.7 | AO9: 0.7 | AP9: 0.7 | AQ9: 0.7 | AR9: 0.7 | AS9: 0.7 | AT9: 0.7 | AU9: 0.7 | AV9: 0.7 | AW9: 0.7 | AX9: 0.7 | AY9: 0.7 | AZ9: 0.7 | BA9: 0.7 | BB9: 0.7 | BC9: 0.7 | BD9: 0.7 | BE9: 0.7 | BF9: 0.7 | BG9: 0.7 | BH9: 0.7 | BI9: 0.7 | BJ9: 0.7 | BK9: 0.7 | BL9: 0.7 | BM9: 0.7 | BN9: 0.7 | BO9: 0.7 | BP9: 0.7 | BQ9: 0.7 | BR9: 0.7
C10: 税理士 ➡ 企業提案 | F10: 0.6 | G10: 0.6 | H10: 0.6 | I10: 0.6 | J10: 0.6 | K10: 0.6 | L10: 0.6 | M10: 0.6 | N10: 0.6 | O10: 0.6 | P10: 0.6 | Q10: 0.6 | R10: 0.6 | S10: 0.6 | T10: 0.6 | U10: 0.6 | V10: 0.6 | W10: 0.6 | X10: 0.6 | Y10: 0.6 | Z10: 0.6 | AA10: 0.6 | AB10: 0.6 | AC10: 0.6 | AD10: 0.6 | AE10: 0.6 | AF10: 0.6 | AG10: 0.6 | AH10: 0.6 | AI10: 0.6 | AJ10: 0.6 | AK10: 0.6 | AL10: 0.6 | AM10: 0.6 | AN10: 0.6 | AO10: 0.6 | AP10: 0.6 | AQ10: 0.6 | AR10: 0.6 | AS10: 0.6 | AT10: 0.6 | AU10: 0.6 | AV10: 0.6 | AW10: 0.6 | AX10: 0.6 | AY10: 0.6 | AZ10: 0.6 | BA10: 0.6 | BB10: 0.6 | BC10: 0.6 | BD10: 0.6 | BE10: 0.6 | BF10: 0.6 | BG10: 0.6 | BH10: 0.6 | BI10: 0.6 | BJ10: 0.6 | BK10: 0.6 | BL10: 0.6 | BM10: 0.6 | BN10: 0.6 | BO10: 0.6 | BP10: 0.6 | BQ10: 0.6 | BR10: 0.6
A11: KPI | C11: 受注率 | F11: 0.25 | G11: 0.25 | H11: 0.25 | I11: 0.25 | J11: 0.25 | K11: 0.25 | L11: 0.25 | M11: 0.25 | N11: 0.25 | O11: 0.25 | P11: 0.25 | Q11: 0.25 | R11: 0.25 | S11: 0.25 | T11: 0.25 | U11: 0.25 | V11: 0.25 | W11: 0.25 | X11: 0.25 | Y11: 0.25 | Z11: 0.25 | AA11: 0.25 | AB11: 0.25 | AC11: 0.25 | AD11: 0.25 | AE11: 0.25 | AF11: 0.25 | AG11: 0.25 | AH11: 0.25 | AI11: 0.25 | AJ11: 0.25 | AK11: 0.25 | AL11: 0.25 | AM11: 0.25 | AN11: 0.25 | AO11: 0.25 | AP11: 0.25 | AQ11: 0.25 | AR11: 0.25 | AS11: 0.25 | AT11: 0.25 | AU11: 0.25 | AV11: 0.25 | AW11: 0.25 | AX11: 0.25 | AY11: 0.25 | AZ11: 0.25 | BA11: 0.25 | BB11: 0.25 | BC11: 0.25 | BD11: 0.25 | BE11: 0.25 | BF11: 0.25 | BG11: 0.25 | BH11: 0.25 | BI11: 0.25 | BJ11: 0.25 | BK11: 0.25 | BL11: 0.25 | BM11: 0.25 | BN11: 0.25 | BO11: 0.25 | BP11: 0.25 | BQ11: 0.25 | BR11: 0.25
A12: KPI | C12: １税理士 / 受注数（累計獲得数・解約前） | F12: =PRODUCT(F6:F11) -> 0 | G12: =PRODUCT(G6:G11) -> 3.85875 | H12: =PRODUCT(H6:H11) -> 21.223125 | I12: =PRODUCT(I6:I11) -> 38.5875 | J12: =PRODUCT(J6:J11) -> 54.0225 | K12: =PRODUCT(K6:K11) -> 73.31625 | L12: =PRODUCT(L6:L11) -> 92.61 | M12: =PRODUCT(M6:M11) -> 111.90375 | ... BR12: =PRODUCT(BR6:BR11) -> 2195.6287
C13: ビジとり 税理士（月/社） | F13: 2500 | G13: 2500 | H13: 2500 | I13: 2500 | J13: 2500 | K13: 2500 | L13: 2500 | M13: 2500 | N13: 2500 | O13: 2500 | P13: 2500 | Q13: 2500 | R13: 2500 | S13: 2500 | T13: 2500 | U13: 2500 | V13: 2500 | W13: 2500 | X13: 2500 | Y13: 2500 | Z13: 2500 | AA13: 2500 | AB13: 2500 | AC13: 2500 | AD13: 2500 | AE13: 2500 | AF13: 2500 | AG13: 2500 | AH13: 2500 | AI13: 2500 | AJ13: 2500 | AK13: 2500 | AL13: 2500 | AM13: 2500 | AN13: 2500 | AO13: 2500 | AP13: 2500 | AQ13: 2500 | AR13: 2500 | AS13: 2500 | AT13: 2500 | AU13: 2500 | AV13: 2500 | AW13: 2500 | AX13: 2500 | AY13: 2500 | AZ13: 2500 | BA13: 2500 | BB13: 2500 | BC13: 2500 | BD13: 2500 | BE13: 2500 | BF13: 2500 | BG13: 2500 | BH13: 2500 | BI13: 2500 | BJ13: 2500 | BK13: 2500 | BL13: 2500 | BM13: 2500 | BN13: 2500 | BO13: 2500 | BP13: 2500 | BQ13: 2500 | BR13: 2500
C14: ビジとり Taxel（月/社） | F14: 500 | G14: 500 | H14: 500 | I14: 500 | J14: 500 | K14: 500 | L14: 500 | M14: 500 | N14: 500 | O14: 500 | P14: 500 | Q14: 500 | R14: 500 | S14: 500 | T14: 500 | U14: 500 | V14: 500 | W14: 500 | X14: 500 | Y14: 500 | Z14: 500 | AA14: 500 | AB14: 500 | AC14: 500 | AD14: 500 | AE14: 500 | AF14: 500 | AG14: 500 | AH14: 500 | AI14: 500 | AJ14: 500 | AK14: 500 | AL14: 500 | AM14: 500 | AN14: 500 | AO14: 500 | AP14: 500 | AQ14: 500 | AR14: 500 | AS14: 500 | AT14: 500 | AU14: 500 | AV14: 500 | AW14: 500 | AX14: 500 | AY14: 500 | AZ14: 500 | BA14: 500 | BB14: 500 | BC14: 500 | BD14: 500 | BE14: 500 | BF14: 500 | BG14: 500 | BH14: 500 | BI14: 500 | BJ14: 500 | BK14: 500 | BL14: 500 | BM14: 500 | BN14: 500 | BO14: 500 | BP14: 500 | BQ14: 500 | BR14: 500
C15: ビジとり 定常浸透率（対象社数に対して） | F15: 0.7 | G15: 0.7 | H15: 0.7 | I15: 0.7 | J15: 0.7 | K15: 0.7 | L15: 0.7 | M15: 0.7 | N15: 0.7 | O15: 0.7 | P15: 0.7 | Q15: 0.7 | R15: 0.7 | S15: 0.7 | T15: 0.7 | U15: 0.7 | V15: 0.7 | W15: 0.7 | X15: 0.7 | Y15: 0.7 | Z15: 0.7 | AA15: 0.7 | AB15: 0.7 | AC15: 0.7 | AD15: 0.7 | AE15: 0.7 | AF15: 0.7 | AG15: 0.7 | AH15: 0.7 | AI15: 0.7 | AJ15: 0.7 | AK15: 0.7 | AL15: 0.7 | AM15: 0.7 | AN15: 0.7 | AO15: 0.7 | AP15: 0.7 | AQ15: 0.7 | AR15: 0.7 | AS15: 0.7 | AT15: 0.7 | AU15: 0.7 | AV15: 0.7 | AW15: 0.7 | AX15: 0.7 | AY15: 0.7 | AZ15: 0.7 | BA15: 0.7 | BB15: 0.7 | BC15: 0.7 | BD15: 0.7 | BE15: 0.7 | BF15: 0.7 | BG15: 0.7 | BH15: 0.7 | BI15: 0.7 | BJ15: 0.7 | BK15: 0.7 | BL15: 0.7 | BM15: 0.7 | BN15: 0.7 | BO15: 0.7 | BP15: 0.7 | BQ15: 0.7 | BR15: 0.7
C16: １税理士 / 紹介費用 | F16: =F13*F25 -> 0 | G16: =G13*G25 -> 9646.875 | H16: =H13*H25 -> 52864.875 | I16: =I13*I25 -> 95218.515 | J16: =J13*J25 -> 131901.64 | K16: =K13*K25 -> 177497.99 | L16: =L13*L25 -> 222182.4 | M16: =M13*M25 -> 265973.13 | ... BM16: =BM13*BM25 -> 3890529.4 | BN16: =SUM(F16:Q16) -> 2515478.4 | BO16: =SUM(R16:AC16) -> 9636243 | BP16: =SUM(AD16:AO16) -> 18419410 | BQ16: =SUM(AP16:BA16) -> 28319764 | BR16: =SUM(BB16:BM16) -> 40369199
C17: 税理士数＝アカウト数 | F17: 0 | G17: 2 | H17: 11 | I17: 20 | J17: 28 | K17: 38 | L17: 48 | M17: 58 | N17: 70 | O17: 81 | P17: 92 | Q17: 105 | R17: 117 | S17: 129 | T17: 143 | U17: 156 | V17: 169 | W17: 184 | X17: 198 | Y17: 212 | Z17: 228 | AA17: 243 | AB17: 258 | AC17: 274 | AD17: 292 | AE17: 309 | AF17: 328 | AG17: 346 | AH17: 365 | AI17: 384 | AJ17: 404 | AK17: 423 | AL17: 444 | AM17: 464 | AN17: 484 | AO17: 506 | AP17: 527 | AQ17: 548 | AR17: 570 | AS17: 592 | AT17: 614 | AU17: 637 | AV17: 660 | AW17: 683 | AX17: 707 | AY17: 730 | AZ17: 754 | BA17: 778 | BB17: 807 | BC17: 835 | BD17: 864 | BE17: 893 | BF17: 922 | BG17: 953 | BH17: 983 | BI17: 1013 | BJ17: 1044 | BK17: 1075 | BL17: 1106 | BM17: 1138 | BN17: =Q17 -> 105 | BO17: =AC17 -> 274 | BP17: =AO17 -> 506 | BQ17: =BA17 -> 778 | BR17: =BM17 -> 1138
A18: KPI | C18: 新規 | F18: 0 | G18: 4 | H18: =PRODUCT(H6:H11)-G18 -> 17.223125 | I18: 5 | J18: 5 | K18: =H18+1 -> 18.223125 | L18: =I18+1 -> 6 | M18: =J18+1 -> 6 | N18: =K18+1 -> 19.223125 | O18: =L18+1 -> 7 | P18: =M18+1 -> 7 | Q18: =N18+1 -> 20.223125 | R18: =O18+1 -> 8 | ... BM18: =BJ18+1 -> 36.223125 | BN18: =SUM(F18:Q18) -> 114.8925 | BO18: =SUM(R18:AC18) -> 166.8925 | BP18: =SUM(AD18:AO18) -> 214.8925 | BQ18: =SUM(AP18:BA18) -> 262.8925 | BR18: =SUM(BB18:BM18) -> 310.8925
C19: 解約予想数 | F19: 0 | G19: =F25*G20 -> 0 | H19: =G25*H20 -> 0.077175 | I19: =H25*I20 -> 0.422919 | J19: =I25*J20 -> 0.76174812 | K19: =J25*K20 -> 1.0552132 | L19: =K25*L20 -> 1.4199839 | M19: =L25*M20 -> 1.7774592 | N19: =M25*N20 -> 2.127785 | ... BM19: =BL25*BM20 -> 22.758453 | BN19: =SUM(F19:Q19) -> 16.400142 | BO19: =SUM(R19:AC19) -> 72.008833 | BP19: =SUM(AD19:AO19) -> 123.25965 | BQ19: =SUM(AP19:BA19) -> 192.42191 | BR19: =SUM(BB19:BM19) -> 235.32647
C20: 解約率 | D20: F&M オフィスステーション1.01% | F20: 0.02 | G20: 0.02 | H20: 0.02 | I20: 0.02 | J20: 0.02 | K20: 0.02 | L20: 0.02 | M20: 0.02 | N20: 0.02 | O20: 0.02 | P20: 0.02 | Q20: 0.02 | R20: 0.02 | S20: 0.02 | T20: 0.02 | U20: 0.02 | V20: 0.02 | W20: 0.02 | X20: 0.02 | Y20: 0.02 | Z20: 0.02 | AA20: 0.02 | AB20: 0.02 | AC20: 0.02 | AD20: 0.0175 | AE20: 0.0175 | AF20: 0.0175 | AG20: 0.0175 | AH20: 0.0175 | AI20: 0.0175 | AJ20: 0.0175 | AK20: 0.0175 | AL20: 0.0175 | AM20: 0.0175 | AN20: 0.0175 | AO20: 0.0175 | AP20: 0.0175 | AQ20: 0.0175 | AR20: 0.0175 | AS20: 0.0175 | AT20: 0.0175 | AU20: 0.0175 | AV20: 0.0175 | AW20: 0.0175 | AX20: 0.0175 | AY20: 0.0175 | AZ20: 0.0175 | BA20: 0.0175 | BB20: 0.015 | BC20: 0.015 | BD20: 0.015 | BE20: 0.015 | BF20: 0.015 | BG20: 0.015 | BH20: 0.015 | BI20: 0.015 | BJ20: 0.015 | BK20: 0.015 | BL20: 0.015 | BM20: 0.015 | BN20: =AVERAGE(F20:Q20) -> 0.02 | BO20: =AVERAGE(R20:AC20) -> 0.02 | BP20: =AVERAGE(AD20:AO20) -> 0.0175 | BQ20: =AVERAGE(AP20:BA20) -> 0.0175 | BR20: =AVERAGE(BB20:BM20) -> 0.015
C23: ■ ストック計算（契約社数＝前月契約社数＋当月新規受注－当月解約）
C24: 新規受注数（当月） | D24: ＝当月の累計獲得数(12行)－前月の累計獲得数。税理士獲得ロジック(×35等)は別途検討中のため、既存ファネルを流用 | F24: =F12 -> 0 | G24: =G12-F12 -> 3.85875 | H24: =H12-G12 -> 17.364375 | I24: =I12-H12 -> 17.364375 | J24: =J12-I12 -> 15.435 | K24: =K12-J12 -> 19.29375 | L24: =L12-K12 -> 19.29375 | M24: =M12-L12 -> 19.29375 | N24: =N12-M12 -> 23.1525 | ... BM24: =BM12-BL12 -> 61.74 | BN24: =SUM(F24:Q24) -> 202.58437 | BO24: =SUM(R24:AC24) -> 326.06437 | BP24: =SUM(AD24:AO24) -> 447.615 | BQ24: =SUM(AP24:BA24) -> 524.79 | BR24: =SUM(BB24:BM24) -> 694.575
C25: 期末契約社数（ストック） | D25: ＝前月末契約社数＋新規受注数－解約予想数。売上＝本行×単価 | F25: =F24-F19 -> 0 | G25: =F25+G24-G19 -> 3.85875 | H25: =G25+H24-H19 -> 21.14595 | I25: =H25+I24-I19 -> 38.087406 | J25: =I25+J24-J19 -> 52.760658 | K25: =J25+K24-K19 -> 70.999195 | L25: =K25+L24-L19 -> 88.872961 | M25: =L25+M24-M19 -> 106.38925 | N25: =M25+N24-N19 -> 127.41397 | ... BM25: =BL25+BM24-BM19 -> 1556.2118 | BN25: =Q25 -> 186.18423 | BO25: =AC25 -> 440.23977 | BP25: =AO25 -> 764.59512 | BQ25: =BA25 -> 1096.9632 | BR25: =BM25 -> 1556.2118

Sheet 支払い.com
C4: ■ 支払い.com ➡ 請求書クレカ払い | F4: Y1_M1 | G4: Y1_M2 | H4: Y1_M3 | I4: Y1_M4 | J4: Y1_M5 | K4: Y1_M6 | L4: Y1_M7 | M4: Y1_M8 | N4: Y1_M9 | O4: Y1_M10 | P4: Y1_M11 | Q4: Y1_M12 | R4: Y2_M1 | S4: Y2_M2 | T4: Y2_M3 | U4: Y2_M4 | V4: Y2_M5 | W4: Y2_M6 | X4: Y2_M7 | Y4: Y2_M8 | Z4: Y2_M9 | AA4: Y2_M10 | AB4: Y2_M11 | AC4: Y2_M12 | AD4: Y3_M1 | AE4: Y3_M2 | AF4: Y3_M3 | AG4: Y3_M4 | AH4: Y3_M5 | AI4: Y3_M6 | AJ4: Y3_M7 | AK4: Y3_M8 | AL4: Y3_M9 | AM4: Y3_M10 | AN4: Y3_M11 | AO4: Y3_M12 | AP4: Y4_M1 | AQ4: Y4_M2 | AR4: Y4_M3 | AS4: Y4_M4 | AT4: Y4_M5 | AU4: Y4_M6 | AV4: Y4_M7 | AW4: Y4_M8 | AX4: Y4_M9 | AY4: Y4_M10 | AZ4: Y4_M11 | BA4: Y4_M12 | BB4: Y5_M1 | BC4: Y5_M2 | BD4: Y5_M3 | BE4: Y5_M4 | BF4: Y5_M5 | BG4: Y5_M6 | BH4: Y5_M7 | BI4: Y5_M8 | BJ4: Y5_M9 | BK4: Y5_M10 | BL4: Y5_M11 | BM4: Y5_M12 | BN4: Y1 | BO4: Y2 | BP4: Y3 | BQ4: Y4 | BR4: Y5
C5: 売上 | F5: =F12*F13 -> 0 | G5: =G12*G13 -> 3748.5 | H5: =H12*H13 -> 20616.75 | I5: =I12*I13 -> 37485 | J5: =J12*J13 -> 52479 | K5: =K12*K13 -> 71221.5 | L5: =L12*L13 -> 89964 | M5: =M12*M13 -> 108706.5 | ... BM5: =BM12*BM13 -> 2132896.5 | BN5: =SUM(F5:Q5) -> 1036460.2 | BO5: =SUM(R5:AC5) -> 4331391.8 | BP5: =SUM(AD5:AO5) -> 8900813.2 | BQ5: =SUM(AP5:BA5) -> 14619150 | BR5: =SUM(BB5:BM5) -> 21803150
C6: 顧問先 | F6: =35*F17 -> 0 | G6: =35*G17 -> 70 | H6: =35*H17 -> 385 | I6: =35*I17 -> 700 | J6: =35*J17 -> 980 | K6: =35*K17 -> 1330 | L6: =35*L17 -> 1680 | M6: =35*M17 -> 2030 | ... BR6: =35*BR17 -> 39830
C7: 年商3,000万円以上 | F7: 0.85 | G7: 0.85 | H7: 0.85 | I7: 0.85 | J7: 0.85 | K7: 0.85 | L7: 0.85 | M7: 0.85 | N7: 0.85 | O7: 0.85 | P7: 0.85 | Q7: 0.85 | R7: 0.85 | S7: 0.85 | T7: 0.85 | U7: 0.85 | V7: 0.85 | W7: 0.85 | X7: 0.85 | Y7: 0.85 | Z7: 0.85 | AA7: 0.85 | AB7: 0.85 | AC7: 0.85 | AD7: 0.85 | AE7: 0.85 | AF7: 0.85 | AG7: 0.85 | AH7: 0.85 | AI7: 0.85 | AJ7: 0.85 | AK7: 0.85 | AL7: 0.85 | AM7: 0.85 | AN7: 0.85 | AO7: 0.85 | AP7: 0.85 | AQ7: 0.85 | AR7: 0.85 | AS7: 0.85 | AT7: 0.85 | AU7: 0.85 | AV7: 0.85 | AW7: 0.85 | AX7: 0.85 | AY7: 0.85 | AZ7: 0.85 | BA7: 0.85 | BB7: 0.85 | BC7: 0.85 | BD7: 0.85 | BE7: 0.85 | BF7: 0.85 | BG7: 0.85 | BH7: 0.85 | BI7: 0.85 | BJ7: 0.85 | BK7: 0.85 | BL7: 0.85 | BM7: 0.85 | BN7: 0.85 | BO7: 0.85 | BP7: 0.85 | BQ7: 0.85 | BR7: 0.85
C8: 資金繰りが逼迫 | D8: ゾンビ率14.3%/赤字法人率61% | F8: 0.25 | G8: 0.25 | H8: 0.25 | I8: 0.25 | J8: 0.25 | K8: 0.25 | L8: 0.25 | M8: 0.25 | N8: 0.25 | O8: 0.25 | P8: 0.25 | Q8: 0.25 | R8: 0.25 | S8: 0.25 | T8: 0.25 | U8: 0.25 | V8: 0.25 | W8: 0.25 | X8: 0.25 | Y8: 0.25 | Z8: 0.25 | AA8: 0.25 | AB8: 0.25 | AC8: 0.25 | AD8: 0.25 | AE8: 0.25 | AF8: 0.25 | AG8: 0.25 | AH8: 0.25 | AI8: 0.25 | AJ8: 0.25 | AK8: 0.25 | AL8: 0.25 | AM8: 0.25 | AN8: 0.25 | AO8: 0.25 | AP8: 0.25 | AQ8: 0.25 | AR8: 0.25 | AS8: 0.25 | AT8: 0.25 | AU8: 0.25 | AV8: 0.25 | AW8: 0.25 | AX8: 0.25 | AY8: 0.25 | AZ8: 0.25 | BA8: 0.25 | BB8: 0.25 | BC8: 0.25 | BD8: 0.25 | BE8: 0.25 | BF8: 0.25 | BG8: 0.25 | BH8: 0.25 | BI8: 0.25 | BJ8: 0.25 | BK8: 0.25 | BL8: 0.25 | BM8: 0.25 | BN8: 0.25 | BO8: 0.25 | BP8: 0.25 | BQ8: 0.25 | BR8: 0.25
C9: カード与信を通過 | F9: 0.7 | G9: 0.7 | H9: 0.7 | I9: 0.7 | J9: 0.7 | K9: 0.7 | L9: 0.7 | M9: 0.7 | N9: 0.7 | O9: 0.7 | P9: 0.7 | Q9: 0.7 | R9: 0.7 | S9: 0.7 | T9: 0.7 | U9: 0.7 | V9: 0.7 | W9: 0.7 | X9: 0.7 | Y9: 0.7 | Z9: 0.7 | AA9: 0.7 | AB9: 0.7 | AC9: 0.7 | AD9: 0.7 | AE9: 0.7 | AF9: 0.7 | AG9: 0.7 | AH9: 0.7 | AI9: 0.7 | AJ9: 0.7 | AK9: 0.7 | AL9: 0.7 | AM9: 0.7 | AN9: 0.7 | AO9: 0.7 | AP9: 0.7 | AQ9: 0.7 | AR9: 0.7 | AS9: 0.7 | AT9: 0.7 | AU9: 0.7 | AV9: 0.7 | AW9: 0.7 | AX9: 0.7 | AY9: 0.7 | AZ9: 0.7 | BA9: 0.7 | BB9: 0.7 | BC9: 0.7 | BD9: 0.7 | BE9: 0.7 | BF9: 0.7 | BG9: 0.7 | BH9: 0.7 | BI9: 0.7 | BJ9: 0.7 | BK9: 0.7 | BL9: 0.7 | BM9: 0.7 | BN9: 0.7 | BO9: 0.7 | BP9: 0.7 | BQ9: 0.7 | BR9: 0.7
C10: 税理士 ➡ 企業提案 | F10: 0.4 | G10: 0.4 | H10: 0.4 | I10: 0.4 | J10: 0.4 | K10: 0.4 | L10: 0.4 | M10: 0.4 | N10: 0.4 | O10: 0.4 | P10: 0.4 | Q10: 0.4 | R10: 0.4 | S10: 0.4 | T10: 0.4 | U10: 0.4 | V10: 0.4 | W10: 0.4 | X10: 0.4 | Y10: 0.4 | Z10: 0.4 | AA10: 0.4 | AB10: 0.4 | AC10: 0.4 | AD10: 0.4 | AE10: 0.4 | AF10: 0.4 | AG10: 0.4 | AH10: 0.4 | AI10: 0.4 | AJ10: 0.4 | AK10: 0.4 | AL10: 0.4 | AM10: 0.4 | AN10: 0.4 | AO10: 0.4 | AP10: 0.4 | AQ10: 0.4 | AR10: 0.4 | AS10: 0.4 | AT10: 0.4 | AU10: 0.4 | AV10: 0.4 | AW10: 0.4 | AX10: 0.4 | AY10: 0.4 | AZ10: 0.4 | BA10: 0.4 | BB10: 0.4 | BC10: 0.4 | BD10: 0.4 | BE10: 0.4 | BF10: 0.4 | BG10: 0.4 | BH10: 0.4 | BI10: 0.4 | BJ10: 0.4 | BK10: 0.4 | BL10: 0.4 | BM10: 0.4 | BN10: 0.4 | BO10: 0.4 | BP10: 0.4 | BQ10: 0.4 | BR10: 0.4
C11: 受注率 | F11: 0.6 | G11: 0.6 | H11: 0.6 | I11: 0.6 | J11: 0.6 | K11: 0.6 | L11: 0.6 | M11: 0.6 | N11: 0.6 | O11: 0.6 | P11: 0.6 | Q11: 0.6 | R11: 0.6 | S11: 0.6 | T11: 0.6 | U11: 0.6 | V11: 0.6 | W11: 0.6 | X11: 0.6 | Y11: 0.6 | Z11: 0.6 | AA11: 0.6 | AB11: 0.6 | AC11: 0.6 | AD11: 0.6 | AE11: 0.6 | AF11: 0.6 | AG11: 0.6 | AH11: 0.6 | AI11: 0.6 | AJ11: 0.6 | AK11: 0.6 | AL11: 0.6 | AM11: 0.6 | AN11: 0.6 | AO11: 0.6 | AP11: 0.6 | AQ11: 0.6 | AR11: 0.6 | AS11: 0.6 | AT11: 0.6 | AU11: 0.6 | AV11: 0.6 | AW11: 0.6 | AX11: 0.6 | AY11: 0.6 | AZ11: 0.6 | BA11: 0.6 | BB11: 0.6 | BC11: 0.6 | BD11: 0.6 | BE11: 0.6 | BF11: 0.6 | BG11: 0.6 | BH11: 0.6 | BI11: 0.6 | BJ11: 0.6 | BK11: 0.6 | BL11: 0.6 | BM11: 0.6 | BN11: 0.6 | BO11: 0.6 | BP11: 0.6 | BQ11: 0.6 | BR11: 0.6
C12: １税理士 / 受注数（累計獲得数・解約前） | F12: =PRODUCT(F6:F11) -> 0 | G12: =PRODUCT(G6:G11) -> 2.499 | H12: =PRODUCT(H6:H11) -> 13.7445 | I12: =PRODUCT(I6:I11) -> 24.99 | J12: =PRODUCT(J6:J11) -> 34.986 | K12: =PRODUCT(K6:K11) -> 47.481 | L12: =PRODUCT(L6:L11) -> 59.976 | M12: =PRODUCT(M6:M11) -> 72.471 | ... BR12: =PRODUCT(BR6:BR11) -> 1421.931
C13: 単価 | F13: =F14*F15 -> 1500 | G13: =G14*G15 -> 1500 | H13: =H14*H15 -> 1500 | I13: =I14*I15 -> 1500 | J13: =J14*J15 -> 1500 | K13: =K14*K15 -> 1500 | L13: =L14*L15 -> 1500 | M13: =M14*M15 -> 1500 | ... BR13: =BR14*BR15 -> 1500
C14: 企業の年間販管費（人件費抜き） | D14: https://www.e-stat.go.jp/stat-search/files?tclass=000001230645&cycle=7&year=20240 | F14: 3000000 | G14: 3000000 | H14: 3000000 | I14: 3000000 | J14: 3000000 | K14: 3000000 | L14: 3000000 | M14: 3000000 | N14: 3000000 | O14: 3000000 | P14: 3000000 | Q14: 3000000 | R14: 3000000 | S14: 3000000 | T14: 3000000 | U14: 3000000 | V14: 3000000 | W14: 3000000 | X14: 3000000 | Y14: 3000000 | Z14: 3000000 | AA14: 3000000 | AB14: 3000000 | AC14: 3000000 | AD14: 3000000 | AE14: 3000000 | AF14: 3000000 | AG14: 3000000 | AH14: 3000000 | AI14: 3000000 | AJ14: 3000000 | AK14: 3000000 | AL14: 3000000 | AM14: 3000000 | AN14: 3000000 | AO14: 3000000 | AP14: 3000000 | AQ14: 3000000 | AR14: 3000000 | AS14: 3000000 | AT14: 3000000 | AU14: 3000000 | AV14: 3000000 | AW14: 3000000 | AX14: 3000000 | AY14: 3000000 | AZ14: 3000000 | BA14: 3000000 | BB14: 3000000 | BC14: 3000000 | BD14: 3000000 | BE14: 3000000 | BF14: 3000000 | BG14: 3000000 | BH14: 3000000 | BI14: 3000000 | BJ14: 3000000 | BK14: 3000000 | BL14: 3000000 | BM14: 3000000 | BN14: 3000000 | BO14: 3000000 | BP14: 3000000 | BQ14: 3000000 | BR14: 3000000
C15: 支払い.com Taxel 紹介費用率 | F15: 0.0005 | G15: 0.0005 | H15: 0.0005 | I15: 0.0005 | J15: 0.0005 | K15: 0.0005 | L15: 0.0005 | M15: 0.0005 | N15: 0.0005 | O15: 0.0005 | P15: 0.0005 | Q15: 0.0005 | R15: 0.0005 | S15: 0.0005 | T15: 0.0005 | U15: 0.0005 | V15: 0.0005 | W15: 0.0005 | X15: 0.0005 | Y15: 0.0005 | Z15: 0.0005 | AA15: 0.0005 | AB15: 0.0005 | AC15: 0.0005 | AD15: 0.0005 | AE15: 0.0005 | AF15: 0.0005 | AG15: 0.0005 | AH15: 0.0005 | AI15: 0.0005 | AJ15: 0.0005 | AK15: 0.0005 | AL15: 0.0005 | AM15: 0.0005 | AN15: 0.0005 | AO15: 0.0005 | AP15: 0.0005 | AQ15: 0.0005 | AR15: 0.0005 | AS15: 0.0005 | AT15: 0.0005 | AU15: 0.0005 | AV15: 0.0005 | AW15: 0.0005 | AX15: 0.0005 | AY15: 0.0005 | AZ15: 0.0005 | BA15: 0.0005 | BB15: 0.0005 | BC15: 0.0005 | BD15: 0.0005 | BE15: 0.0005 | BF15: 0.0005 | BG15: 0.0005 | BH15: 0.0005 | BI15: 0.0005 | BJ15: 0.0005 | BK15: 0.0005 | BL15: 0.0005 | BM15: 0.0005 | BN15: 0.0005 | BO15: 0.0005 | BP15: 0.0005 | BQ15: 0.0005 | BR15: 0.0005
C16: １税理士 / 紹介費用 | F16: =F24*F13/12 -> 0 | G16: =G24*G13/12 -> 312.375 | H16: =H24*H13/12 -> 1711.815 | I16: =I24*I13/12 -> 3083.2662 | J16: =J24*J13/12 -> 4271.1009 | K16: =K24*K13/12 -> 5747.5539 | L16: =L24*L13/12 -> 7194.4778 | M16: =M24*M13/12 -> 8612.4632 | ... BM16: =BM24*BM13/12 -> 125979.05 | BN16: =SUM(F16:Q16) -> 81453.585 | BO16: =SUM(R16:AC16) -> 312030.73 | BP16: =SUM(AD16:AO16) -> 596438.03 | BQ16: =SUM(AP16:BA16) -> 917020.93 | BR16: =SUM(BB16:BM16) -> 1307193.1
C17: 税理士数＝アカウト数 | F17: 0 | G17: 2 | H17: 11 | I17: 20 | J17: 28 | K17: 38 | L17: 48 | M17: 58 | N17: 70 | O17: 81 | P17: 92 | Q17: 105 | R17: 117 | S17: 129 | T17: 143 | U17: 156 | V17: 169 | W17: 184 | X17: 198 | Y17: 212 | Z17: 228 | AA17: 243 | AB17: 258 | AC17: 274 | AD17: 292 | AE17: 309 | AF17: 328 | AG17: 346 | AH17: 365 | AI17: 384 | AJ17: 404 | AK17: 423 | AL17: 444 | AM17: 464 | AN17: 484 | AO17: 506 | AP17: 527 | AQ17: 548 | AR17: 570 | AS17: 592 | AT17: 614 | AU17: 637 | AV17: 660 | AW17: 683 | AX17: 707 | AY17: 730 | AZ17: 754 | BA17: 778 | BB17: 807 | BC17: 835 | BD17: 864 | BE17: 893 | BF17: 922 | BG17: 953 | BH17: 983 | BI17: 1013 | BJ17: 1044 | BK17: 1075 | BL17: 1106 | BM17: 1138 | BN17: =Q17 -> 105 | BO17: =AC17 -> 274 | BP17: =AO17 -> 506 | BQ17: =BA17 -> 778 | BR17: =BM17 -> 1138
C18: 新規 | F18: 0 | G18: 1 | H18: 5 | I18: 5 | J18: 5 | K18: =H18+1 -> 6 | L18: =I18+1 -> 6 | M18: =J18+1 -> 6 | N18: =K18+1 -> 7 | O18: =L18+1 -> 7 | P18: =M18+1 -> 7 | Q18: =N18+1 -> 8 | R18: =O18+1 -> 8 | ... BM18: =BJ18+1 -> 24 | BN18: =SUM(F18:Q18) -> 63 | BO18: =SUM(R18:AC18) -> 118 | BP18: =SUM(AD18:AO18) -> 166 | BQ18: =SUM(AP18:BA18) -> 214 | BR18: =SUM(BB18:BM18) -> 262
C19: 解約予想数 | F19: 0 | G19: =F24*G20 -> 0 | H19: =G24*H20 -> 0.04998 | I19: =H24*I20 -> 0.2738904 | J19: =I24*J20 -> 0.49332259 | K19: =J24*K20 -> 0.68337614 | L19: =K24*L20 -> 0.91960862 | M19: =L24*M20 -> 1.1511164 | N19: =M24*N20 -> 1.3779941 | ... BM19: =BL24*BM20 -> 14.738808 | BN19: =SUM(F19:Q19) -> 10.621044 | BO19: =SUM(R19:AC19) -> 46.634292 | BP19: =SUM(AD19:AO19) -> 79.825297 | BQ19: =SUM(AP19:BA19) -> 124.61609 | BR19: =SUM(BB19:BM19) -> 152.4019
C20: 解約率 | D20: F&M オフィスステーション1.01% | F20: 0.02 | G20: 0.02 | H20: 0.02 | I20: 0.02 | J20: 0.02 | K20: 0.02 | L20: 0.02 | M20: 0.02 | N20: 0.02 | O20: 0.02 | P20: 0.02 | Q20: 0.02 | R20: 0.02 | S20: 0.02 | T20: 0.02 | U20: 0.02 | V20: 0.02 | W20: 0.02 | X20: 0.02 | Y20: 0.02 | Z20: 0.02 | AA20: 0.02 | AB20: 0.02 | AC20: 0.02 | AD20: 0.0175 | AE20: 0.0175 | AF20: 0.0175 | AG20: 0.0175 | AH20: 0.0175 | AI20: 0.0175 | AJ20: 0.0175 | AK20: 0.0175 | AL20: 0.0175 | AM20: 0.0175 | AN20: 0.0175 | AO20: 0.0175 | AP20: 0.0175 | AQ20: 0.0175 | AR20: 0.0175 | AS20: 0.0175 | AT20: 0.0175 | AU20: 0.0175 | AV20: 0.0175 | AW20: 0.0175 | AX20: 0.0175 | AY20: 0.0175 | AZ20: 0.0175 | BA20: 0.0175 | BB20: 0.015 | BC20: 0.015 | BD20: 0.015 | BE20: 0.015 | BF20: 0.015 | BG20: 0.015 | BH20: 0.015 | BI20: 0.015 | BJ20: 0.015 | BK20: 0.015 | BL20: 0.015 | BM20: 0.015 | BN20: =AVERAGE(F20:Q20) -> 0.02 | BO20: =AVERAGE(R20:AC20) -> 0.02 | BP20: =AVERAGE(AD20:AO20) -> 0.0175 | BQ20: =AVERAGE(AP20:BA20) -> 0.0175 | BR20: =AVERAGE(BB20:BM20) -> 0.015
C22: ■ ストック計算（契約社数＝前月契約社数＋当月新規受注－当月解約）
C23: 新規受注数（当月） | D23: ＝当月の累計獲得数(12行)－前月の累計獲得数。税理士獲得ロジック(×35等)は別途検討中のため、既存ファネルを流用 | F23: =F12 -> 0 | G23: =G12-F12 -> 2.499 | H23: =H12-G12 -> 11.2455 | I23: =I12-H12 -> 11.2455 | J23: =J12-I12 -> 9.996 | K23: =K12-J12 -> 12.495 | L23: =L12-K12 -> 12.495 | M23: =M12-L12 -> 12.495 | N23: =N12-M12 -> 14.994 | ... BM23: =BM12-BL12 -> 39.984 | BN23: =SUM(F23:Q23) -> 131.1975 | BO23: =SUM(R23:AC23) -> 211.1655 | BP23: =SUM(AD23:AO23) -> 289.884 | BQ23: =SUM(AP23:BA23) -> 339.864 | BR23: =SUM(BB23:BM23) -> 449.82
C24: 期末契約社数（ストック） | D24: ＝前月末契約社数＋新規受注数－解約予想数。売上＝本行×単価 | F24: =F23-F19 -> 0 | G24: =F24+G23-G19 -> 2.499 | H24: =G24+H23-H19 -> 13.69452 | I24: =H24+I23-I19 -> 24.66613 | J24: =I24+J23-J19 -> 34.168807 | K24: =J24+K23-K19 -> 45.980431 | L24: =K24+L23-L19 -> 57.555822 | M24: =L24+M23-M19 -> 68.899706 | N24: =M24+N23-N19 -> 82.515712 | ... BM24: =BL24+BM23-BM19 -> 1007.8324 | BN24: =Q24 -> 120.57646 | BO24: =AC24 -> 285.10766 | BP24: =AO24 -> 495.16637 | BQ24: =BA24 -> 710.41428 | BR24: =BM24 -> 1007.8324

Sheet PB
C4: ■ プライベートバンク ➡ UBM 積立式 | F4: Y1_M1 | G4: Y1_M2 | H4: Y1_M3 | I4: Y1_M4 | J4: Y1_M5 | K4: Y1_M6 | L4: Y1_M7 | M4: Y1_M8 | N4: Y1_M9 | O4: Y1_M10 | P4: Y1_M11 | Q4: Y1_M12 | R4: Y2_M1 | S4: Y2_M2 | T4: Y2_M3 | U4: Y2_M4 | V4: Y2_M5 | W4: Y2_M6 | X4: Y2_M7 | Y4: Y2_M8 | Z4: Y2_M9 | AA4: Y2_M10 | AB4: Y2_M11 | AC4: Y2_M12 | AD4: Y3_M1 | AE4: Y3_M2 | AF4: Y3_M3 | AG4: Y3_M4 | AH4: Y3_M5 | AI4: Y3_M6 | AJ4: Y3_M7 | AK4: Y3_M8 | AL4: Y3_M9 | AM4: Y3_M10 | AN4: Y3_M11 | AO4: Y3_M12 | AP4: Y4_M1 | AQ4: Y4_M2 | AR4: Y4_M3 | AS4: Y4_M4 | AT4: Y4_M5 | AU4: Y4_M6 | AV4: Y4_M7 | AW4: Y4_M8 | AX4: Y4_M9 | AY4: Y4_M10 | AZ4: Y4_M11 | BA4: Y4_M12 | BB4: Y5_M1 | BC4: Y5_M2 | BD4: Y5_M3 | BE4: Y5_M4 | BF4: Y5_M5 | BG4: Y5_M6 | BH4: Y5_M7 | BI4: Y5_M8 | BJ4: Y5_M9 | BK4: Y5_M10 | BL4: Y5_M11 | BM4: Y5_M12 | BN4: Y1 | BO4: Y2 | BP4: Y3 | BQ4: Y4 | BR4: Y5
C5: 売上 | F5: =F10*F11 -> 0 | G5: =G22*G11 -> 1814.4 | H5: =H22*H11 -> 9942.912 | I5: =I22*I11 -> 17908.854 | J5: =J22*J11 -> 24808.277 | K5: =K22*K11 -> 33384.111 | L5: =L22*L11 -> 41788.429 | M5: =M22*M11 -> 50024.66 | N5: =N22*N11 -> 59910.567 | ... BM5: =BM22*BM11 -> 731737.12 | BN5: =SUM(F5:Q5) -> 473115.28 | BO5: =SUM(R5:AC5) -> 1812400.3 | BP5: =SUM(AD5:AO5) -> 3464352.7 | BQ5: =SUM(AP5:BA5) -> 5326427.4 | BR5: =SUM(BB5:BM5) -> 7592704.8
C6: 顧問先 | F6: =35*F15 -> 0 | G6: =35*G15 -> 70 | H6: =35*H15 -> 385 | I6: =35*I15 -> 700 | J6: =35*J15 -> 980 | K6: =35*K15 -> 1330 | L6: =35*L15 -> 1680 | M6: =35*M15 -> 2030 | ... BR6: =35*BR15 -> 39830
C7: 月20万円積立可能（役員報酬1,500万円以上） | F7: 0.2 | G7: 0.2 | H7: 0.2 | I7: 0.2 | J7: 0.2 | K7: 0.2 | L7: 0.2 | M7: 0.2 | N7: 0.2 | O7: 0.2 | P7: 0.2 | Q7: 0.2 | R7: 0.2 | S7: 0.2 | T7: 0.2 | U7: 0.2 | V7: 0.2 | W7: 0.2 | X7: 0.2 | Y7: 0.2 | Z7: 0.2 | AA7: 0.2 | AB7: 0.2 | AC7: 0.2 | AD7: 0.2 | AE7: 0.2 | AF7: 0.2 | AG7: 0.2 | AH7: 0.2 | AI7: 0.2 | AJ7: 0.2 | AK7: 0.2 | AL7: 0.2 | AM7: 0.2 | AN7: 0.2 | AO7: 0.2 | AP7: 0.2 | AQ7: 0.2 | AR7: 0.2 | AS7: 0.2 | AT7: 0.2 | AU7: 0.2 | AV7: 0.2 | AW7: 0.2 | AX7: 0.2 | AY7: 0.2 | AZ7: 0.2 | BA7: 0.2 | BB7: 0.2 | BC7: 0.2 | BD7: 0.2 | BE7: 0.2 | BF7: 0.2 | BG7: 0.2 | BH7: 0.2 | BI7: 0.2 | BJ7: 0.2 | BK7: 0.2 | BL7: 0.2 | BM7: 0.2 | BN7: 0.2 | BO7: 0.2 | BP7: 0.2 | BQ7: 0.2 | BR7: 0.2
C8: 税理士 ➡ 企業提案 | F8: 0.3 | G8: 0.3 | H8: 0.3 | I8: 0.3 | J8: 0.3 | K8: 0.3 | L8: 0.3 | M8: 0.3 | N8: 0.3 | O8: 0.3 | P8: 0.3 | Q8: 0.3 | R8: 0.3 | S8: 0.3 | T8: 0.3 | U8: 0.3 | V8: 0.3 | W8: 0.3 | X8: 0.3 | Y8: 0.3 | Z8: 0.3 | AA8: 0.3 | AB8: 0.3 | AC8: 0.3 | AD8: 0.3 | AE8: 0.3 | AF8: 0.3 | AG8: 0.3 | AH8: 0.3 | AI8: 0.3 | AJ8: 0.3 | AK8: 0.3 | AL8: 0.3 | AM8: 0.3 | AN8: 0.3 | AO8: 0.3 | AP8: 0.3 | AQ8: 0.3 | AR8: 0.3 | AS8: 0.3 | AT8: 0.3 | AU8: 0.3 | AV8: 0.3 | AW8: 0.3 | AX8: 0.3 | AY8: 0.3 | AZ8: 0.3 | BA8: 0.3 | BB8: 0.3 | BC8: 0.3 | BD8: 0.3 | BE8: 0.3 | BF8: 0.3 | BG8: 0.3 | BH8: 0.3 | BI8: 0.3 | BJ8: 0.3 | BK8: 0.3 | BL8: 0.3 | BM8: 0.3 | BN8: 0.3 | BO8: 0.3 | BP8: 0.3 | BQ8: 0.3 | BR8: 0.3
C9: 受注率 | F9: 0.2 | G9: 0.2 | H9: 0.2 | I9: 0.2 | J9: 0.2 | K9: 0.2 | L9: 0.2 | M9: 0.2 | N9: 0.2 | O9: 0.2 | P9: 0.2 | Q9: 0.2 | R9: 0.2 | S9: 0.2 | T9: 0.2 | U9: 0.2 | V9: 0.2 | W9: 0.2 | X9: 0.2 | Y9: 0.2 | Z9: 0.2 | AA9: 0.2 | AB9: 0.2 | AC9: 0.2 | AD9: 0.2 | AE9: 0.2 | AF9: 0.2 | AG9: 0.2 | AH9: 0.2 | AI9: 0.2 | AJ9: 0.2 | AK9: 0.2 | AL9: 0.2 | AM9: 0.2 | AN9: 0.2 | AO9: 0.2 | AP9: 0.2 | AQ9: 0.2 | AR9: 0.2 | AS9: 0.2 | AT9: 0.2 | AU9: 0.2 | AV9: 0.2 | AW9: 0.2 | AX9: 0.2 | AY9: 0.2 | AZ9: 0.2 | BA9: 0.2 | BB9: 0.2 | BC9: 0.2 | BD9: 0.2 | BE9: 0.2 | BF9: 0.2 | BG9: 0.2 | BH9: 0.2 | BI9: 0.2 | BJ9: 0.2 | BK9: 0.2 | BL9: 0.2 | BM9: 0.2 | BN9: 0.2 | BO9: 0.2 | BP9: 0.2 | BQ9: 0.2 | BR9: 0.2
C10: １税理士 / 受注数（累計獲得数・解約前） | F10: =PRODUCT(F6:F9) -> 0 | G10: =PRODUCT(G6:G9) -> 0.84 | H10: =PRODUCT(H6:H9) -> 4.62 | I10: =PRODUCT(I6:I9) -> 8.4 | J10: =PRODUCT(J6:J9) -> 11.76 | K10: =PRODUCT(K6:K9) -> 15.96 | L10: =PRODUCT(L6:L9) -> 20.16 | M10: =PRODUCT(M6:M9) -> 24.36 | ... BR10: =PRODUCT(BR6:BR9) -> 477.96
C11: 単価 | E11: average | F11: =F12*12*F13 -> 2160 | G11: =G12*12*G13 -> 2160 | H11: =H12*12*H13 -> 2160 | I11: =I12*12*I13 -> 2160 | J11: =J12*12*J13 -> 2160 | K11: =K12*12*K13 -> 2160 | L11: =L12*12*L13 -> 2160 | M11: =M12*12*M13 -> 2160 | ... BM11: =BM12*12*BM13 -> 2160 | BN11: =BN12*BN13 -> 2160 | BO11: =BO12*BO13 -> 2160 | BP11: =BP12*BP13 -> 2160 | BQ11: =BQ12*BQ13 -> 2160 | BR11: =BR12*BR13 -> 2160
C12: 毎月の積立金額 | F12: 300000 | G12: 300000 | H12: 300000 | I12: 300000 | J12: 300000 | K12: 300000 | L12: 300000 | M12: 300000 | N12: 300000 | O12: 300000 | P12: 300000 | Q12: 300000 | R12: 300000 | S12: 300000 | T12: 300000 | U12: 300000 | V12: 300000 | W12: 300000 | X12: 300000 | Y12: 300000 | Z12: 300000 | AA12: 300000 | AB12: 300000 | AC12: 300000 | AD12: 300000 | AE12: 300000 | AF12: 300000 | AG12: 300000 | AH12: 300000 | AI12: 300000 | AJ12: 300000 | AK12: 300000 | AL12: 300000 | AM12: 300000 | AN12: 300000 | AO12: 300000 | AP12: 300000 | AQ12: 300000 | AR12: 300000 | AS12: 300000 | AT12: 300000 | AU12: 300000 | AV12: 300000 | AW12: 300000 | AX12: 300000 | AY12: 300000 | AZ12: 300000 | BA12: 300000 | BB12: 300000 | BC12: 300000 | BD12: 300000 | BE12: 300000 | BF12: 300000 | BG12: 300000 | BH12: 300000 | BI12: 300000 | BJ12: 300000 | BK12: 300000 | BL12: 300000 | BM12: 300000 | BN12: =300000*12 -> 3600000 | BO12: =300000*12 -> 3600000 | BP12: =300000*12 -> 3600000 | BQ12: =300000*12 -> 3600000 | BR12: =300000*12 -> 3600000
C13: Taxel 紹介費用率 | F13: =0.2%*30% -> 0.0006 | G13: =0.2%*30% -> 0.0006 | H13: =0.2%*30% -> 0.0006 | I13: =0.2%*30% -> 0.0006 | J13: =0.2%*30% -> 0.0006 | K13: =0.2%*30% -> 0.0006 | L13: =0.2%*30% -> 0.0006 | M13: =0.2%*30% -> 0.0006 | ... BR13: =0.2%*30% -> 0.0006
C14: １税理士 / 紹介費用 | F14: =F22*F11/12 -> 0 | G14: =G22*G11/12 -> 151.2 | H14: =H22*H11/12 -> 828.576 | I14: =I22*I11/12 -> 1492.4045 | J14: =J22*J11/12 -> 2067.3564 | K14: =K22*K11/12 -> 2782.0093 | L14: =L22*L11/12 -> 3482.3691 | M14: =M22*M11/12 -> 4168.7217 | ... BM14: =BM22*BM11/12 -> 60978.093 | BN14: =SUM(F14:Q14) -> 39426.273 | BO14: =SUM(R14:AC14) -> 151033.36 | BP14: =SUM(AD14:AO14) -> 288696.05 | BQ14: =SUM(AP14:BA14) -> 443868.95 | BR14: =SUM(BB14:BM14) -> 632725.4
C15: 税理士数＝アカウト数 | F15: 0 | G15: 2 | H15: 11 | I15: 20 | J15: 28 | K15: 38 | L15: 48 | M15: 58 | N15: 70 | O15: 81 | P15: 92 | Q15: 105 | R15: 117 | S15: 129 | T15: 143 | U15: 156 | V15: 169 | W15: 184 | X15: 198 | Y15: 212 | Z15: 228 | AA15: 243 | AB15: 258 | AC15: 274 | AD15: 292 | AE15: 309 | AF15: 328 | AG15: 346 | AH15: 365 | AI15: 384 | AJ15: 404 | AK15: 423 | AL15: 444 | AM15: 464 | AN15: 484 | AO15: 506 | AP15: 527 | AQ15: 548 | AR15: 570 | AS15: 592 | AT15: 614 | AU15: 637 | AV15: 660 | AW15: 683 | AX15: 707 | AY15: 730 | AZ15: 754 | BA15: 778 | BB15: 807 | BC15: 835 | BD15: 864 | BE15: 893 | BF15: 922 | BG15: 953 | BH15: 983 | BI15: 1013 | BJ15: 1044 | BK15: 1075 | BL15: 1106 | BM15: 1138 | BN15: =Q15 -> 105 | BO15: =AC15 -> 274 | BP15: =AO15 -> 506 | BQ15: =BA15 -> 778 | BR15: =BM15 -> 1138
C16: 新規 | F16: 0 | G16: 1 | H16: 5 | I16: 5 | J16: 5 | K16: =H16+1 -> 6 | L16: =I16+1 -> 6 | M16: =J16+1 -> 6 | N16: =K16+1 -> 7 | O16: =L16+1 -> 7 | P16: =M16+1 -> 7 | Q16: =N16+1 -> 8 | R16: =O16+1 -> 8 | ... BM16: =BJ16+1 -> 24 | BN16: =SUM(F16:Q16) -> 63 | BO16: =SUM(R16:AC16) -> 118 | BP16: =SUM(AD16:AO16) -> 166 | BQ16: =SUM(AP16:BA16) -> 214 | BR16: =SUM(BB16:BM16) -> 262
C17: 解約予想数 | F17: 0 | G17: =F22*G18 -> 0 | H17: =G22*H18 -> 0.0168 | I17: =H22*I18 -> 0.092064 | J17: =I22*J18 -> 0.16582272 | K17: =J22*K18 -> 0.22970627 | L17: =K22*L18 -> 0.30911214 | M17: =L22*M18 -> 0.3869299 | N17: =M22*N18 -> 0.4631913 | ... BM17: =BL22*BM18 -> 4.9542211 | BN17: =SUM(F17:Q17) -> 3.570099 | BO17: =SUM(R17:AC17) -> 15.675392 | BP17: =SUM(AD17:AO17) -> 26.832033 | BQ17: =SUM(AP17:BA17) -> 41.887762 | BR17: =SUM(BB17:BM17) -> 51.22753
C18: 解約率 | D18: F&M オフィスステーション1.01% | F18: 0.02 | G18: 0.02 | H18: 0.02 | I18: 0.02 | J18: 0.02 | K18: 0.02 | L18: 0.02 | M18: 0.02 | N18: 0.02 | O18: 0.02 | P18: 0.02 | Q18: 0.02 | R18: 0.02 | S18: 0.02 | T18: 0.02 | U18: 0.02 | V18: 0.02 | W18: 0.02 | X18: 0.02 | Y18: 0.02 | Z18: 0.02 | AA18: 0.02 | AB18: 0.02 | AC18: 0.02 | AD18: 0.0175 | AE18: 0.0175 | AF18: 0.0175 | AG18: 0.0175 | AH18: 0.0175 | AI18: 0.0175 | AJ18: 0.0175 | AK18: 0.0175 | AL18: 0.0175 | AM18: 0.0175 | AN18: 0.0175 | AO18: 0.0175 | AP18: 0.0175 | AQ18: 0.0175 | AR18: 0.0175 | AS18: 0.0175 | AT18: 0.0175 | AU18: 0.0175 | AV18: 0.0175 | AW18: 0.0175 | AX18: 0.0175 | AY18: 0.0175 | AZ18: 0.0175 | BA18: 0.0175 | BB18: 0.015 | BC18: 0.015 | BD18: 0.015 | BE18: 0.015 | BF18: 0.015 | BG18: 0.015 | BH18: 0.015 | BI18: 0.015 | BJ18: 0.015 | BK18: 0.015 | BL18: 0.015 | BM18: 0.015 | BN18: =AVERAGE(F18:Q18) -> 0.02 | BO18: =AVERAGE(R18:AC18) -> 0.02 | BP18: =AVERAGE(AD18:AO18) -> 0.0175 | BQ18: =AVERAGE(AP18:BA18) -> 0.0175 | BR18: =AVERAGE(BB18:BM18) -> 0.015
C20: ■ ストック計算（契約社数＝前月契約社数＋当月新規受注－当月解約）
C21: 新規受注数（当月） | D21: ＝当月の累計獲得数(10行)－前月の累計獲得数。税理士獲得ロジック(×35等)は別途検討中のため、既存ファネルを流用 | F21: =F10 -> 0 | G21: =G10-F10 -> 0.84 | H21: =H10-G10 -> 3.78 | I21: =I10-H10 -> 3.78 | J21: =J10-I10 -> 3.36 | K21: =K10-J10 -> 4.2 | L21: =L10-K10 -> 4.2 | M21: =M10-L10 -> 4.2 | N21: =N10-M10 -> 5.04 | ... BM21: =BM10-BL10 -> 13.44 | BN21: =SUM(F21:Q21) -> 44.1 | BO21: =SUM(R21:AC21) -> 70.98 | BP21: =SUM(AD21:AO21) -> 97.44 | BQ21: =SUM(AP21:BA21) -> 114.24 | BR21: =SUM(BB21:BM21) -> 151.2
C22: 期末契約社数（ストック） | D22: ＝前月末契約社数＋新規受注数－解約予想数。売上＝本行×単価 | F22: =F21-F17 -> 0 | G22: =F22+G21-G17 -> 0.84 | H22: =G22+H21-H17 -> 4.6032 | I22: =H22+I21-I17 -> 8.291136 | J22: =I22+J21-J17 -> 11.485313 | K22: =J22+K21-K17 -> 15.455607 | L22: =K22+L21-L17 -> 19.346495 | M22: =L22+M21-M17 -> 23.159565 | N22: =M22+N21-N17 -> 27.736374 | ... BM22: =BL22+BM21-BM17 -> 338.76718 | BN22: =Q22 -> 40.529901 | BO22: =AC22 -> 95.834509 | BP22: =AO22 -> 166.44248 | BQ22: =BA22 -> 238.79471 | BR22: =BM22 -> 338.76718

Sheet 電力コスト削減
R3: Y2
C4: ■ ④ コスト削減（電力切替）※Y2から開拓 | D4: 丸紅新電力等の大手系の取次。継続報酬型（契約が続く限り毎月）。市場連動プランは扱わない（21-22年高騰の教訓） | F4: Y1_M1 | G4: Y1_M2 | H4: Y1_M3 | I4: Y1_M4 | J4: Y1_M5 | K4: Y1_M6 | L4: Y1_M7 | M4: Y1_M8 | N4: Y1_M9 | O4: Y1_M10 | P4: Y1_M11 | Q4: Y1_M12 | R4: Y2_M1 | S4: Y2_M2 | T4: Y2_M3 | U4: Y2_M4 | V4: Y2_M5 | W4: Y2_M6 | X4: Y2_M7 | Y4: Y2_M8 | Z4: Y2_M9 | AA4: Y2_M10 | AB4: Y2_M11 | AC4: Y2_M12 | AD4: Y3_M1 | AE4: Y3_M2 | AF4: Y3_M3 | AG4: Y3_M4 | AH4: Y3_M5 | AI4: Y3_M6 | AJ4: Y3_M7 | AK4: Y3_M8 | AL4: Y3_M9 | AM4: Y3_M10 | AN4: Y3_M11 | AO4: Y3_M12 | AP4: Y4_M1 | AQ4: Y4_M2 | AR4: Y4_M3 | AS4: Y4_M4 | AT4: Y4_M5 | AU4: Y4_M6 | AV4: Y4_M7 | AW4: Y4_M8 | AX4: Y4_M9 | AY4: Y4_M10 | AZ4: Y4_M11 | BA4: Y4_M12 | BB4: Y5_M1 | BC4: Y5_M2 | BD4: Y5_M3 | BE4: Y5_M4 | BF4: Y5_M5 | BG4: Y5_M6 | BH4: Y5_M7 | BI4: Y5_M8 | BJ4: Y5_M9 | BK4: Y5_M10 | BL4: Y5_M11 | BM4: Y5_M12 | BN4: Y1 | BO4: Y2 | BP4: Y3 | BQ4: Y4 | BR4: Y5
C5: 売上 | F5: =F25*F16 -> 0 | G5: =G11*G16 -> 2450 | H5: =H11*H16 -> 13475 | I5: =I11*I16 -> 24500 | J5: =J11*J16 -> 34300 | K5: =K11*K16 -> 46550 | L5: =L11*L16 -> 58800 | M5: =M11*M16 -> 71050 | N5: =N11*N16 -> 85750 | ... BM5: =BM11*BM16 -> 1394050 | BN5: =SUM(F5:Q5) -> 677425 | BO5: =SUM(R5:AC5) -> 2830975 | BP5: =SUM(AD5:AO5) -> 5817525 | BQ5: =SUM(AP5:BA5) -> 9555000 | BR5: =SUM(BB5:BM5) -> 14250425
C6: 顧問先 | F6: =35*F18 -> 0 | G6: =35*G18 -> 70 | H6: =35*H18 -> 385 | I6: =35*I18 -> 700 | J6: =35*J18 -> 980 | K6: =35*K18 -> 1330 | L6: =35*L18 -> 1680 | M6: =35*M18 -> 2030 | ... BR6: =35*BR18 -> 39830
C7: 電力コスト大・切替メリットあり割合 | D7: 検出＝決算書の水道光熱費が売上比大（製造・飲食・介護等）。推定 | F7: 0.4 | G7: 0.4 | H7: 0.4 | I7: 0.4 | J7: 0.4 | K7: 0.4 | L7: 0.4 | M7: 0.4 | N7: 0.4 | O7: 0.4 | P7: 0.4 | Q7: 0.4 | R7: 0.4 | S7: 0.4 | T7: 0.4 | U7: 0.4 | V7: 0.4 | W7: 0.4 | X7: 0.4 | Y7: 0.4 | Z7: 0.4 | AA7: 0.4 | AB7: 0.4 | AC7: 0.4 | AD7: 0.4 | AE7: 0.4 | AF7: 0.4 | AG7: 0.4 | AH7: 0.4 | AI7: 0.4 | AJ7: 0.4 | AK7: 0.4 | AL7: 0.4 | AM7: 0.4 | AN7: 0.4 | AO7: 0.4 | AP7: 0.4 | AQ7: 0.4 | AR7: 0.4 | AS7: 0.4 | AT7: 0.4 | AU7: 0.4 | AV7: 0.4 | AW7: 0.4 | AX7: 0.4 | AY7: 0.4 | AZ7: 0.4 | BA7: 0.4 | BB7: 0.4 | BC7: 0.4 | BD7: 0.4 | BE7: 0.4 | BF7: 0.4 | BG7: 0.4 | BH7: 0.4 | BI7: 0.4 | BJ7: 0.4 | BK7: 0.4 | BL7: 0.4 | BM7: 0.4 | BN7: 0.4 | BO7: 0.4 | BP7: 0.4 | BQ7: 0.4 | BR7: 0.4
C8: 税理士 ➡ 企業提案 | D8: 工事なし・書類1枚・削減額は請求書で確定＝提案しやすい。推定 | F8: 0.5 | G8: 0.5 | H8: 0.5 | I8: 0.5 | J8: 0.5 | K8: 0.5 | L8: 0.5 | M8: 0.5 | N8: 0.5 | O8: 0.5 | P8: 0.5 | Q8: 0.5 | R8: 0.5 | S8: 0.5 | T8: 0.5 | U8: 0.5 | V8: 0.5 | W8: 0.5 | X8: 0.5 | Y8: 0.5 | Z8: 0.5 | AA8: 0.5 | AB8: 0.5 | AC8: 0.5 | AD8: 0.5 | AE8: 0.5 | AF8: 0.5 | AG8: 0.5 | AH8: 0.5 | AI8: 0.5 | AJ8: 0.5 | AK8: 0.5 | AL8: 0.5 | AM8: 0.5 | AN8: 0.5 | AO8: 0.5 | AP8: 0.5 | AQ8: 0.5 | AR8: 0.5 | AS8: 0.5 | AT8: 0.5 | AU8: 0.5 | AV8: 0.5 | AW8: 0.5 | AX8: 0.5 | AY8: 0.5 | AZ8: 0.5 | BA8: 0.5 | BB8: 0.5 | BC8: 0.5 | BD8: 0.5 | BE8: 0.5 | BF8: 0.5 | BG8: 0.5 | BH8: 0.5 | BI8: 0.5 | BJ8: 0.5 | BK8: 0.5 | BL8: 0.5 | BM8: 0.5 | BN8: 0.5 | BO8: 0.5 | BP8: 0.5 | BQ8: 0.5 | BR8: 0.5
C9: 受注率 | D9: 推定 | F9: 0.5 | G9: 0.5 | H9: 0.5 | I9: 0.5 | J9: 0.5 | K9: 0.5 | L9: 0.5 | M9: 0.5 | N9: 0.5 | O9: 0.5 | P9: 0.5 | Q9: 0.5 | R9: 0.5 | S9: 0.5 | T9: 0.5 | U9: 0.5 | V9: 0.5 | W9: 0.5 | X9: 0.5 | Y9: 0.5 | Z9: 0.5 | AA9: 0.5 | AB9: 0.5 | AC9: 0.5 | AD9: 0.5 | AE9: 0.5 | AF9: 0.5 | AG9: 0.5 | AH9: 0.5 | AI9: 0.5 | AJ9: 0.5 | AK9: 0.5 | AL9: 0.5 | AM9: 0.5 | AN9: 0.5 | AO9: 0.5 | AP9: 0.5 | AQ9: 0.5 | AR9: 0.5 | AS9: 0.5 | AT9: 0.5 | AU9: 0.5 | AV9: 0.5 | AW9: 0.5 | AX9: 0.5 | AY9: 0.5 | AZ9: 0.5 | BA9: 0.5 | BB9: 0.5 | BC9: 0.5 | BD9: 0.5 | BE9: 0.5 | BF9: 0.5 | BG9: 0.5 | BH9: 0.5 | BI9: 0.5 | BJ9: 0.5 | BK9: 0.5 | BL9: 0.5 | BM9: 0.5 | BN9: 0.5 | BO9: 0.5 | BP9: 0.5 | BQ9: 0.5 | BR9: 0.5
C10: 定常浸透率 | D10: 導入後の継続利用率。推定 | F10: 0.7 | G10: 0.7 | H10: 0.7 | I10: 0.7 | J10: 0.7 | K10: 0.7 | L10: 0.7 | M10: 0.7 | N10: 0.7 | O10: 0.7 | P10: 0.7 | Q10: 0.7 | R10: 0.7 | S10: 0.7 | T10: 0.7 | U10: 0.7 | V10: 0.7 | W10: 0.7 | X10: 0.7 | Y10: 0.7 | Z10: 0.7 | AA10: 0.7 | AB10: 0.7 | AC10: 0.7 | AD10: 0.7 | AE10: 0.7 | AF10: 0.7 | AG10: 0.7 | AH10: 0.7 | AI10: 0.7 | AJ10: 0.7 | AK10: 0.7 | AL10: 0.7 | AM10: 0.7 | AN10: 0.7 | AO10: 0.7 | AP10: 0.7 | AQ10: 0.7 | AR10: 0.7 | AS10: 0.7 | AT10: 0.7 | AU10: 0.7 | AV10: 0.7 | AW10: 0.7 | AX10: 0.7 | AY10: 0.7 | AZ10: 0.7 | BA10: 0.7 | BB10: 0.7 | BC10: 0.7 | BD10: 0.7 | BE10: 0.7 | BF10: 0.7 | BG10: 0.7 | BH10: 0.7 | BI10: 0.7 | BJ10: 0.7 | BK10: 0.7 | BL10: 0.7 | BM10: 0.7 | BN10: 0.7 | BO10: 0.7 | BP10: 0.7 | BQ10: 0.7 | BR10: 0.7
C11: １税理士 / 受注数（定常）（累計獲得数・解約前） | F11: =PRODUCT(F6:F10) -> 0 | G11: =PRODUCT(G6:G10) -> 4.9 | H11: =PRODUCT(H6:H10) -> 26.95 | I11: =PRODUCT(I6:I10) -> 49 | J11: =PRODUCT(J6:J10) -> 68.6 | K11: =PRODUCT(K6:K10) -> 93.1 | L11: =PRODUCT(L6:L10) -> 117.6 | M11: =PRODUCT(M6:M10) -> 142.1 | ... BR11: =PRODUCT(BR6:BR10) -> 2788.1
C12: 想定電気料金（月/社） | D12: 中小の電気代 月10〜30万の保守側。推定 | F12: 150000 | G12: 150000 | H12: 150000 | I12: 150000 | J12: 150000 | K12: 150000 | L12: 150000 | M12: 150000 | N12: 150000 | O12: 150000 | P12: 150000 | Q12: 150000 | R12: 150000 | S12: 150000 | T12: 150000 | U12: 150000 | V12: 150000 | W12: 150000 | X12: 150000 | Y12: 150000 | Z12: 150000 | AA12: 150000 | AB12: 150000 | AC12: 150000 | AD12: 150000 | AE12: 150000 | AF12: 150000 | AG12: 150000 | AH12: 150000 | AI12: 150000 | AJ12: 150000 | AK12: 150000 | AL12: 150000 | AM12: 150000 | AN12: 150000 | AO12: 150000 | AP12: 150000 | AQ12: 150000 | AR12: 150000 | AS12: 150000 | AT12: 150000 | AU12: 150000 | AV12: 150000 | AW12: 150000 | AX12: 150000 | AY12: 150000 | AZ12: 150000 | BA12: 150000 | BB12: 150000 | BC12: 150000 | BD12: 150000 | BE12: 150000 | BF12: 150000 | BG12: 150000 | BH12: 150000 | BI12: 150000 | BJ12: 150000 | BK12: 150000 | BL12: 150000 | BM12: 150000 | BN12: 150000 | BO12: 150000 | BP12: 150000 | BQ12: 150000 | BR12: 150000
C13: 取次手数料率（継続・対電気料金） | D13: 新電力取次の相場1〜5%の下側。料率は非公開＝要交渉。推定 | F13: 0.02 | G13: 0.02 | H13: 0.02 | I13: 0.02 | J13: 0.02 | K13: 0.02 | L13: 0.02 | M13: 0.02 | N13: 0.02 | O13: 0.02 | P13: 0.02 | Q13: 0.02 | R13: 0.02 | S13: 0.02 | T13: 0.02 | U13: 0.02 | V13: 0.02 | W13: 0.02 | X13: 0.02 | Y13: 0.02 | Z13: 0.02 | AA13: 0.02 | AB13: 0.02 | AC13: 0.02 | AD13: 0.02 | AE13: 0.02 | AF13: 0.02 | AG13: 0.02 | AH13: 0.02 | AI13: 0.02 | AJ13: 0.02 | AK13: 0.02 | AL13: 0.02 | AM13: 0.02 | AN13: 0.02 | AO13: 0.02 | AP13: 0.02 | AQ13: 0.02 | AR13: 0.02 | AS13: 0.02 | AT13: 0.02 | AU13: 0.02 | AV13: 0.02 | AW13: 0.02 | AX13: 0.02 | AY13: 0.02 | AZ13: 0.02 | BA13: 0.02 | BB13: 0.02 | BC13: 0.02 | BD13: 0.02 | BE13: 0.02 | BF13: 0.02 | BG13: 0.02 | BH13: 0.02 | BI13: 0.02 | BJ13: 0.02 | BK13: 0.02 | BL13: 0.02 | BM13: 0.02 | BN13: 0.02 | BO13: 0.02 | BP13: 0.02 | BQ13: 0.02 | BR13: 0.02
C14: 手数料計（月/社） | F14: =F12*F13 -> 3000 | G14: =G12*G13 -> 3000 | H14: =H12*H13 -> 3000 | I14: =I12*I13 -> 3000 | J14: =J12*J13 -> 3000 | K14: =K12*K13 -> 3000 | L14: =L12*L13 -> 3000 | M14: =M12*M13 -> 3000 | ... BR14: =BR12*BR13 -> 3000
C15: 内・税理士（月/社） | D15: ビジとりと同配分（税理士5：taXel1） | F15: 2500 | G15: 2500 | H15: 2500 | I15: 2500 | J15: 2500 | K15: 2500 | L15: 2500 | M15: 2500 | N15: 2500 | O15: 2500 | P15: 2500 | Q15: 2500 | R15: 2500 | S15: 2500 | T15: 2500 | U15: 2500 | V15: 2500 | W15: 2500 | X15: 2500 | Y15: 2500 | Z15: 2500 | AA15: 2500 | AB15: 2500 | AC15: 2500 | AD15: 2500 | AE15: 2500 | AF15: 2500 | AG15: 2500 | AH15: 2500 | AI15: 2500 | AJ15: 2500 | AK15: 2500 | AL15: 2500 | AM15: 2500 | AN15: 2500 | AO15: 2500 | AP15: 2500 | AQ15: 2500 | AR15: 2500 | AS15: 2500 | AT15: 2500 | AU15: 2500 | AV15: 2500 | AW15: 2500 | AX15: 2500 | AY15: 2500 | AZ15: 2500 | BA15: 2500 | BB15: 2500 | BC15: 2500 | BD15: 2500 | BE15: 2500 | BF15: 2500 | BG15: 2500 | BH15: 2500 | BI15: 2500 | BJ15: 2500 | BK15: 2500 | BL15: 2500 | BM15: 2500 | BN15: 2500 | BO15: 2500 | BP15: 2500 | BQ15: 2500 | BR15: 2500
C16: 内・taXel（月/社） | F16: =F14-F15 -> 500 | G16: =G14-G15 -> 500 | H16: =H14-H15 -> 500 | I16: =I14-I15 -> 500 | J16: =J14-J15 -> 500 | K16: =K14-K15 -> 500 | L16: =L14-L15 -> 500 | M16: =M14-M15 -> 500 | ... BR16: =BR14-BR15 -> 500
C17: １税理士 / 紹介費用 | D17: Y2（M13）から開拓 | F17: 0 | G17: 0 | H17: 0 | I17: 0 | J17: 0 | K17: 0 | L17: 0 | M17: 0 | N17: 0 | O17: 0 | P17: 0 | Q17: 0 | R17: =R16*R25 -> 130547.97 | S17: =S16*S25 -> 142637.01 | T17: =T16*T25 -> 156934.27 | U17: =U16*U25 -> 169720.58 | V17: =V16*V25 -> 182251.17 | W17: =W16*W25 -> 196981.15 | X17: =X16*X25 -> 210191.52 | Y17: =Y16*Y25 -> 223137.69 | ... BM17: =BM16*BM25 -> 988070.95 | BN17: =SUM(F17:Q17) -> 0 | BO17: =SUM(R17:AC17) -> 2447299.8 | BP17: =SUM(AD17:AO17) -> 4677945.3 | BQ17: =SUM(AP17:BA17) -> 7192321 | BR17: =SUM(BB17:BM17) -> 10252495
C18: 税理士数＝アカウト数 | F18: 0 | G18: 2 | H18: 11 | I18: 20 | J18: 28 | K18: 38 | L18: 48 | M18: 58 | N18: 70 | O18: 81 | P18: 92 | Q18: 105 | R18: 117 | S18: 129 | T18: 143 | U18: 156 | V18: 169 | W18: 184 | X18: 198 | Y18: 212 | Z18: 228 | AA18: 243 | AB18: 258 | AC18: 274 | AD18: 292 | AE18: 309 | AF18: 328 | AG18: 346 | AH18: 365 | AI18: 384 | AJ18: 404 | AK18: 423 | AL18: 444 | AM18: 464 | AN18: 484 | AO18: 506 | AP18: 527 | AQ18: 548 | AR18: 570 | AS18: 592 | AT18: 614 | AU18: 637 | AV18: 660 | AW18: 683 | AX18: 707 | AY18: 730 | AZ18: 754 | BA18: 778 | BB18: 807 | BC18: 835 | BD18: 864 | BE18: 893 | BF18: 922 | BG18: 953 | BH18: 983 | BI18: 1013 | BJ18: 1044 | BK18: 1075 | BL18: 1106 | BM18: 1138 | BN18: =Q18 -> 105 | BO18: =AC18 -> 274 | BP18: =AO18 -> 506 | BQ18: =BA18 -> 778 | BR18: =BM18 -> 1138
C19: 新規 | F19: 0 | G19: 1 | H19: 5 | I19: 5 | J19: 5 | K19: =H19+1 -> 6 | L19: =I19+1 -> 6 | M19: =J19+1 -> 6 | N19: =K19+1 -> 7 | O19: =L19+1 -> 7 | P19: =M19+1 -> 7 | Q19: =N19+1 -> 8 | R19: =O19+1 -> 8 | ... BM19: =BJ19+1 -> 24 | BN19: =SUM(F19:Q19) -> 63 | BO19: =SUM(R19:AC19) -> 118 | BP19: =SUM(AD19:AO19) -> 166 | BQ19: =SUM(AP19:BA19) -> 214 | BR19: =SUM(BB19:BM19) -> 262
C20: 解約予想数 | F20: 0 | G20: =F25*G21 -> 0 | H20: =G25*H21 -> 0.098 | I20: =H25*I21 -> 0.53704 | J20: =I25*J21 -> 0.9672992 | K20: =J25*K21 -> 1.3399532 | L20: =K25*L21 -> 1.8031542 | M20: =L25*M21 -> 2.2570911 | N20: =M25*N21 -> 2.7019492 | ... BM20: =BL25*BM21 -> 28.899623 | BN20: =SUM(F20:Q20) -> 20.825577 | BO20: =SUM(R20:AC20) -> 91.439788 | BP20: =SUM(AD20:AO20) -> 156.52019 | BQ20: =SUM(AP20:BA20) -> 244.34528 | BR20: =SUM(BB20:BM20) -> 298.82726
C21: 解約率 | D21: F&M オフィスステーション1.01% | F21: 0.02 | G21: 0.02 | H21: 0.02 | I21: 0.02 | J21: 0.02 | K21: 0.02 | L21: 0.02 | M21: 0.02 | N21: 0.02 | O21: 0.02 | P21: 0.02 | Q21: 0.02 | R21: 0.02 | S21: 0.02 | T21: 0.02 | U21: 0.02 | V21: 0.02 | W21: 0.02 | X21: 0.02 | Y21: 0.02 | Z21: 0.02 | AA21: 0.02 | AB21: 0.02 | AC21: 0.02 | AD21: 0.0175 | AE21: 0.0175 | AF21: 0.0175 | AG21: 0.0175 | AH21: 0.0175 | AI21: 0.0175 | AJ21: 0.0175 | AK21: 0.0175 | AL21: 0.0175 | AM21: 0.0175 | AN21: 0.0175 | AO21: 0.0175 | AP21: 0.0175 | AQ21: 0.0175 | AR21: 0.0175 | AS21: 0.0175 | AT21: 0.0175 | AU21: 0.0175 | AV21: 0.0175 | AW21: 0.0175 | AX21: 0.0175 | AY21: 0.0175 | AZ21: 0.0175 | BA21: 0.0175 | BB21: 0.015 | BC21: 0.015 | BD21: 0.015 | BE21: 0.015 | BF21: 0.015 | BG21: 0.015 | BH21: 0.015 | BI21: 0.015 | BJ21: 0.015 | BK21: 0.015 | BL21: 0.015 | BM21: 0.015 | BN21: =AVERAGE(F21:Q21) -> 0.02 | BO21: =AVERAGE(R21:AC21) -> 0.02 | BP21: =AVERAGE(AD21:AO21) -> 0.0175 | BQ21: =AVERAGE(AP21:BA21) -> 0.0175 | BR21: =AVERAGE(BB21:BM21) -> 0.015
C23: ■ ストック計算（契約社数＝前月契約社数＋当月新規受注－当月解約）
C24: 新規受注数（当月） | D24: ＝当月の累計獲得数(11行)－前月の累計獲得数。税理士獲得ロジック(×35等)は別途検討中のため、既存ファネルを流用 | F24: =F11 -> 0 | G24: =G11-F11 -> 4.9 | H24: =H11-G11 -> 22.05 | I24: =I11-H11 -> 22.05 | J24: =J11-I11 -> 19.6 | K24: =K11-J11 -> 24.5 | L24: =L11-K11 -> 24.5 | M24: =M11-L11 -> 24.5 | N24: =N11-M11 -> 29.4 | ... BM24: =BM11-BL11 -> 78.4 | BN24: =SUM(F24:Q24) -> 257.25 | BO24: =SUM(R24:AC24) -> 414.05 | BP24: =SUM(AD24:AO24) -> 568.4 | BQ24: =SUM(AP24:BA24) -> 666.4 | BR24: =SUM(BB24:BM24) -> 882
C25: 期末契約社数（ストック） | D25: ＝前月末契約社数＋新規受注数－解約予想数。売上＝本行×単価 | F25: =F24-F20 -> 0 | G25: =F25+G24-G20 -> 4.9 | H25: =G25+H24-H20 -> 26.852 | I25: =H25+I24-I20 -> 48.36496 | J25: =I25+J24-J20 -> 66.997661 | K25: =J25+K24-K20 -> 90.157708 | L25: =K25+L24-L20 -> 112.85455 | M25: =L25+M24-M20 -> 135.09746 | N25: =M25+N24-N20 -> 161.79551 | ... BM25: =BL25+BM24-BM20 -> 1976.1419 | BN25: =Q25 -> 236.42442 | BO25: =AC25 -> 559.03463 | BP25: =AO25 -> 970.91444 | BQ25: =BA25 -> 1392.9692 | BR25: =BM25 -> 1976.1419

Sheet  売掛保証（保証型ファクタリング
C4: ■ ⑤ 売掛保証（保証型ファクタリング）※Y1から開拓 | D4: イー・ギャランティ（東証プライム・会計事務所チャネルが本業）等。買取型ファクタリングは扱わない（高手数料・信用リスク）。URIHOは2026/3新規終了 | F4: Y1_M1 | G4: Y1_M2 | H4: Y1_M3 | I4: Y1_M4 | J4: Y1_M5 | K4: Y1_M6 | L4: Y1_M7 | M4: Y1_M8 | N4: Y1_M9 | O4: Y1_M10 | P4: Y1_M11 | Q4: Y1_M12 | R4: Y2_M1 | S4: Y2_M2 | T4: Y2_M3 | U4: Y2_M4 | V4: Y2_M5 | W4: Y2_M6 | X4: Y2_M7 | Y4: Y2_M8 | Z4: Y2_M9 | AA4: Y2_M10 | AB4: Y2_M11 | AC4: Y2_M12 | AD4: Y3_M1 | AE4: Y3_M2 | AF4: Y3_M3 | AG4: Y3_M4 | AH4: Y3_M5 | AI4: Y3_M6 | AJ4: Y3_M7 | AK4: Y3_M8 | AL4: Y3_M9 | AM4: Y3_M10 | AN4: Y3_M11 | AO4: Y3_M12 | AP4: Y4_M1 | AQ4: Y4_M2 | AR4: Y4_M3 | AS4: Y4_M4 | AT4: Y4_M5 | AU4: Y4_M6 | AV4: Y4_M7 | AW4: Y4_M8 | AX4: Y4_M9 | AY4: Y4_M10 | AZ4: Y4_M11 | BA4: Y4_M12 | BB4: Y5_M1 | BC4: Y5_M2 | BD4: Y5_M3 | BE4: Y5_M4 | BF4: Y5_M5 | BG4: Y5_M6 | BH4: Y5_M7 | BI4: Y5_M8 | BJ4: Y5_M9 | BK4: Y5_M10 | BL4: Y5_M11 | BM4: Y5_M12 | BN4: Y1 | BO4: Y2 | BP4: Y3 | BQ4: Y4 | BR4: Y5
C5: 売上 | F5: =F25*F16 -> 0 | G5: =G25*G16 -> 3780 | H5: =H25*H16 -> 20714.4 | I5: =I25*I16 -> 37310.112 | J5: =J25*J16 -> 51683.91 | K5: =K25*K16 -> 69550.232 | L5: =L25*L16 -> 87059.227 | M5: =M25*M16 -> 104218.04 | ... BM5: =BM25*BM16 -> 1524452.3 | BN5: =SUM(F5:Q5) -> 985656.83 | BO5: =SUM(R5:AC5) -> 3775834 | BP5: =SUM(AD5:AO5) -> 7217401.4 | BQ5: =SUM(AP5:BA5) -> 11096724 | BR5: =SUM(BB5:BM5) -> 15818135
C6: 顧問先 | F6: =35*F18 -> 0 | G6: =35*G18 -> 70 | H6: =35*H18 -> 385 | I6: =35*I18 -> 700 | J6: =35*J18 -> 980 | K6: =35*K18 -> 1330 | L6: =35*L18 -> 1680 | M6: =35*M18 -> 2030 | ... BR6: =35*BR18 -> 39830
C7: 掛売り中心・売掛金2ヶ月超割合 | D7: 検出＝売掛金÷月商＞2ヶ月（決算書から自動）。推定 | F7: 0.5 | G7: 0.5 | H7: 0.5 | I7: 0.5 | J7: 0.5 | K7: 0.5 | L7: 0.5 | M7: 0.5 | N7: 0.5 | O7: 0.5 | P7: 0.5 | Q7: 0.5 | R7: 0.5 | S7: 0.5 | T7: 0.5 | U7: 0.5 | V7: 0.5 | W7: 0.5 | X7: 0.5 | Y7: 0.5 | Z7: 0.5 | AA7: 0.5 | AB7: 0.5 | AC7: 0.5 | AD7: 0.5 | AE7: 0.5 | AF7: 0.5 | AG7: 0.5 | AH7: 0.5 | AI7: 0.5 | AJ7: 0.5 | AK7: 0.5 | AL7: 0.5 | AM7: 0.5 | AN7: 0.5 | AO7: 0.5 | AP7: 0.5 | AQ7: 0.5 | AR7: 0.5 | AS7: 0.5 | AT7: 0.5 | AU7: 0.5 | AV7: 0.5 | AW7: 0.5 | AX7: 0.5 | AY7: 0.5 | AZ7: 0.5 | BA7: 0.5 | BB7: 0.5 | BC7: 0.5 | BD7: 0.5 | BE7: 0.5 | BF7: 0.5 | BG7: 0.5 | BH7: 0.5 | BI7: 0.5 | BJ7: 0.5 | BK7: 0.5 | BL7: 0.5 | BM7: 0.5 | BN7: 0.5 | BO7: 0.5 | BP7: 0.5 | BQ7: 0.5 | BR7: 0.5
C8: 税理士 ➡ 企業提案 | D8: 貸倒＝社長の実痛。1社依存の顧問先に刺さる（北村ヒアリング#08） | F8: 0.4 | G8: 0.4 | H8: 0.4 | I8: 0.4 | J8: 0.4 | K8: 0.4 | L8: 0.4 | M8: 0.4 | N8: 0.4 | O8: 0.4 | P8: 0.4 | Q8: 0.4 | R8: 0.4 | S8: 0.4 | T8: 0.4 | U8: 0.4 | V8: 0.4 | W8: 0.4 | X8: 0.4 | Y8: 0.4 | Z8: 0.4 | AA8: 0.4 | AB8: 0.4 | AC8: 0.4 | AD8: 0.4 | AE8: 0.4 | AF8: 0.4 | AG8: 0.4 | AH8: 0.4 | AI8: 0.4 | AJ8: 0.4 | AK8: 0.4 | AL8: 0.4 | AM8: 0.4 | AN8: 0.4 | AO8: 0.4 | AP8: 0.4 | AQ8: 0.4 | AR8: 0.4 | AS8: 0.4 | AT8: 0.4 | AU8: 0.4 | AV8: 0.4 | AW8: 0.4 | AX8: 0.4 | AY8: 0.4 | AZ8: 0.4 | BA8: 0.4 | BB8: 0.4 | BC8: 0.4 | BD8: 0.4 | BE8: 0.4 | BF8: 0.4 | BG8: 0.4 | BH8: 0.4 | BI8: 0.4 | BJ8: 0.4 | BK8: 0.4 | BL8: 0.4 | BM8: 0.4 | BN8: 0.4 | BO8: 0.4 | BP8: 0.4 | BQ8: 0.4 | BR8: 0.4
C9: 受注率 | D9: 保証料コストが発生するため保守。推定 | F9: 0.3 | G9: 0.3 | H9: 0.3 | I9: 0.3 | J9: 0.3 | K9: 0.3 | L9: 0.3 | M9: 0.3 | N9: 0.3 | O9: 0.3 | P9: 0.3 | Q9: 0.3 | R9: 0.3 | S9: 0.3 | T9: 0.3 | U9: 0.3 | V9: 0.3 | W9: 0.3 | X9: 0.3 | Y9: 0.3 | Z9: 0.3 | AA9: 0.3 | AB9: 0.3 | AC9: 0.3 | AD9: 0.3 | AE9: 0.3 | AF9: 0.3 | AG9: 0.3 | AH9: 0.3 | AI9: 0.3 | AJ9: 0.3 | AK9: 0.3 | AL9: 0.3 | AM9: 0.3 | AN9: 0.3 | AO9: 0.3 | AP9: 0.3 | AQ9: 0.3 | AR9: 0.3 | AS9: 0.3 | AT9: 0.3 | AU9: 0.3 | AV9: 0.3 | AW9: 0.3 | AX9: 0.3 | AY9: 0.3 | AZ9: 0.3 | BA9: 0.3 | BB9: 0.3 | BC9: 0.3 | BD9: 0.3 | BE9: 0.3 | BF9: 0.3 | BG9: 0.3 | BH9: 0.3 | BI9: 0.3 | BJ9: 0.3 | BK9: 0.3 | BL9: 0.3 | BM9: 0.3 | BN9: 0.3 | BO9: 0.3 | BP9: 0.3 | BQ9: 0.3 | BR9: 0.3
C10: 定常浸透率 | D10: 保証は見直し・解約あり。推定 | F10: 0.6 | G10: 0.6 | H10: 0.6 | I10: 0.6 | J10: 0.6 | K10: 0.6 | L10: 0.6 | M10: 0.6 | N10: 0.6 | O10: 0.6 | P10: 0.6 | Q10: 0.6 | R10: 0.6 | S10: 0.6 | T10: 0.6 | U10: 0.6 | V10: 0.6 | W10: 0.6 | X10: 0.6 | Y10: 0.6 | Z10: 0.6 | AA10: 0.6 | AB10: 0.6 | AC10: 0.6 | AD10: 0.6 | AE10: 0.6 | AF10: 0.6 | AG10: 0.6 | AH10: 0.6 | AI10: 0.6 | AJ10: 0.6 | AK10: 0.6 | AL10: 0.6 | AM10: 0.6 | AN10: 0.6 | AO10: 0.6 | AP10: 0.6 | AQ10: 0.6 | AR10: 0.6 | AS10: 0.6 | AT10: 0.6 | AU10: 0.6 | AV10: 0.6 | AW10: 0.6 | AX10: 0.6 | AY10: 0.6 | AZ10: 0.6 | BA10: 0.6 | BB10: 0.6 | BC10: 0.6 | BD10: 0.6 | BE10: 0.6 | BF10: 0.6 | BG10: 0.6 | BH10: 0.6 | BI10: 0.6 | BJ10: 0.6 | BK10: 0.6 | BL10: 0.6 | BM10: 0.6 | BN10: 0.6 | BO10: 0.6 | BP10: 0.6 | BQ10: 0.6 | BR10: 0.6
C11: １税理士 / 受注数（定常）（累計獲得数・解約前） | F11: =PRODUCT(F6:F10) -> 0 | G11: =PRODUCT(G6:G10) -> 2.52 | H11: =PRODUCT(H6:H10) -> 13.86 | I11: =PRODUCT(I6:I10) -> 25.2 | J11: =PRODUCT(J6:J10) -> 35.28 | K11: =PRODUCT(K6:K10) -> 47.88 | L11: =PRODUCT(L6:L10) -> 60.48 | M11: =PRODUCT(M6:M10) -> 73.08 | ... BR11: =PRODUCT(BR6:BR10) -> 1433.88
